Workbook

Sheet MARKUP
A1: System | B1: Discount | C1: Markup | Z1: (cumulative)
A2: Window Profile | B2: -0.65 | C2: 1.08 | Z2: =(1+B2)*(1+C2)-1 -> -27.20%
A3: Window Hardware | B3: -0.65 | C3: 1.08 | Z3: =(1+B3)*(1+C3)-1 -> -27.20%
A4: Bifold Profile | B4: -0.65 | C4: 0.9 | Z4: =(1+B4)*(1+C4)-1 -> -33.50%
A5: Bifold Hardware | B5: -0.55 | C5: 0.9 | Z5: =(1+B5)*(1+C5)-1 -> -14.50%
A6: Slider Profile | B6: -0.65 | C6: 1.15 | Z6: =(1+B6)*(1+C6)-1 -> -24.75%
A7: Slider Hardware | B7: -0.65 | C7: 1.15 | Z7: =(1+B7)*(1+C7)-1 -> -24.75%
A8: Internal Bifold | B8: -0.55 | C8: 0.9 | Z8: =(1+B8)*(1+C8)-1 -> -14.50%
A9: Internal Slider | B9: -0.55 | C9: 0.9 | Z9: =(1+B9)*(1+C9)-1 -> -14.50%
A10: Composite | B10: -0.55 | C10: 0.9 | Z10: =(1+B10)*(1+C10)-1 -> -14.50%
A11: Ultra Slider Profile | B11: -0.7 | C11: 1.15
A12: Ultra Slider Hardware | B12: -0.7 | C12: 1.15

Sheet bifold
A1: type | B1: values | D1: before discount | F1: markup
A2: bifold_leaf | B2: 395
A3: french_fixed | B3: 0
A4: single_fixed | B4: 100
A5: bifold_cill_90 | B5: =D5*(1+F5) -> 17.29 | D5: 26 | F5: =MARKUP!$Z$4 -> -33.50%
A6: bifold_cill_150 | B6: =D6*(1+F6) -> 26.6 | D6: 40 | F6: =MARKUP!$Z$4 -> -33.50%
A7: bifold_cill_180 | B7: =D7*(1+F7) -> 28.595 | D7: 43 | F7: =MARKUP!$Z$4 -> -33.50%
A8: bifold_cill_230 | B8: =D8*(1+F8) -> 32.585 | D8: 49 | F8: =MARKUP!$Z$4 -> -33.50%
A9: bifold_handle_grey | B9: 0 | D9: 18 | F9: =MARKUP!$Z$5 -> -14.50%
A10: bifold_handle_black | B10: 0 | D10: 18 | F10: =MARKUP!$Z$5 -> -14.50%
A11: bifold_handle_white | B11: 0 | D11: 18 | F11: =MARKUP!$Z$5 -> -14.50%
A12: bifold_handle_chrome | B12: =D12*(1+F12) -> 30.78 | D12: 36 | F12: =MARKUP!$Z$5 -> -14.50%
A13: bifold_handle_satin | B13: =D13*(1+F13) -> 36.765 | D13: 43 | F13: =MARKUP!$Z$5 -> -14.50%
A14: bifold_handle_gold | B14: =D14*(1+F14) -> 36.765 | D14: 43 | F14: =MARKUP!$Z$5 -> -14.50%
A15: bifold_handle_rose_gold | B15: =D15*(1+F15) -> 36.765 | D15: 43 | F15: =MARKUP!$Z$5 -> -14.50%
A16: bifold_handle_dual | B16: =D16*(1+F16) -> 36.765 | D16: 43 | F16: =MARKUP!$Z$5 -> -14.50%
A17: bifold_handle_coastal_stainless_steel | B17: =D17*(1+F17) -> 94.05 | D17: 110 | F17: =MARKUP!$Z$5 -> -14.50%
A18: bifold_floating_corner | B18: 75
A19: bifold_adjustable_jamb | B19: 100
A20: bifold_toe_heel_adjuster | B20: 0
A21: bifold_trickle_vent | B21: 15
A22: bifold_addon_20 | B22: =D22*(1+F22) -> 16.625 | D22: 25 | F22: =MARKUP!$Z$4 -> -33.50%
A23: bifold_addon_38 | B23: =D23*(1+F23) -> 21.945 | D23: 33 | F23: =MARKUP!$Z$4 -> -33.50%
A24: bifold_ral | B24: 250
A25: bifold_second_ral | B25: 0
A26: astragal_bar_fixed | B26: 50
A27: transom_bar_fixed | B27: 50
A28: blinds | B28: 200
A29: sidelight_frame | B29: 30
A30: sidelight_frame_fixed | B30: 0
A31: ult_bifold_low_e_tuff_per_pane | B31: 55 | C31: comes from options tab partsStrategy

Sheet patio
A1: type | B1: values | D1: before discount | F1: markup
A2: patio_cill_230 | B2: =D2*(1+F2) -> 42.5915 | D2: 56.6 | F2: =MARKUP!$Z$6 -> -24.75%
A3: patio_cill_250 | B3: =D3*(1+F3) -> 48.724375 | D3: 64.75 | F3: =MARKUP!$Z$6 -> -24.75%
A4: patio_lift_slide_uplift | B4: 200 | F4: =MARKUP!$Z$7 -> -24.75%
A5: patio_trickle_vent | B5: 40 | F5: =MARKUP!$Z$7 -> -24.75%
A6: patio_additional_slide | B6: =D6*(1+F6) -> 0 | F6: =MARKUP!$Z$7 -> -24.75%
A7: patio_monorail_fixed | B7: =D7*(1+F7) -> 0 | F7: =MARKUP!$Z$7 -> -24.75%
A8: patio_addon_35 | B8: =D8*(1+F8) -> 30.1 | D8: 40 | F8: =MARKUP!$Z$6 -> -24.75%
A9: patio_handle_gold | B9: =D9*(1+F9) -> 53.4275 | D9: 71 | F9: =MARKUP!$Z$7 -> -24.75%
A10: patio_handle_smoke_chrome | B10: =D10*(1+F10) -> 63.21 | D10: 84 | F10: =MARKUP!$Z$7 -> -24.75%
A11: patio_handle_satin | B11: =D11*(1+F11) -> 45.9025 | D11: 61 | F11: =MARKUP!$Z$7 -> -24.75%
A12: patio_handle_black | B12: =D12*(1+F12) -> 25.585 | D12: 34 | F12: =MARKUP!$Z$7 -> -24.75%
A13: patio_handle_white | B13: =D13*(1+F13) -> 25.585 | D13: 34 | F13: =MARKUP!$Z$7 -> -24.75%
A14: patio_handle_chrome | B14: =D14*(1+F14) -> 52.675 | C14: (this is Polished Chrome) | D14: 70 | F14: =MARKUP!$Z$7 -> -24.75%
A15: patio_handle_coastal_steel | B15: =D15*(1+F15) -> 167.055 | D15: 222 | F15: =MARKUP!$Z$7 -> -24.75%
A16: patio_handle_coastal_black | B16: =D16*(1+F16) -> 312.2875 | D16: 415 | F16: =MARKUP!$Z$7 -> -24.75%
A17: patio_handle_l&s_white | B17: =D17*(1+F17) -> 79.765 | D17: 106 | F17: =MARKUP!$Z$7 -> -24.75%
A18: patio_handle_l&s_black | B18: =D18*(1+F18) -> 79.765 | D18: 106 | F18: =MARKUP!$Z$7 -> -24.75%
A19: patio_ral | B19: 300
A20: patio_second_ral | B20: 0

Sheet cortizo_patio
A1: type | B1: values
A2: cortizo_patio_cill_180 | B2: 37.639
A3: cortizo_patio_cill_230 | B3: =patio!B2 -> 42.5915
A4: cortizo_patio_cill_250 | B4: =patio!B3 -> 48.724375
A5: cortizo_patio_trickle_vent | B5: =patio!B5 -> 40
A6: cortizo_patio_additional_slide | B6: =patio!B6 -> 0
A7: cortizo_patio_addon_35 | B7: =patio!B8 -> 30.1
A8: cortizo_patio_ral | B8: =patio!B19 -> 300
A9: cortizo_patio_second_ral | B9: =patio!B20 -> 0
A10: cortizo_patio_handle_grey | B10: =B11 -> 25.585
A11: cortizo_patio_handle_black | B11: =patio!B12 -> 25.585
A12: cortizo_patio_handle_white | B12: =patio!B13 -> 25.585

Sheet window
A1: type | B1: values | D1: before discount | F1: markup
A2: window_sash_per_m | B2: =D2*(1+F2) -> 22.48792 | D2: 30.89 | F2: =MARKUP!$Z$2 -> -27.20%
A3: window_sash_fixed | B3: =D3*(1+F3) -> 12.8856 | D3: 17.7 | F3: =MARKUP!$Z$3 -> -27.20%
A4: window_opener_fixed | B4: =D4*(1+F4) -> 38.78784 | D4: 53.28 | F4: =MARKUP!$Z$3 -> -27.20%
A5: window_bar_per_m | B5: =D5*(1+F5) -> 22.48792 | D5: 30.89 | F5: =MARKUP!$Z$2 -> -27.20%
A6: window_frame_per_m | B6: =D6*(1+F6) -> 23.90752 | D6: 32.84 | F6: =MARKUP!$Z$2 -> -27.20%
A7: window_frame_fixed | B7: =D7*(1+F7) -> 9.62416 | D7: 13.22 | F7: =MARKUP!$Z$3 -> -27.20%
A8: window_bar_fixed | B8: =D8*(1+F8) -> 2.3296 | D8: 3.2 | F8: =MARKUP!$Z$2 -> -27.20%
A9: window_bead_per_m | B9: =D9*(1+F9) -> 5.64928 | D9: 7.76 | F9: =MARKUP!$Z$2 -> -27.20%
A10: window_sash_tilt_per_m | B10: =D10*(1+F10) -> 24.0604 | D10: 33.05 | F10: =MARKUP!$Z$2 -> -27.20%
A11: window_sash_tilt_fixed | B11: =D11*(1+F11) -> 12.8856 | D11: 17.7 | F11: =MARKUP!$Z$3 -> -27.20%
A12: window_opener_tilt_fixed | B12: =D12*(1+F12) -> 158.62392 | D12: 217.89 | F12: =MARKUP!$Z$3 -> -27.20%
A13: window_bar_tilt_per_m | B13: =D13*(1+F13) -> 22.48792 | D13: 30.89 | F13: =MARKUP!$Z$2 -> -27.20%
A14: window_frame_tilt_per_m | B14: =D14*(1+F14) -> 24.47536 | D14: 33.62 | F14: =MARKUP!$Z$2 -> -27.20%
A15: window_sash_flush_per_m | B15: =D15*(1+F15) -> 22.48792 | D15: 30.89 | F15: =MARKUP!$Z$2 -> -27.20%
A16: window_sash_flush_fixed | B16: =D16*(1+F16) -> 12.8856 | D16: 17.7 | F16: =MARKUP!$Z$3 -> -27.20%
A17: window_opener_flush_fixed | B17: =D17*(1+F17) -> 38.78784 | D17: 53.28 | F17: =MARKUP!$Z$3 -> -27.20%
A18: window_bar_flush_per_m | B18: =D18*(1+F18) -> 22.48792 | D18: 30.89 | F18: =MARKUP!$Z$2 -> -27.20%
A19: window_frame_flush_per_m | B19: =D19*(1+F19) -> 23.90752 | D19: 32.84 | F19: =MARKUP!$Z$2 -> -27.20%
A20: window_cill_90 | B20: =D20*(1+F20) -> 16.4892 | D20: 22.65 | F20: =MARKUP!$Z$2 -> -27.20%
A21: window_cill_150 | B21: =D21*(1+F21) -> 22.83008 | D21: 31.36 | F21: =MARKUP!$Z$2 -> -27.20%
A22: window_cill_180 | B22: =D22*(1+F22) -> 26.52832 | D22: 36.44 | F22: =MARKUP!$Z$2 -> -27.20%
A23: window_cill_230 | B23: =D23*(1+F23) -> 31.10744 | D23: 42.73 | F23: =MARKUP!$Z$2 -> -27.20%
A24: window_addon_20 | B24: =D24*(1+F24) -> 13.45344 | D24: 18.48 | F24: =MARKUP!$Z$2 -> -27.20%
A25: window_addon_38 | B25: =D25*(1+F25) -> 15.88496 | D25: 21.82 | F25: =MARKUP!$Z$2 -> -27.20%
A26: window_hooded_vent | B26: =D26*(1+F26) -> 19.19008 | D26: 26.36 | F26: =MARKUP!$Z$2 -> -27.20%
A27: window_trickle_vent | B27: 15
A28: window_handle_black_casement | B28: =D28*(1+F28) -> 4.53544 | D28: 6.23 | F28: =MARKUP!$Z$3 -> -27.20%
A29: window_handle_chrome_casement | B29: =D29*(1+F29) -> 9.07816 | D29: 12.47 | F29: =MARKUP!$Z$3 -> -27.20%
A30: window_handle_gold_casement | B30: =D30*(1+F30) -> 9.07816 | D30: 12.47 | F30: =MARKUP!$Z$3 -> -27.20%
A31: window_handle_steel_casement | B31: =D31*(1+F31) -> 9.07816 | D31: 12.47 | F31: =MARKUP!$Z$3 -> -27.20%
A32: window_handle_white_casement | B32: =D32*(1+F32) -> 4.53544 | D32: 6.23 | F32: =MARKUP!$Z$3 -> -27.20%
A33: window_handle_coastal_steel_casement | B33: =D33*(1+F33) -> 75.166 | D33: 103.25 | F33: =MARKUP!$Z$3 -> -27.20%
A34: window_handle_coastal_black_casement | B34: =D34*(1+F34) -> 63.52528 | D34: 87.26 | F34: =MARKUP!$Z$3 -> -27.20%
A35: window_handle_black_tilt_turn | B35: =D35*(1+F35) -> 8.4084 | D35: 11.55 | F35: =MARKUP!$Z$3 -> -27.20%
A36: window_handle_chrome_tilt_turn | B36: =D36*(1+F36) -> 15.82672 | D36: 21.74 | F36: =MARKUP!$Z$3 -> -27.20%
A37: window_handle_gold_tilt_turn | B37: =D37*(1+F37) -> 15.82672 | D37: 21.74 | F37: =MARKUP!$Z$3 -> -27.20%
A38: window_handle_steel_tilt_turn | B38: =D38*(1+F38) -> 15.82672 | D38: 21.74 | F38: =MARKUP!$Z$3 -> -27.20%
A39: window_handle_white_tilt_turn | B39: =D39*(1+F39) -> 8.4084 | D39: 11.55 | F39: =MARKUP!$Z$3 -> -27.20%
... A41: window_handle_coastal_black_tilt_turn | B41: =D41*(1+F41) -> 62.14936 | D41: 85.37 | F41: =MARKUP!$Z$3 -> -27.20%
A42: window_french | B42: =D42*(1+F42) -> 18.2 | D42: 25 | F42: =MARKUP!$Z$2 -> -27.20%
A43: window_ral | B43: 200
A44: window_second_ral | B44: 0
A45: bay_pole_90_per_m | B45: 30
A46: bay_pole_angled_per_m | B46: 45
A47: window_hinge_egress | B47: 6

Sheet glass
A1: type | B1: values
A2: glass_low_e | B2: 49
A3: glass_low_e_oversized | B3: 20
A4: glass_low_e_tuff | B4: 49
A5: glass_low_e_tuff_oversized | B5: 20
A6: glass_low_e_one | B6: 56
A7: glass_low_e_one_oversized | B7: 20
A8: glass_low_e_one_tuff | B8: 56
A9: glass_low_e_one_tuff_oversized | B9: 20
A10: glass_laminated_6.8 | B10: 82
A11: glass_laminated_6.8_oversized | B11: 20
A12: glass_laminated_6.8_tuff | B12: 82
A13: glass_laminated_6.8_tuff_oversized | B13: 20
... A43: glass_pattern_SAT_tuff | B43: 30

Sheet upvc_window
A1: type | B1: values
A2: upvc_window_sash_per_m | B2: 6
A3: upvc_window_sash_fixed | B3: 4
A4: upvc_window_opener_fixed | B4: 8.75
A5: upvc_window_frame_per_m | B5: 4.75
A6: upvc_window_bar_per_m | B6: 5.5
A7: upvc_window_bead_per_m | B7: 1
A8: upvc_window_frame_fixed | B8: 2.5
A9: upvc_cill_standard_85 | B9: 20
A10: upvc_cill_standard_125 | B10: 25
A11: upvc_cill_standard_150 | B11: 30
A12: upvc_cill_standard_180 | B12: 35
A13: upvc_cill_standard_225 | B13: 40

Sheet values
A1: type | B1: values
A2: upvc_door_single | B2: 200
A3: upvc_door_french | B3: 400

Sheet composite
A1: type | B1: values | E1: before discount
A2: AbercornSlab | B2: {=E2:E495*(1+MARKUP!$Z$10)} -> 664.27 | E2: 776.92308
A3: AbercornUltimateSlab | B3: 689.20892 | E3: 806.09231
A4: CornwallSlab | B4: 585.74077 | E4: 685.07692
A5: CambridgeSlab | B5: 533.07277 | E5: 623.47692
A6: CornwallUltimateSlab | B6: 606.06346 | E6: 708.84615
A7: WhitmoreSolidSlab | B7: 533.07277 | E7: 623.47692
A8: NorfolkSolidSlab | B8: 532.152 | E8: 622.4
A9: AstonSolidSlab | B9: 533.07277 | E9: 623.47692
A10: MiddletonSolidSlab | B10: 533.07277 | E10: 623.47692
A11: MiddletonGlazed4Slab | B11: 631.93708 | E11: 739.10769
A12: WinslowSolidSlab | B12: 533.07277 | E12: 623.47692
A13: Winslow3Slab | B13: 658.73146 | E13: 770.44615
A14: ElmhurstSlab | B14: 606.06346 | E14: 708.84615
... A31: OpenOut | B31: 32.332154 | E31: 37.815385
A32: Cill1 | B32: 9.6286154 | C32: pm | E32: 11.261538
A33: Cill2 | B33: 15.416308 | C33: pm | E33: 18.030769
A34: Cill3 | B34: 17.586692 | C34: pm | E34: 20.569231
A35: AM3Threshold | B35: 32.174308 | E35: 37.630769
A36: AM370Threshold | B36: 27.688846 | E36: 32.384615
A37: Addons1 | B37: 5.7482308 | C37: pm | E37: 6.7230769
A38: Addons2 | B38: 14.153538 | C38: pm | E38: 16.553846
A39: Addons3 | B39: 16.258154 | C39: pm | E39: 19.015385
A40: StandardAstonGlass | B40: 21.296077 | E40: 24.907692
A41: StandardBramptonGlass | B41: 10.641462 | E41: 12.446154
A42: StandardMiddleton4Glass | B42: 42.605308 | E42: 49.830769
A43: StandardWinslow3Glass | B43: 34.620923 | E43: 40.492308
A44: StandardElmhurstGlass | B44: 21.296077 | E44: 24.907692
A45: StandardHattonGlass | B45: 27.531 | E45: 32.2
A46: StandardAxwellGlass | B46: 12.075231 | E46: 14.123077
A47: StandardBuxtonGlass | B47: 21.743308 | E47: 25.430769
A48: StandardGraftonGlass | B48: 27.162692 | E48: 31.769231
A49: StandardWalcotGlass | B49: 27.965077 | E49: 32.707692
A50: StandardRutlandGlass | B50: 12.338308 | E50: 14.430769
A51: StandardSomersetGlass | B51: 10.641462 | E51: 12.446154
... A462: StandardCornwallGlass | B462: 10.641462 | E462: 12.446154
A463: composite_sidelight_bar_g1 | B463: 16.39035 | E463: 19.17
A464: composite_sidelight_bar_g2 | B464: 24.111 | E464: 28.20
A465: composite_sidelight_bar_g3 | B465: 27.7533 | E465: 32.46
A466: composite_sidelight_coupler_g1 | B466: 25.1541 | E466: 29.42
A467: composite_sidelight_coupler_g2 | B467: 30.951 | E467: 36.20
A468: composite_sidelight_coupler_g3 | B468: 14.4324 | E468: 16.88
A469: composite_sidelight_frame_1600_g1 | B469: 14.35545 | E469: 16.79
A470: composite_sidelight_frame_1600_g2 | B470: 27.5481 | E470: 32.22
A471: composite_sidelight_frame_1600_g3 | B471: 31.7034 | E471: 37.08
A472: composite_sidelight_frame_2600_g1 | B472: 23.3244 | E472: 27.28
A473: composite_sidelight_frame_2600_g2 | B473: 44.77635 | E473: 52.37
A474: composite_sidelight_frame_2600_g3 | B474: 51.5223 | E474: 60.26
... A495: composite_sidelight_frame_max_g3 | B495: 170.42715 | E495: 199.33
A496: composite_sidelight_glass_clear_toughened | B496: =E496 -> 54.46 | E496: 54.46 | F496: non-discountable
A497: composite_sidelight_glass_obscure_toughened | B497: =E497 -> 63.54 | E497: 63.54 | F497: non-discountable
A498: composite_sidelight_glass_clear_laminated | B498: =E498 -> 66.56 | E498: 66.56 | F498: non-discountable
A499: composite_sidelight_glass_obscure_laminated | B499: =E499 -> 92.28 | E499: 92.28 | F499: non-discountable
A500: composite_sidelight_glass_design | B500: =E500 -> 64.84 | E500: 64.84 | F500: non-discountable

Sheet price_files
A1: type | B1: pricefile | C1: trade/trade/retail
A2: name | B2: id | C2: delivery charge | D2: all markup | E2: aluminium markup | F2: upvc markup | G2: glass markup | H2: composite markup | I2: overrides
A3: Trade | B3: trade | C3: No | I3: =IFERROR(__xludf.DUMMYFUNCTION("IFERROR(TEXTJOIN(""/"", TRUE, FILTER('(price file overrides)'!$B$2:$B995 & ""="" & '(price file overrides)'!$C$2:$C995, '(price file overrides)'!$A$2:$A995 = B3)), """") "),"")
A4: Partner | B4: partner | C4: No | D4: -10 | I4: =IFERROR(__xludf.DUMMYFUNCTION("IFERROR(TEXTJOIN(""/"", TRUE, FILTER('(price file overrides)'!$B$2:$B995 & ""="" & '(price file overrides)'!$C$2:$C995, '(price file overrides)'!$A$2:$A995 = B4)), """") "),"")
A5: Retail | B5: retail | C5: No | D5: 10 | I5: =IFERROR(__xludf.DUMMYFUNCTION("IFERROR(TEXTJOIN(""/"", TRUE, FILTER('(price file overrides)'!$B$2:$B995 & ""="" & '(price file overrides)'!$C$2:$C995, '(price file overrides)'!$A$2:$A995 = B5)), """") "),"")

Sheet (price file overrides)
A1: price file | B1: pricing key | C1: value

Sheet (patio_costs)
C2: patio_2_
B3: 1500 | C3: 1600 | D3: 1700 | E3: 1800 | F3: 1900 | G3: 2000 | H3: 2100 | I3: 2200 | J3: 2300 | K3: 2400 | L3: 2500 | M3: 2600 | N3: 2700 | O3: 2800 | P3: 2900 | Q3: 3000 | R3: 3100 | S3: 3200 | T3: 3300 | U3: 3400 | V3: 3500 | W3: 3600 | X3: 3700 | Y3: 3800 | Z3: 3900 | AA3: 4000 | AB3: 4100 | AC3: 4200 | AD3: 4300 | AE3: 4400 | AF3: 4500 | AG3: 4600 | AH3: 4700 | AI3: 4800 | AJ3: 4900 | AK3: 5000
A4: 2000 | B4: 1476.0865 | C4: 1503.9421 | D4: 1531.7977 | E4: 1559.6533 | F4: 1587.5089 | G4: 1615.3645 | H4: 1643.2201 | I4: 1671.0756 | J4: 1699.6378 | K4: 1727.4933 | L4: 1755.3489 | M4: 1783.2045 | N4: 1811.0601 | O4: 1838.9157 | P4: 1866.7609 | Q4: 1894.6165 | R4: 1922.4721 | S4: 1951.0342 | T4: 1978.8898 | U4: 2006.7454 | V4: 2054.903 | W4: 2082.7586 | X4: 2110.6142 | Y4: 2138.4698 | Z4: 2166.3254 | AA4: 2194.181 | AB4: 2222.7431 | AC4: 2250.5987 | AD4: 2278.4543 | AE4: 2306.2995 | AF4: 2334.1551 | AG4: 2362.0106 | AH4: 2389.8662 | AI4: 2417.7218 | AJ4: 2445.5774 | AK4: 2474.1395
A5: 2100 | B5: 1514.1659 | C5: 1542.0215 | D5: 1569.877 | E5: 1597.7326 | F5: 1625.5882 | G5: 1653.4438 | H5: 1681.2994 | I5: 1709.155 | J5: 1737.7171 | K5: 1765.5727 | L5: 1793.4283 | M5: 1821.2839 | N5: 1849.1291 | O5: 1876.9847 | P5: 1904.8403 | Q5: 1932.6959 | R5: 1960.5514 | S5: 1989.1135 | T5: 2037.2712 | U5: 2065.1268 | V5: 2092.9824 | W5: 2120.838 | X5: 2148.6936 | Y5: 2176.5491 | Z5: 2204.4047 | AA5: 2232.2603 | AB5: 2260.8224 | AC5: 2288.6676 | AD5: 2316.5232 | AE5: 2344.3788 | AF5: 2372.2344 | AG5: 2400.09 | AH5: 2427.9456 | AI5: 2455.8012 | AJ5: 2483.6568 | AK5: 2512.2189
A6: 2200 | B6: 1552.2452 | C6: 1580.1008 | D6: 1607.9564 | E6: 1635.812 | F6: 1663.6676 | G6: 1691.5232 | H6: 1719.3788 | I6: 1747.2343 | J6: 1775.7965 | K6: 1803.652 | L6: 1831.4972 | M6: 1859.3528 | N6: 1887.2084 | O6: 1915.064 | P6: 1942.9196 | Q6: 1970.7752 | R6: 1998.6308 | S6: 2047.495 | T6: 2075.3506 | U6: 2103.2061 | V6: 2131.0617 | W6: 2158.9173 | X6: 2186.7729 | Y6: 2214.6285 | Z6: 2242.4841 | AA6: 2270.3293 | AB6: 2298.8914 | AC6: 2326.747 | AD6: 2354.6026 | AE6: 2382.4582 | AF6: 2410.3138 | AG6: 2438.1694 | AH6: 2466.0249 | AI6: 2493.8805 | AJ6: 2521.7361 | AK6: 2550.2982
A7: 2300 | B7: 1590.3246 | C7: 1618.1802 | D7: 1646.0357 | E7: 1673.8913 | F7: 1701.7469 | G7: 1729.6025 | H7: 1757.4581 | I7: 1785.3137 | J7: 1813.8654 | K7: 1841.721 | L7: 1869.5766 | M7: 1897.4322 | N7: 1925.2878 | O7: 1953.1434 | P7: 1980.999 | Q7: 2029.1566 | R7: 2057.0122 | S7: 2085.5743 | T7: 2113.4299 | U7: 2141.2855 | V7: 2169.1411 | W7: 2196.9967 | X7: 2224.8523 | Y7: 2252.6975 | Z7: 2280.553 | AA7: 2308.4086 | AB7: 2336.9707 | AC7: 2364.8263 | AD7: 2392.6819 | AE7: 2420.5375 | AF7: 2448.3931 | AG7: 2476.2487 | AH7: 2504.1043 | AI7: 2531.9599 | AJ7: 2559.8155 | AK7: 2588.3776
A8: 2400 | B8: 1628.4039 | C8: 1656.2595 | D8: 1684.1151 | E8: 1711.9707 | F8: 1739.8263 | G8: 1767.6819 | H8: 1795.5271 | I8: 1823.3827 | J8: 1851.9448 | K8: 1879.8004 | L8: 1907.6559 | M8: 1935.5115 | N8: 1963.3671 | O8: 1991.2227 | P8: 2039.3804 | Q8: 2067.236 | R8: 2095.0916 | S8: 2123.6537 | T8: 2151.5093 | U8: 2179.3648 | V8: 2207.21 | W8: 2235.0656 | X8: 2262.9212 | Y8: 2290.7768 | Z8: 2318.6324 | AA8: 2346.488 | AB8: 2375.0501 | AC8: 2402.9057 | AD8: 2430.7613 | AE8: 2458.6169 | AF8: 2486.4725 | AG8: 2514.328 | AH8: 2542.1836 | AI8: 2570.0392 | AJ8: 2597.8948 | AK8: 2626.4465
A9: 2500 | B9: 1666.4833 | C9: 1694.3389 | D9: 1722.1944 | E9: 1750.0396 | F9: 1777.8952 | G9: 1805.7508 | H9: 1833.6064 | I9: 1861.462 | J9: 1890.0241 | K9: 1917.8797 | L9: 1945.7353 | M9: 1973.5909 | N9: 2001.4465 | O9: 2049.6041 | P9: 2077.4597 | Q9: 2105.3153 | R9: 2133.1709 | S9: 2161.733 | T9: 2189.5886 | U9: 2217.4338 | V9: 2245.2894 | W9: 2273.145 | X9: 2301.0006 | Y9: 2328.8562 | Z9: 2356.7117 | AA9: 2384.5673 | AB9: 2413.1294 | AC9: 2440.985 | AD9: 2468.8406 | AE9: 2496.6962 | AF9: 2524.5518 | AG9: 2552.4074 | AH9: 2580.263 | AI9: 2608.1186 | AJ9: 2635.9638 | AK9: 2664.5259
A10: 2600 | B10: 1704.5626 | C10: 1732.4182 | D10: 1760.2634 | E10: 1788.119 | F10: 1815.9746 | G10: 1843.8302 | H10: 1871.6858 | I10: 1899.5414 | J10: 1928.1035 | K10: 1955.9591 | L10: 1983.8146 | M10: 2011.6702 | N10: 2059.8279 | O10: 2087.6835 | P10: 2115.5391 | Q10: 2143.3947 | R10: 2171.2399 | S10: 2199.802 | T10: 2227.6576 | U10: 2255.5131 | V10: 2283.3687 | W10: 2311.2243 | X10: 2339.0799 | Y10: 2366.9355 | Z10: 2394.7911 | AA10: 2422.6467 | AB10: 2451.2088 | AC10: 2479.0644 | AD10: 2506.92 | AE10: 2534.7756 | AF10: 2562.6312 | AG10: 2590.4868 | AH10: 2618.3319 | AI10: 2646.1875 | AJ10: 2674.0431 | AK10: 2702.6052
A11: 2700 | B11: 1742.6316 | C11: 1770.4872 | D11: 1798.3428 | E11: 1826.1983 | F11: 1854.0539 | G11: 1881.9095 | H11: 1909.7651 | I11: 1937.6207 | J11: 1966.1828 | K11: 1994.0384 | L11: 2021.894 | M11: 2070.0516 | N11: 2097.9072 | O11: 2125.7628 | P11: 2153.608 | Q11: 2181.4636 | R11: 2209.3192 | S11: 2237.8813 | T11: 2265.7369 | U11: 2293.5925 | V11: 2321.4481 | W11: 2349.3037 | X11: 2377.1593 | Y11: 2405.0149 | Z11: 2432.8704 | AA11: 2460.726 | AB11: 2489.2881 | AC11: 2517.1437 | AD11: 2544.9993 | AE11: 2572.8445 | AF11: 2600.7001 | AG11: 2628.5557 | AH11: 2656.4113 | AI11: 2684.2669 | AJ11: 2712.1225 | AK11: 2740.6846
C13: patio_3_
B14: 2250 | C14: 2350 | D14: 2450 | E14: 2550 | F14: 2650 | G14: 2750 | H14: 2850 | I14: 2950 | J14: 3050 | K14: 3150 | L14: 3250 | M14: 3350 | N14: 3450 | O14: 3550 | P14: 3650 | Q14: 3750 | R14: 3850 | S14: 3950 | T14: 4050 | U14: 4150 | V14: 4250 | W14: 4350 | X14: 4450 | Y14: 4550 | Z14: 4650 | AA14: 4750 | AB14: 4850 | AC14: 4950 | AD14: 5050 | AE14: 5150 | AF14: 5250 | AG14: 5350 | AH14: 5450 | AI14: 5550 | AJ14: 5650 | AK14: 5750 | AL14: 5850 | AM14: 5950 | AN14: 6050 | AO14: 6150 | AP14: 6250 | AQ14: 6350 | AR14: 6450 | AS14: 6550 | AT14: 6650 | AU14: 6750 | AV14: 6850 | AW14: 6950 | AX14: 7050 | AY14: 7150 | AZ14: 7250 | BA14: 7350 | BB14: 7450 | BC14: 7500
A15: 2000 | B15: 2190.212 | C15: 2223.9795 | D15: 2257.747 | E15: 2291.5145 | F15: 2325.282 | G15: 2359.0495 | H15: 2392.817 | I15: 2426.5845 | J15: 2460.3416 | K15: 2494.1091 | L15: 2528.9364 | M15: 2562.7039 | N15: 2596.4714 | O15: 2630.2389 | P15: 2664.0064 | Q15: 2697.7635 | R15: 2731.531 | S15: 2765.2985 | T15: 2799.066 | U15: 2832.8335 | V15: 2866.601 | W15: 2900.3685 | X15: 2934.1256 | Y15: 2967.8931 | Z15: 3002.7204 | AA15: 3036.4879 | AB15: 3070.2554 | AC15: 3104.0229 | AD15: 3137.7904 | AE15: 3212.162 | AF15: 3245.9191 | AG15: 3279.6866 | AH15: 3313.4541 | AI15: 3347.2216 | AJ15: 3380.9891 | AK15: 3414.7566 | AL15: 3448.5241 | AM15: 3483.341 | AN15: 3517.1085 | AO15: 3550.876 | AP15: 3584.6435 | AQ15: 3618.411 | AR15: 3652.1785 | AS15: 3685.946 | AT15: 3719.7031 | AU15: 3753.4706 | AV15: 3787.2381 | AW15: 3821.0056 | AX15: 3854.7731 | AY15: 3888.5406 | AZ15: 3922.3081 | BA15: 3957.1354 | BB15: 3990.8925 | BC15: 4007.7763
A16: 2100 | B16: 2243.4919 | C16: 2277.2594 | D16: 2311.0269 | E16: 2344.7944 | F16: 2378.5619 | G16: 2412.3294 | H16: 2446.0865 | I16: 2479.854 | J16: 2513.6215 | K16: 2547.389 | L16: 2582.2163 | M16: 2615.9838 | N16: 2649.7513 | O16: 2683.5084 | P16: 2717.2759 | Q16: 2751.0434 | R16: 2784.8109 | S16: 2818.5784 | T16: 2852.3459 | U16: 2886.1134 | V16: 2919.8705 | W16: 2953.638 | X16: 2987.4055 | Y16: 3021.173 | Z16: 3056.0003 | AA16: 3089.7678 | AB16: 3143.8374 | AC16: 3197.8965 | AD16: 3231.664 | AE16: 3265.4315 | AF16: 3299.199 | AG16: 3332.9665 | AH16: 3366.734 | AI16: 3400.5015 | AJ16: 3434.269 | AK16: 3468.0261 | AL16: 3501.7936 | AM16: 3536.6209 | AN16: 3570.3884 | AO16: 3604.1559 | AP16: 3637.9234 | AQ16: 3671.6909 | AR16: 3705.448 | AS16: 3739.2155 | AT16: 3772.983 | AU16: 3806.7505 | AV16: 3840.518 | AW16: 3874.2855 | AX16: 3908.053 | AY16: 3941.8101 | AZ16: 3975.5776 | BA16: 4010.4049 | BB16: 4044.1724 | BC16: 4061.0562
A17: 2200 | B17: 2296.7718 | C17: 2330.5393 | D17: 2364.3068 | E17: 2398.064 | F17: 2431.8315 | G17: 2465.599 | H17: 2499.3664 | I17: 2533.1339 | J17: 2566.9014 | K17: 2600.669 | L17: 2635.4858 | M17: 2669.2533 | N17: 2703.0208 | O17: 2736.7883 | P17: 2770.5558 | Q17: 2804.3233 | R17: 2838.0908 | S17: 2871.8479 | T17: 2905.6154 | U17: 2939.383 | V17: 2973.1505 | W17: 3006.918 | X17: 3040.6854 | Y17: 3074.4529 | Z17: 3149.8843 | AA17: 3183.6415 | AB17: 3217.409 | AC17: 3251.1765 | AD17: 3284.944 | AE17: 3318.7115 | AF17: 3352.479 | AG17: 3386.2465 | AH17: 3420.014 | AI17: 3453.7711 | AJ17: 3487.5386 | AK17: 3521.3061 | AL17: 3555.0736 | AM17: 3589.9008 | AN17: 3623.6683 | AO17: 3657.4358 | AP17: 3691.193 | AQ17: 3724.9605 | AR17: 3758.728 | AS17: 3792.4955 | AT17: 3826.263 | AU17: 3860.0305 | AV17: 3893.798 | AW17: 3927.5551 | AX17: 3961.3226 | AY17: 3995.0901 | AZ17: 4028.8576 | BA17: 4063.6848 | BB17: 4097.4523 | BC17: 4114.3361
A18: 2300 | B18: 2350.0518 | C18: 2383.8089 | D18: 2417.5764 | E18: 2451.3439 | F18: 2485.1114 | G18: 2518.8789 | H18: 2552.6464 | I18: 2586.4139 | J18: 2620.171 | K18: 2653.9385 | L18: 2688.7658 | M18: 2722.5333 | N18: 2756.3008 | O18: 2790.0683 | P18: 2823.8358 | Q18: 2857.5929 | R18: 2891.3604 | S18: 2925.1279 | T18: 2958.8954 | U18: 2992.6629 | V18: 3026.4304 | W18: 3060.1979 | X18: 3134.5591 | Y18: 3168.3266 | Z18: 3203.1539 | AA18: 3236.9214 | AB18: 3270.6889 | AC18: 3304.4564 | AD18: 3338.2239 | AE18: 3371.9914 | AF18: 3405.7485 | AG18: 3439.516 | AH18: 3473.2835 | AI18: 3507.051 | AJ18: 3540.8185 | AK18: 3574.586 | AL18: 3608.3535 | AM18: 3643.1704 | AN18: 3676.9379 | AO18: 3710.7054 | AP18: 3744.4729 | AQ18: 3778.2404 | AR18: 3812.0079 | AS18: 3845.7754 | AT18: 3879.5325 | AU18: 3913.3 | AV18: 3947.0675 | AW18: 3980.835 | AX18: 4014.6025 | AY18: 4048.37 | AZ18: 4082.1375 | BA18: 4116.9648 | BB18: 4150.7219 | BC18: 4167.6056
A19: 2400 | B19: 2403.3213 | C19: 2437.0888 | D19: 2470.8563 | E19: 2504.6238 | F19: 2538.3913 | G19: 2572.1588 | H19: 2605.9159 | I19: 2639.6834 | J19: 2673.4509 | K19: 2707.2184 | L19: 2742.0457 | M19: 2775.8132 | N19: 2809.5807 | O19: 2843.3378 | P19: 2877.1053 | Q19: 2910.8728 | R19: 2944.6403 | S19: 2978.4078 | T19: 3012.1753 | U19: 3045.9428 | V19: 3120.3144 | W19: 3154.0715 | X19: 3187.839 | Y19: 3221.6065 | Z19: 3256.4338 | AA19: 3290.2013 | AB19: 3323.9688 | AC19: 3357.7259 | AD19: 3391.4934 | AE19: 3425.2609 | AF19: 3459.0284 | AG19: 3492.7959 | AH19: 3526.5634 | AI19: 3560.3309 | AJ19: 3594.0984 | AK19: 3627.8555 | AL19: 3661.623 | AM19: 3696.4503 | AN19: 3730.2178 | AO19: 3763.9853 | AP19: 3797.7528 | AQ19: 3831.5203 | AR19: 3865.2774 | AS19: 3899.0449 | AT19: 3932.8124 | AU19: 3966.5799 | AV19: 4000.3474 | AW19: 4034.1149 | AX19: 4067.8824 | AY19: 4101.6499 | AZ19: 4135.407 | BA19: 4170.2343 | BB19: 4204.0018 | BC19: 4220.8855
A20: 2500 | B20: 2456.6012 | C20: 2490.3687 | D20: 2524.1362 | E20: 2557.8933 | F20: 2591.6608 | G20: 2625.4283 | H20: 2659.1958 | I20: 2692.9633 | J20: 2726.7308 | K20: 2760.4983 | L20: 2795.3256 | M20: 2829.0827 | N20: 2862.8502 | O20: 2896.6177 | P20: 2930.3852 | Q20: 2964.1527 | R20: 2997.9202 | S20: 3031.6877 | T20: 3085.7469 | U20: 3139.8164 | V20: 3173.5839 | W20: 3207.3514 | X20: 3241.1189 | Y20: 3274.8864 | Z20: 3309.7137 | AA20: 3343.4708 | AB20: 3377.2383 | AC20: 3411.0058 | AD20: 3444.7733 | AE20: 3478.5408 | AF20: 3512.3083 | AG20: 3546.0758 | AH20: 3579.8433 | AI20: 3613.6004 | AJ20: 3647.3679 | AK20: 3681.1354 | AL20: 3714.9029 | AM20: 3749.7302 | AN20: 3783.4977 | AO20: 3817.2652 | AP20: 3851.0223 | AQ20: 3884.7898 | AR20: 3918.5573 | AS20: 3952.3248 | AT20: 3986.0923 | AU20: 4019.8598 | AV20: 4053.6273 | AW20: 4087.3844 | AX20: 4121.1519 | AY20: 4154.9194 | AZ20: 4188.6869 | BA20: 4223.5142 | BB20: 4257.2817 | BC20: 4274.1655
A21: 2600 | B21: 2509.8811 | C21: 2543.6382 | D21: 2577.4057 | E21: 2611.1732 | F21: 2644.9407 | G21: 2678.7082 | H21: 2712.4757 | I21: 2746.2432 | J21: 2780.0003 | K21: 2813.7678 | L21: 2848.5951 | M21: 2882.3626 | N21: 2916.1301 | O21: 2949.8976 | P21: 2983.6651 | Q21: 3017.4222 | R21: 3071.4918 | S21: 3125.5614 | T21: 3159.3289 | U21: 3193.0964 | V21: 3226.8639 | W21: 3260.6314 | X21: 3294.3885 | Y21: 3328.156 | Z21: 3362.9832 | AA21: 3396.7507 | AB21: 3430.5182 | AC21: 3464.2857 | AD21: 3498.0532 | AE21: 3531.8207 | AF21: 3565.5779 | AG21: 3599.3454 | AH21: 3633.1129 | AI21: 3666.8804 | AJ21: 3700.6479 | AK21: 3734.4154 | AL21: 3768.1829 | AM21: 3802.9997 | AN21: 3836.7672 | AO21: 3870.5347 | AP21: 3904.3022 | AQ21: 3938.0697 | AR21: 3971.8372 | AS21: 4005.6047 | AT21: 4039.3619 | AU21: 4073.1294 | AV21: 4106.8969 | AW21: 4140.6644 | AX21: 4174.4319 | AY21: 4208.1994 | AZ21: 4241.9669 | BA21: 4276.7837 | BB21: 4310.5512 | BC21: 4327.435
A22: 2700 | B22: 2563.1507 | C22: 2596.9182 | D22: 2630.6857 | E22: 2664.4532 | F22: 2698.2207 | G22: 2731.9882 | H22: 2765.7453 | I22: 2799.5128 | J22: 2833.2803 | K22: 2867.0478 | L22: 2901.875 | M22: 2935.6425 | N22: 2969.41 | O22: 3003.1672 | P22: 3036.9347 | Q22: 3111.3063 | R22: 3145.0738 | S22: 3178.8413 | T22: 3212.6088 | U22: 3246.3763 | V22: 3280.1334 | W22: 3313.9009 | X22: 3347.6684 | Y22: 3381.4359 | Z22: 3416.2632 | AA22: 3450.0307 | AB22: 3483.7982 | AC22: 3517.5553 | AD22: 3551.3228 | AE22: 3585.0903 | AF22: 3618.8578 | AG22: 3652.6253 | AH22: 3686.3928 | AI22: 3720.1603 | AJ22: 3753.9278 | AK22: 3787.6849 | AL22: 3821.4524 | AM22: 3856.2797 | AN22: 3890.0472 | AO22: 3923.8147 | AP22: 3957.5822 | AQ22: 3991.3497 | AR22: 4025.1068 | AS22: 4058.8743 | AT22: 4092.6418 | AU22: 4126.4093 | AV22: 4160.1768 | AW22: 4193.9443 | AX22: 4227.7118 | AY22: 4261.4793 | AZ22: 4295.2364 | BA22: 4330.0637 | BB22: 4363.8312 | BC22: 4342.5628
C24: patio_4_
B25: 2800 | C25: 2900 | D25: 3000 | E25: 3100 | F25: 3200 | G25: 3300 | H25: 3400 | I25: 3500 | J25: 3600 | K25: 3700 | L25: 3800 | M25: 3900 | N25: 4000 | O25: 4100 | P25: 4200 | Q25: 4300 | R25: 4400 | S25: 4500 | T25: 4600 | U25: 4700 | V25: 4800 | W25: 4900 | X25: 5000 | Y25: 5100 | Z25: 5200 | AA25: 5300 | AB25: 5400 | AC25: 5500 | AD25: 5600 | AE25: 5700 | AF25: 5800 | AG25: 5900 | AH25: 6000 | AI25: 6100 | AJ25: 6200 | AK25: 6300 | AL25: 6400 | AM25: 6500 | AN25: 6600 | AO25: 6700 | AP25: 6800 | AQ25: 6900 | AR25: 7000 | AS25: 7100 | AT25: 7200 | AU25: 7300 | AV25: 7400 | AW25: 7500 | AX25: 7600 | AY25: 7700 | AZ25: 7800 | BA25: 7900 | BB25: 8000 | BC25: 8100 | BD25: 8200 | BE25: 8300 | BF25: 8400 | BG25: 8500 | BH25: 8600 | BI25: 8700 | BJ25: 8800 | BK25: 8900 | BL25: 9000 | BM25: 9100 | BN25: 9200 | BO25: 9300 | BP25: 9400 | BQ25: 9500 | BR25: 9600 | BS25: 9700 | BT25: 9800 | BU25: 9900 | BV25: 10000
A26: 2000 | B26: 2573.2393 | C26: 2601.0949 | D26: 2628.9505 | E26: 2656.8061 | F26: 2684.6617 | G26: 2712.5173 | H26: 2740.3625 | I26: 2768.2181 | J26: 2796.0737 | K26: 2823.9293 | L26: 2851.7849 | M26: 2879.6404 | N26: 2907.496 | O26: 2935.3516 | P26: 2963.2072 | Q26: 2991.0628 | R26: 3020.3314 | S26: 3048.187 | T26: 3076.0426 | U26: 3103.8982 | V26: 3131.7538 | W26: 3159.599 | X26: 3187.4546 | Y26: 3215.3102 | Z26: 3243.1658 | AA26: 3271.0214 | AB26: 3298.8769 | AC26: 3326.7325 | AD26: 3354.5881 | AE26: 3382.4437 | AF26: 3410.2993 | AG26: 3438.1549 | AH26: 3466.0105 | AI26: 3493.8661 | AJ26: 3523.1347 | AK26: 3550.9903 | AL26: 3578.8355 | AM26: 3606.6911 | AN26: 3634.5467 | AO26: 3682.7043 | AP26: 3710.5599 | AQ26: 3758.7176 | AR26: 3786.5732 | AS26: 3814.4287 | AT26: 3842.2843 | AU26: 3870.1399 | AV26: 3897.9955 | AW26: 3925.8511 | AX26: 3953.7067 | AY26: 3981.5623 | AZ26: 4009.4075 | BA26: 4037.2631 | BB26: 4066.5317 | BC26: 4094.3873 | BD26: 4122.2429 | BE26: 4150.0985 | BF26: 4177.9541 | BG26: 4205.8097 | BH26: 4233.6653 | BI26: 4261.5208 | BJ26: 4289.3764 | BK26: 4317.232 | BL26: 4345.0876 | BM26: 4372.9432 | BN26: 4400.7884 | BO26: 4428.6544 | BP26: 4456.4996 | BQ26: 4484.3552 | BR26: 4512.2108 | BS26: 4540.0663 | BT26: 4569.335 | BU26: 4597.1906 | BV26: 4625.0462
A27: 2100 | B27: 2636.8054 | C27: 2664.661 | D27: 2692.5165 | E27: 2720.3721 | F27: 2748.2277 | G27: 2776.0833 | H27: 2803.9389 | I27: 2831.7945 | J27: 2859.6501 | K27: 2887.5057 | L27: 2915.3509 | M27: 2943.2065 | N27: 2971.0621 | O27: 2998.9176 | P27: 3026.7732 | Q27: 3054.6288 | R27: 3083.8975 | S27: 3111.753 | T27: 3139.6086 | U27: 3167.4642 | V27: 3195.3198 | W27: 3223.1754 | X27: 3251.031 | Y27: 3278.8866 | Z27: 3306.7318 | AA27: 3334.5874 | AB27: 3362.443 | AC27: 3390.2986 | AD27: 3418.1541 | AE27: 3446.0097 | AF27: 3473.8653 | AG27: 3501.7209 | AH27: 3529.5765 | AI27: 3557.4321 | AJ27: 3586.7007 | AK27: 3634.8584 | AL27: 3662.714 | AM27: 3710.8716 | AN27: 3738.7168 | AO27: 3766.5828 | AP27: 3794.428 | AQ27: 3822.2836 | AR27: 3850.1392 | AS27: 3877.9948 | AT27: 3905.8504 | AU27: 3933.706 | AV27: 3961.5615 | AW27: 3989.4171 | AX27: 4017.2727 | AY27: 4045.1283 | AZ27: 4072.9839 | BA27: 4100.8395 | BB27: 4130.1081 | BC27: 4157.9637 | BD27: 4185.8089 | BE27: 4213.6645 | BF27: 4241.5201 | BG27: 4269.3757 | BH27: 4297.2313 | BI27: 4325.0869 | BJ27: 4352.9424 | BK27: 4380.798 | BL27: 4408.6536 | BM27: 4436.5092 | BN27: 4464.3648 | BO27: 4492.2204 | BP27: 4520.076 | BQ27: 4547.9316 | BR27: 4575.7872 | BS27: 4603.6324 | BT27: 4632.9114 | BU27: 4660.7566 | BV27: 4688.6122
A28: 2200 | B28: 2700.3714 | C28: 2728.227 | D28: 2756.0826 | E28: 2783.9382 | F28: 2811.7937 | G28: 2839.6493 | H28: 2867.5049 | I28: 2895.3605 | J28: 2923.2161 | K28: 2951.0717 | L28: 2978.9273 | M28: 3006.7829 | N28: 3034.6385 | O28: 3062.4941 | P28: 3090.3393 | Q28: 3118.2052 | R28: 3147.4635 | S28: 3175.3191 | T28: 3203.1747 | U28: 3231.0302 | V28: 3258.8858 | W28: 3286.7414 | X28: 3314.597 | Y28: 3342.4526 | Z28: 3370.3082 | AA28: 3398.1638 | AB28: 3426.0194 | AC28: 3453.875 | AD28: 3481.7202 | AE28: 3509.5758 | AF28: 3537.4313 | AG28: 3565.2869 | AH28: 3613.4446 | AI28: 3641.3002 | AJ28: 3690.8709 | AK28: 3718.7265 | AL28: 3746.582 | AM28: 3774.4376 | AN28: 3802.2932 | AO28: 3830.1488 | AP28: 3858.0044 | AQ28: 3885.86 | AR28: 3913.7156 | AS28: 3941.5712 | AT28: 3969.4268 | AU28: 3997.272 | AV28: 4025.1276 | AW28: 4052.9831 | AX28: 4080.8387 | AY28: 4108.6943 | AZ28: 4136.5499 | BA28: 4164.4055 | BB28: 4193.6741 | BC28: 4221.5297 | BD28: 4249.3853 | BE28: 4277.2409 | BF28: 4305.0965 | BG28: 4332.9521 | BH28: 4360.8077 | BI28: 4388.6529 | BJ28: 4416.5085 | BK28: 4444.3641 | BL28: 4472.2197 | BM28: 4500.0752 | BN28: 4527.9308 | BO28: 4555.7864 | BP28: 4583.642 | BQ28: 4611.4976 | BR28: 4639.3532 | BS28: 4667.2088 | BT28: 4696.4774 | BU28: 4724.333 | BV28: 4752.1886
A29: 2300 | B29: 2763.9478 | C29: 2791.8034 | D29: 2819.659 | E29: 2847.5042 | F29: 2875.3598 | G29: 2903.2154 | H29: 2931.0709 | I29: 2958.9265 | J29: 2986.7821 | K29: 3014.6377 | L29: 3042.4933 | M29: 3070.3489 | N29: 3098.2045 | O29: 3126.0601 | P29: 3153.9157 | Q29: 3181.7713 | R29: 3211.0399 | S29: 3238.8851 | T29: 3266.7511 | U29: 3294.5963 | V29: 3322.4519 | W29: 3350.3074 | X29: 3378.163 | Y29: 3406.0186 | Z29: 3433.8742 | AA29: 3461.7298 | AB29: 3489.5854 | AC29: 3517.441 | AD29: 3545.2966 | AE29: 3593.4542 | AF29: 3621.3098 | AG29: 3669.4675 | AH29: 3697.3231 | AI29: 3725.1683 | AJ29: 3754.4473 | AK29: 3782.2925 | AL29: 3810.1481 | AM29: 3838.0037 | AN29: 3865.8592 | AO29: 3893.7148 | AP29: 3921.5704 | AQ29: 3949.426 | AR29: 3977.2816 | AS29: 4005.1372 | AT29: 4032.9928 | AU29: 4060.8484 | AV29: 4088.704 | AW29: 4116.5492 | AX29: 4144.4151 | AY29: 4172.2603 | AZ29: 4200.1159 | BA29: 4227.9715 | BB29: 4257.2402 | BC29: 4285.0957 | BD29: 4312.9513 | BE29: 4340.8069 | BF29: 4368.6625 | BG29: 4396.5181 | BH29: 4424.3737 | BI29: 4452.2293 | BJ29: 4480.0849 | BK29: 4507.9405 | BL29: 4535.7857 | BM29: 4563.6413 | BN29: 4591.4968 | BO29: 4619.3524 | BP29: 4647.208 | BQ29: 4675.0636 | BR29: 4702.9192 | BS29: 4730.7748 | BT29: 4760.0434 | BU29: 4787.899 | BV29: 4815.7546
A30: 2400 | B30: 2827.5138 | C30: 2855.3694 | D30: 2883.225 | E30: 2911.0806 | F30: 2938.9362 | G30: 2966.7918 | H30: 2994.6474 | I30: 3022.4926 | J30: 3050.3481 | K30: 3078.2037 | L30: 3106.0593 | M30: 3133.9149 | N30: 3161.7705 | O30: 3189.6261 | P30: 3217.4817 | Q30: 3245.3373 | R30: 3274.6059 | S30: 3302.4615 | T30: 3330.3171 | U30: 3358.1727 | V30: 3386.0283 | W30: 3413.8839 | X30: 3441.7291 | Y30: 3469.5846 | Z30: 3497.4402 | AA30: 3525.2958 | AB30: 3553.1514 | AC30: 3601.3091 | AD30: 3629.1647 | AE30: 3677.3223 | AF30: 3705.1779 | AG30: 3733.0335 | AH30: 3760.8891 | AI30: 3788.7447 | AJ30: 3818.0133 | AK30: 3845.8689 | AL30: 3873.7245 | AM30: 3901.5697 | AN30: 3929.4253 | AO30: 3957.2809 | AP30: 3985.1364 | AQ30: 4012.992 | AR30: 4040.8476 | AS30: 4068.7032 | AT30: 4096.5588 | AU30: 4124.4144 | AV30: 4152.27 | AW30: 4180.1256 | AX30: 4207.9812 | AY30: 4235.8368 | AZ30: 4263.6923 | BA30: 4291.5479 | BB30: 4320.8062 | BC30: 4348.6722 | BD30: 4376.5174 | BE30: 4404.3729 | BF30: 4432.2285 | BG30: 4460.0841 | BH30: 4487.9397 | BI30: 4515.7953 | BJ30: 4543.6509 | BK30: 4571.5065 | BL30: 4599.3621 | BM30: 4627.2177 | BN30: 4655.0733 | BO30: 4682.9288 | BP30: 4710.7844 | BQ30: 4738.64 | BR30: 4766.4852 | BS30: 4794.3408 | BT30: 4823.6094 | BU30: 4851.465 | BV30: 4879.3206
A31: 2500 | B31: 2891.0798 | C31: 2918.9354 | D31: 2946.791 | E31: 2974.6466 | F31: 3002.5022 | G31: 3030.3578 | H31: 3058.2134 | I31: 3086.069 | J31: 3113.9246 | K31: 3141.7801 | L31: 3169.6357 | M31: 3197.4913 | N31: 3225.3365 | O31: 3253.1921 | P31: 3281.0477 | Q31: 3308.9033 | R31: 3338.1719 | S31: 3366.0275 | T31: 3393.8831 | U31: 3421.7387 | V31: 3449.5943 | W31: 3477.4499 | X31: 3505.3055 | Y31: 3533.1611 | Z31: 3581.3187 | AA31: 3609.1743 | AB31: 3657.3319 | AC31: 3685.1875 | AD31: 3713.0327 | AE31: 3740.8883 | AF31: 3768.7439 | AG31: 3796.5995 | AH31: 3824.4551 | AI31: 3852.3107 | AJ31: 3881.5793 | AK31: 3909.4349 | AL31: 3937.2905 | AM31: 3965.1461 | AN31: 3993.0017 | AO31: 4020.8573 | AP31: 4048.7129 | AQ31: 4076.5684 | AR31: 4104.4136 | AS31: 4132.2692 | AT31: 4160.1248 | AU31: 4187.9804 | AV31: 4215.836 | AW31: 4243.6916 | AX31: 4271.5472 | AY31: 4299.4028 | AZ31: 4327.2584 | BA31: 4355.114 | BB31: 4384.3826 | BC31: 4412.2382 | BD31: 4440.0938 | BE31: 4467.939 | BF31: 4495.7946 | BG31: 4523.6502 | BH31: 4551.5057 | BI31: 4579.3613 | BJ31: 4607.2169 | BK31: 4635.0725 | BL31: 4662.9281 | BM31: 4690.7837 | BN31: 4718.6393 | BO31: 4746.4949 | BP31: 4774.3505 | BQ31: 4802.206 | BR31: 4830.0616 | BS31: 4857.9172 | BT31: 4887.1859 | BU31: 4915.0311 | BV31: 4942.8867
A32: 2600 | B32: 2954.6562 | C32: 2982.5014 | D32: 3010.357 | E32: 3038.2126 | F32: 3066.0682 | G32: 3093.9238 | H32: 3121.7794 | I32: 3149.635 | J32: 3177.4906 | K32: 3205.3462 | L32: 3233.2018 | M32: 3261.0574 | N32: 3288.9129 | O32: 3316.7685 | P32: 3344.6137 | Q32: 3372.4797 | R32: 3401.7379 | S32: 3429.5935 | T32: 3457.4491 | U32: 3485.3047 | V32: 3513.1603 | W32: 3541.0159 | X32: 3589.1735 | Y32: 3617.0291 | Z32: 3665.1868 | AA32: 3693.0424 | AB32: 3720.898 | AC32: 3748.7536 | AD32: 3776.6091 | AE32: 3804.4543 | AF32: 3832.3203 | AG32: 3860.1655 | AH32: 3888.0211 | AI32: 3915.8767 | AJ32: 3945.1453 | AK32: 3973.0009 | AL32: 4000.8565 | AM32: 4028.7121 | AN32: 4056.5677 | AO32: 4084.4233 | AP32: 4112.2789 | AQ32: 4140.1345 | AR32: 4167.9901 | AS32: 4195.8456 | AT32: 4223.7012 | AU32: 4251.5464 | AV32: 4279.402 | AW32: 4307.2576 | AX32: 4335.1132 | AY32: 4362.9688 | AZ32: 4390.8244 | BA32: 4418.68 | BB32: 4447.9486 | BC32: 4475.8042 | BD32: 4503.6598 | BE32: 4531.5154 | BF32: 4559.371 | BG32: 4587.2266 | BH32: 4615.0822 | BI32: 4642.9377 | BJ32: 4670.7933 | BK32: 4698.6385 | BL32: 4726.4941 | BM32: 4754.3497 | BN32: 4782.2053 | BO32: 4810.0609 | BP32: 4837.9165 | BQ32: 4865.7721 | BR32: 4893.6277 | BS32: 4921.4832 | BT32: 4950.7519 | BU32: 4978.6075 | BV32: 5006.4631
A33: 2700 | B33: 3018.2223 | C33: 3046.0779 | D33: 3073.9334 | E33: 3101.789 | F33: 3129.6446 | G33: 3157.4898 | H33: 3185.3454 | I33: 3213.201 | J33: 3241.0566 | K33: 3268.9122 | L33: 3296.7678 | M33: 3324.6234 | N33: 3352.479 | O33: 3380.3345 | P33: 3408.1901 | Q33: 3436.0457 | R33: 3465.3144 | S33: 3493.1699 | T33: 3521.0255 | U33: 3548.8707 | V33: 3597.0388 | W33: 3624.884 | X33: 3673.0416 | Y33: 3700.8972 | Z33: 3728.7528 | AA33: 3756.6084 | AB33: 3784.464 | AC33: 3812.3196 | AD33: 3840.1752 | AE33: 3868.0308 | AF33: 3895.8863 | AG33: 3923.7419 | AH33: 3951.5975 | AI33: 3979.4531 | AJ33: 4008.7217 | AK33: 4036.5773 | AL33: 4064.4225 | AM33: 4092.2781 | AN33: 4120.1337 | AO33: 4147.9893 | AP33: 4175.8449 | AQ33: 4203.7005 | AR33: 4231.5561 | AS33: 4259.4117 | AT33: 4287.2673 | AU33: 4315.1228 | AV33: 4342.9784 | AW33: 4370.834 | AX33: 4398.6896 | AY33: 4426.5452 | AZ33: 4454.3904 | BA33: 4482.246 | BB33: 4511.5146 | BC33: 4539.3702 | BD33: 4567.2258 | BE33: 4595.0814 | BF33: 4622.937 | BG33: 4650.7926 | BH33: 4678.6482 | BI33: 4706.5038 | BJ33: 4734.3593 | BK33: 4762.2149 | BL33: 4790.0705 | BM33: 4817.9261 | BN33: 4845.7713 | BO33: 4873.6269 | BP33: 4901.4825 | BQ33: 4929.3381 | BR33: 4957.1937 | BS33: 4985.0493 | BT33: 5014.3179 | BU33: 5004.0214 | BV33: 5031.877
C35: patio_mono_2_
B36: 1500 | C36: 1600 | D36: 1700 | E36: 1800 | F36: 1900 | G36: 2000 | H36: 2100 | I36: 2200 | J36: 2300 | K36: 2400 | L36: 2500 | M36: 2600 | N36: 2700 | O36: 2800 | P36: 2900 | Q36: 3000 | R36: 3100 | S36: 3200 | T36: 3300 | U36: 3400 | V36: 3500 | W36: 3600 | X36: 3700 | Y36: 3800 | Z36: 3900 | AA36: 4000 | AB36: 4100 | AC36: 4200 | AD36: 4300 | AE36: 4400 | AF36: 4500 | AG36: 4600 | AH36: 4700 | AI36: 4800 | AJ36: 4900 | AK36: 5000
A37: 2000 | B37: 1190.7875 | C37: 1211.1 | D37: 1231.402 | E37: 1251.7145 | F37: 1272.0269 | G37: 1292.3394 | H37: 1312.6518 | I37: 1333.6708 | J37: 1353.9832 | K37: 1374.2957 | L37: 1394.6081 | M37: 1414.9102 | N37: 1435.2226 | O37: 1455.5351 | P37: 1475.8475 | Q37: 1496.16 | R37: 1517.179 | S37: 1537.4914 | T37: 1557.8039 | U37: 1598.4184 | V37: 1618.7204 | W37: 1639.0329 | X37: 1659.3453 | Y37: 1679.6578 | Z37: 1699.9702 | AA37: 1720.9892 | AB37: 1741.3017 | AC37: 1761.6141 | AD37: 1781.9266 | AE37: 1802.2286 | AF37: 1822.5411 | AG37: 1842.8535 | AH37: 1863.166 | AI37: 1883.4784 | AJ37: 1904.4974 | AK37: 1924.8098
A38: 2100 | B38: 1221.251 | C38: 1241.5634 | D38: 1261.8759 | E38: 1282.1883 | F38: 1302.4904 | G38: 1322.8029 | H38: 1343.1153 | I38: 1364.1343 | J38: 1384.4467 | K38: 1404.7592 | L38: 1425.0716 | M38: 1445.3841 | N38: 1465.6965 | O38: 1485.9986 | P38: 1506.311 | Q38: 1526.6235 | R38: 1547.6424 | S38: 1588.257 | T38: 1608.5694 | U38: 1628.8819 | V38: 1649.1943 | W38: 1669.5068 | X38: 1689.8192 | Y38: 1710.1213 | Z38: 1730.4337 | AA38: 1751.4527 | AB38: 1771.7651 | AC38: 1792.0776 | AD38: 1812.39 | AE38: 1832.7025 | AF38: 1853.0149 | AG38: 1873.3274 | AH38: 1893.6294 | AI38: 1913.9419 | AJ38: 1934.9609 | AK38: 1955.2733
A39: 2200 | B39: 1251.7145 | C39: 1272.0269 | D39: 1292.3394 | E39: 1312.6518 | F39: 1332.9643 | G39: 1353.2767 | H39: 1373.5892 | I39: 1394.5977 | J39: 1414.9102 | K39: 1435.2226 | L39: 1455.5351 | M39: 1475.8475 | N39: 1496.16 | O39: 1516.4724 | P39: 1536.7849 | Q39: 1557.0974 | R39: 1598.408 | S39: 1618.7204 | T39: 1639.0329 | U39: 1659.3453 | V39: 1679.6578 | W39: 1699.9702 | X39: 1720.2827 | Y39: 1740.5951 | Z39: 1760.9076 | AA39: 1781.9162 | AB39: 1802.2286 | AC39: 1822.5411 | AD39: 1842.8535 | AE39: 1863.166 | AF39: 1883.4784 | AG39: 1903.7909 | AH39: 1924.1033 | AI39: 1944.4158 | AJ39: 1965.4244 | AK39: 1985.7368
A40: 2300 | B40: 1282.1779 | C40: 1302.4904 | D40: 1322.8029 | E40: 1343.1153 | F40: 1363.4277 | G40: 1383.7402 | H40: 1404.0526 | I40: 1425.0716 | J40: 1445.3841 | K40: 1465.6861 | L40: 1485.9986 | M40: 1506.311 | N40: 1526.6235 | O40: 1546.9359 | P40: 1587.5504 | Q40: 1607.8629 | R40: 1628.8819 | S40: 1649.1943 | T40: 1669.4964 | U40: 1689.8088 | V40: 1710.1213 | W40: 1730.4337 | X40: 1750.7462 | Y40: 1771.0586 | Z40: 1791.3711 | AA40: 1812.39 | AB40: 1832.7025 | AC40: 1853.0045 | AD40: 1873.317 | AE40: 1893.6294 | AF40: 1913.9419 | AG40: 1934.2543 | AH40: 1954.5668 | AI40: 1974.8792 | AJ40: 1995.8982 | AK40: 2016.2107
A41: 2400 | B41: 1312.6518 | C41: 1332.9643 | D41: 1353.2767 | E41: 1373.5788 | F41: 1393.8912 | G41: 1414.2037 | H41: 1434.5161 | I41: 1455.5351 | J41: 1475.8475 | K41: 1496.16 | L41: 1516.4724 | M41: 1536.7849 | N41: 1557.087 | O41: 1597.7015 | P41: 1618.0139 | Q41: 1638.3264 | R41: 1659.3453 | S41: 1679.6578 | T41: 1699.9702 | U41: 1720.2827 | V41: 1740.5951 | W41: 1760.8972 | X41: 1781.2096 | Y41: 1801.5221 | Z41: 1821.8345 | AA41: 1842.8535 | AB41: 1863.166 | AC41: 1883.4784 | AD41: 1903.7909 | AE41: 1924.1033 | AF41: 1944.4054 | AG41: 1964.7178 | AH41: 1985.0303 | AI41: 2005.3427 | AJ41: 2026.3617 | AK41: 2046.6741
A42: 2500 | B42: 1343.1153 | C42: 1363.4277 | D42: 1383.7402 | E42: 1404.0526 | F42: 1424.3651 | G42: 1444.6672 | H42: 1464.9796 | I42: 1485.9986 | J42: 1506.311 | K42: 1526.6235 | L42: 1546.9359 | M42: 1567.2484 | N42: 1607.8629 | O42: 1628.1753 | P42: 1648.4774 | Q42: 1668.7898 | R42: 1689.8088 | S42: 1710.1213 | T42: 1730.4337 | U42: 1750.7462 | V42: 1771.0586 | W42: 1791.3711 | X42: 1811.6835 | Y42: 1831.9856 | Z42: 1852.298 | AA42: 1873.317 | AB42: 1893.6294 | AC42: 1913.9419 | AD42: 1934.2543 | AE42: 1954.5668 | AF42: 1974.8792 | AG42: 1995.1917 | AH42: 2015.5041 | AI42: 2035.8062 | AJ42: 2056.8252 | AK42: 2077.1376
A43: 2600 | B43: 1373.5788 | C43: 1393.8912 | D43: 1414.2037 | E43: 1434.5161 | F43: 1454.8286 | G43: 1475.141 | H43: 1495.4535 | I43: 1516.4724 | J43: 1536.7745 | K43: 1557.087 | L43: 1577.3994 | M43: 1618.0139 | N43: 1638.3264 | O43: 1658.6388 | P43: 1678.9513 | Q43: 1699.2637 | R43: 1720.2827 | S43: 1740.5847 | T43: 1760.8972 | U43: 1781.2096 | V43: 1801.5221 | W43: 1821.8345 | X43: 1842.147 | Y43: 1862.4594 | Z43: 1882.7719 | AA43: 1903.7909 | AB43: 1924.0929 | AC43: 1944.4054 | AD43: 1964.7178 | AE43: 1985.0303 | AF43: 2005.3427 | AG43: 2025.6552 | AH43: 2045.9676 | AI43: 2066.2801 | AJ43: 2087.2991 | AK43: 2107.6011
A44: 2700 | B44: 1404.0526 | C44: 1424.3547 | D44: 1444.6672 | E44: 1464.9796 | F44: 1485.2921 | G44: 1505.6045 | H44: 1525.917 | I44: 1546.9359 | J44: 1567.2484 | K44: 1587.5608 | L44: 1628.1649 | M44: 1648.4774 | N44: 1668.7898 | O44: 1689.1023 | P44: 1709.4147 | Q44: 1729.7272 | R44: 1750.7462 | S44: 1771.0586 | T44: 1791.3711 | U44: 1811.6731 | V44: 1831.9856 | W44: 1852.298 | X44: 1872.6105 | Y44: 1892.9229 | Z44: 1913.2354 | AA44: 1934.2543 | AB44: 1954.5668 | AC44: 1974.8792 | AD44: 1995.1917 | AE44: 2015.4938 | AF44: 2035.8062 | AG44: 2056.1187 | AH44: 2076.4311 | AI44: 2096.7436 | AJ44: 2117.7625 | AK44: 2099.9229
C46: patio_mono_4_
B47: 2800 | C47: 2900 | D47: 3000 | E47: 3100 | F47: 3200 | G47: 3300 | H47: 3400 | I47: 3500 | J47: 3600 | K47: 3700 | L47: 3800 | M47: 3900 | N47: 4000 | O47: 4100 | P47: 4200 | Q47: 4300 | R47: 4400 | S47: 4500 | T47: 4600 | U47: 4700 | V47: 4800 | W47: 4900 | X47: 5000 | Y47: 5100 | Z47: 5200 | AA47: 5300 | AB47: 5400 | AC47: 5500 | AD47: 5600 | AE47: 5700 | AF47: 5800 | AG47: 5900 | AH47: 6000 | AI47: 6100 | AJ47: 6200 | AK47: 6300 | AL47: 6400 | AM47: 6500 | AN47: 6600 | AO47: 6700 | AP47: 6800 | AQ47: 6900 | AR47: 7000 | AS47: 7100 | AT47: 7200 | AU47: 7300 | AV47: 7400 | AW47: 7500 | AX47: 7600 | AY47: 7700 | AZ47: 7800 | BA47: 7900 | BB47: 8000 | BC47: 8100 | BD47: 8200 | BE47: 8300 | BF47: 8400 | BG47: 8500 | BH47: 8600 | BI47: 8700 | BJ47: 8800 | BK47: 8900 | BL47: 9000 | BM47: 9100 | BN47: 9200 | BO47: 9300 | BP47: 9400 | BQ47: 9500 | BR47: 9600 | BS47: 9700 | BT47: 9800 | BU47: 9900 | BV47: 10000
A48: 2000 | B48: 2056.9499 | C48: 2077.2519 | D48: 2097.5644 | E48: 2117.8768 | F48: 2138.1893 | G48: 2158.5017 | H48: 2178.8142 | I48: 2199.1266 | J48: 2219.4391 | K48: 2239.7515 | L48: 2260.064 | M48: 2280.366 | N48: 2300.6785 | O48: 2320.9909 | P48: 2341.3034 | Q48: 2363.0289 | R48: 2383.3413 | S48: 2403.6538 | T48: 2423.9662 | U48: 2444.2787 | V48: 2464.5807 | W48: 2484.8932 | X48: 2505.2056 | Y48: 2525.5181 | Z48: 2545.8305 | AA48: 2566.143 | AB48: 2586.4554 | AC48: 2606.7679 | AD48: 2627.0803 | AE48: 2647.3928 | AF48: 2667.6948 | AG48: 2688.0073 | AH48: 2708.3197 | AI48: 2730.0452 | AJ48: 2750.3577 | AK48: 2770.6701 | AL48: 2790.9826 | AM48: 2831.5971 | AN48: 2851.9095 | AO48: 2892.5137 | AP48: 2912.8261 | AQ48: 2933.1386 | AR48: 2953.451 | AS48: 2973.7635 | AT48: 2994.0759 | AU48: 3014.3884 | AV48: 3034.7008 | AW48: 3055.0133 | AX48: 3075.3153 | AY48: 3095.6278 | AZ48: 3115.9402 | BA48: 3137.6657 | BB48: 3157.9782 | BC48: 3178.2906 | BD48: 3198.6031 | BE48: 3218.9155 | BF48: 3239.228 | BG48: 3259.53 | BH48: 3279.8425 | BI48: 3300.1549 | BJ48: 3320.4674 | BK48: 3340.7798 | BL48: 3361.0923 | BM48: 3381.4047 | BN48: 3401.7172 | BO48: 3422.0296 | BP48: 3442.3421 | BQ48: 3462.6441 | BR48: 3482.9566 | BS48: 3504.6821 | BT48: 3524.9945 | BU48: 3545.307 | BV48: 3565.6194
A49: 2100 | B49: 2107.8816 | C49: 2128.1941 | D49: 2148.5065 | E49: 2168.819 | F49: 2189.121 | G49: 2209.4335 | H49: 2229.7459 | I49: 2250.0584 | J49: 2270.3708 | K49: 2290.6833 | L49: 2310.9958 | M49: 2331.3082 | N49: 2351.6206 | O49: 2371.9227 | P49: 2392.2352 | Q49: 2413.9606 | R49: 2434.2731 | S49: 2454.5855 | T49: 2474.898 | U49: 2495.2105 | V49: 2515.5229 | W49: 2535.8353 | X49: 2556.1374 | Y49: 2576.4499 | Z49: 2596.7623 | AA49: 2617.0748 | AB49: 2637.3872 | AC49: 2657.6997 | AD49: 2678.0121 | AE49: 2698.3246 | AF49: 2718.637 | AG49: 2738.9495 | AH49: 2759.2515 | AI49: 2780.977 | AJ49: 2821.5915 | AK49: 2841.904 | AL49: 2882.5185 | AM49: 2902.8309 | AN49: 2923.1434 | AO49: 2943.4558 | AP49: 2963.7683 | AQ49: 2984.0703 | AR49: 3004.3828 | AS49: 3024.6952 | AT49: 3045.0077 | AU49: 3065.3201 | AV49: 3085.6326 | AW49: 3105.945 | AX49: 3126.2575 | AY49: 3146.5699 | AZ49: 3166.872 | BA49: 3188.5975 | BB49: 3208.9099 | BC49: 3229.2224 | BD49: 3249.5348 | BE49: 3269.8473 | BF49: 3290.1597 | BG49: 3310.4722 | BH49: 3330.7846 | BI49: 3351.0867 | BJ49: 3371.3991 | BK49: 3391.7116 | BL49: 3412.024 | BM49: 3432.3365 | BN49: 3452.6489 | BO49: 3472.9614 | BP49: 3493.2739 | BQ49: 3513.5863 | BR49: 3533.8884 | BS49: 3555.6138 | BT49: 3575.9263 | BU49: 3596.2387 | BV49: 3616.5512
A50: 2200 | B50: 2158.8134 | C50: 2179.1259 | D50: 2199.4383 | E50: 2219.7508 | F50: 2240.0632 | G50: 2260.3757 | H50: 2280.6777 | I50: 2300.9902 | J50: 2321.3026 | K50: 2341.6151 | L50: 2361.9275 | M50: 2382.24 | N50: 2402.5524 | O50: 2422.8649 | P50: 2443.1773 | Q50: 2464.8924 | R50: 2485.2049 | S50: 2505.5173 | T50: 2525.8298 | U50: 2546.1422 | V50: 2566.4547 | W50: 2586.7671 | X50: 2607.0796 | Y50: 2627.392 | Z50: 2647.6941 | AA50: 2668.0065 | AB50: 2688.319 | AC50: 2708.6314 | AD50: 2728.9439 | AE50: 2749.2563 | AF50: 2769.5688 | AG50: 2810.1833 | AH50: 2830.4957 | AI50: 2872.5129 | AJ50: 2892.8254 | AK50: 2913.1378 | AL50: 2933.4503 | AM50: 2953.7627 | AN50: 2974.0752 | AO50: 2994.3876 | AP50: 3014.7001 | AQ50: 3035.0125 | AR50: 3055.325 | AS50: 3075.627 | AT50: 3095.9395 | AU50: 3116.2519 | AV50: 3136.5644 | AW50: 3156.8768 | AX50: 3177.1893 | AY50: 3197.5017 | AZ50: 3217.8142 | BA50: 3239.5397 | BB50: 3259.8417 | BC50: 3280.1542 | BD50: 3300.4666 | BE50: 3320.7791 | BF50: 3341.0915 | BG50: 3361.404 | BH50: 3381.7164 | BI50: 3402.0289 | BJ50: 3422.3413 | BK50: 3442.6434 | BL50: 3462.9558 | BM50: 3483.2683 | BN50: 3503.5807 | BO50: 3523.8932 | BP50: 3544.2056 | BQ50: 3564.5181 | BR50: 3584.8305 | BS50: 3606.556 | BT50: 3626.8581 | BU50: 3647.1705 | BV50: 3667.483
A51: 2300 | B51: 2209.7452 | C51: 2230.0576 | D51: 2250.3701 | E51: 2270.6825 | F51: 2290.995 | G51: 2311.3075 | H51: 2331.6199 | I51: 2351.9324 | J51: 2372.2344 | K51: 2392.5469 | L51: 2412.8593 | M51: 2433.1718 | N51: 2453.4842 | O51: 2473.7967 | P51: 2494.1091 | Q51: 2515.8346 | R51: 2536.147 | S51: 2556.4491 | T51: 2576.7616 | U51: 2597.074 | V51: 2617.3865 | W51: 2637.6989 | X51: 2658.0114 | Y51: 2678.3238 | Z51: 2698.6363 | AA51: 2718.9487 | AB51: 2739.2508 | AC51: 2759.5632 | AD51: 2800.1777 | AE51: 2820.4902 | AF51: 2861.1047 | AG51: 2881.4171 | AH51: 2901.7296 | AI51: 2923.4551 | AJ51: 2943.7675 | AK51: 2964.0696 | AL51: 2984.382 | AM51: 3004.6945 | AN51: 3025.0069 | AO51: 3045.3194 | AP51: 3065.6318 | AQ51: 3085.9443 | AR51: 3106.2567 | AS51: 3126.5692 | AT51: 3146.8712 | AU51: 3167.1837 | AV51: 3187.4961 | AW51: 3207.8086 | AX51: 3228.121 | AY51: 3248.4335 | AZ51: 3268.7459 | BA51: 3290.4714 | BB51: 3310.7839 | BC51: 3331.086 | BD51: 3351.3984 | BE51: 3371.7108 | BF51: 3392.0233 | BG51: 3412.3357 | BH51: 3432.6482 | BI51: 3452.9606 | BJ51: 3473.2731 | BK51: 3493.5855 | BL51: 3513.8876 | BM51: 3534.2001 | BN51: 3554.5125 | BO51: 3574.825 | BP51: 3595.1374 | BQ51: 3615.4499 | BR51: 3635.7623 | BS51: 3657.4878 | BT51: 3677.8002 | BU51: 3698.1127 | BV51: 3718.4148
A52: 2400 | B52: 2260.677 | C52: 2280.9894 | D52: 2301.3019 | E52: 2321.6143 | F52: 2341.9268 | G52: 2362.2392 | H52: 2382.5517 | I52: 2402.8641 | J52: 2423.1766 | K52: 2443.489 | L52: 2463.7911 | M52: 2484.1035 | N52: 2504.416 | O52: 2524.7284 | P52: 2545.0409 | Q52: 2566.7664 | R52: 2587.0788 | S52: 2607.3913 | T52: 2627.7037 | U52: 2648.0058 | V52: 2668.3182 | W52: 2688.6307 | X52: 2708.9431 | Y52: 2729.2556 | Z52: 2749.568 | AA52: 2790.1825 | AB52: 2810.495 | AC52: 2851.1095 | AD52: 2871.4116 | AE52: 2891.724 | AF52: 2912.0365 | AG52: 2932.3489 | AH52: 2952.6614 | AI52: 2974.3869 | AJ52: 2994.6993 | AK52: 3015.0118 | AL52: 3035.3242 | AM52: 3055.6263 | AN52: 3075.9387 | AO52: 3096.2512 | AP52: 3116.5636 | AQ52: 3136.8761 | AR52: 3157.1885 | AS52: 3177.501 | AT52: 3197.8134 | AU52: 3218.1259 | AV52: 3238.4279 | AW52: 3258.7404 | AX52: 3279.0528 | AY52: 3299.3653 | AZ52: 3319.6777 | BA52: 3341.4032 | BB52: 3361.7157 | BC52: 3382.0281 | BD52: 3402.3406 | BE52: 3422.653 | BF52: 3442.9551 | BG52: 3463.2675 | BH52: 3483.58 | BI52: 3503.8924 | BJ52: 3524.2049 | BK52: 3544.5173 | BL52: 3564.8298 | BM52: 3585.1422 | BN52: 3605.4547 | BO52: 3625.7567 | BP52: 3646.0692 | BQ52: 3666.3816 | BR52: 3686.6941 | BS52: 3708.4196 | BT52: 3728.732 | BU52: 3749.0445 | BV52: 3769.3569
A53: 2500 | B53: 2311.6191 | C53: 2331.9316 | D53: 2352.2337 | E53: 2372.5461 | F53: 2392.8586 | G53: 2413.171 | H53: 2433.4835 | I53: 2453.7959 | J53: 2474.1084 | K53: 2494.4208 | L53: 2514.7333 | M53: 2535.0457 | N53: 2555.3478 | O53: 2575.6602 | P53: 2595.9727 | Q53: 2617.6982 | R53: 2638.0106 | S53: 2658.3231 | T53: 2678.6355 | U53: 2698.948 | V53: 2719.2604 | W53: 2739.5625 | X53: 2759.8749 | Y53: 2800.4894 | Z53: 2820.8019 | AA53: 2861.4164 | AB53: 2881.7288 | AC53: 2902.0413 | AD53: 2922.3537 | AE53: 2942.6662 | AF53: 2962.9682 | AG53: 2983.2807 | AH53: 3003.5931 | AI53: 3025.3186 | AJ53: 3045.6311 | AK53: 3065.9435 | AL53: 3086.256 | AM53: 3106.5684 | AN53: 3126.8809 | AO53: 3147.1829 | AP53: 3167.4954 | AQ53: 3187.8078 | AR53: 3208.1203 | AS53: 3228.4327 | AT53: 3248.7452 | AU53: 3269.0576 | AV53: 3289.3701 | AW53: 3309.6825 | AX53: 3329.995 | AY53: 3350.2971 | AZ53: 3370.6095 | BA53: 3392.335 | BB53: 3412.6474 | BC53: 3432.9599 | BD53: 3453.2723 | BE53: 3473.5848 | BF53: 3493.8972 | BG53: 3514.2097 | BH53: 3534.5118 | BI53: 3554.8242 | BJ53: 3575.1367 | BK53: 3595.4491 | BL53: 3615.7616 | BM53: 3636.074 | BN53: 3656.3865 | BO53: 3676.6989 | BP53: 3697.0114 | BQ53: 3717.3134 | BR53: 3737.6259 | BS53: 3759.3514 | BT53: 3779.6638 | BU53: 3799.9763 | BV53: 3820.2887
A54: 2600 | B54: 2362.5509 | C54: 2382.8634 | D54: 2403.1758 | E54: 2423.4883 | F54: 2443.7903 | G54: 2464.1028 | H54: 2484.4152 | I54: 2504.7277 | J54: 2525.0401 | K54: 2545.3526 | L54: 2565.665 | M54: 2585.9775 | N54: 2606.2899 | O54: 2626.6024 | P54: 2646.9044 | Q54: 2668.6299 | R54: 2688.9424 | S54: 2709.2548 | T54: 2729.5673 | U54: 2749.8797 | V54: 2770.1922 | W54: 2810.8067 | X54: 2831.1088 | Y54: 2871.7233 | Z54: 2892.0357 | AA54: 2912.3482 | AB54: 2932.6606 | AC54: 2952.9731 | AD54: 2973.2855 | AE54: 2993.598 | AF54: 3013.9104 | AG54: 3034.2229 | AH54: 3054.5249 | AI54: 3076.2504 | AJ54: 3096.5629 | AK54: 3116.8753 | AL54: 3137.1878 | AM54: 3157.5002 | AN54: 3177.8127 | AO54: 3198.1251 | AP54: 3218.4376 | AQ54: 3238.7396 | AR54: 3259.0521 | AS54: 3279.3645 | AT54: 3299.677 | AU54: 3319.9894 | AV54: 3340.3019 | AW54: 3360.6143 | AX54: 3380.9268 | AY54: 3401.2392 | AZ54: 3421.5413 | BA54: 3443.2668 | BB54: 3463.5792 | BC54: 3483.8917 | BD54: 3504.2041 | BE54: 3524.5166 | BF54: 3544.829 | BG54: 3565.1415 | BH54: 3585.4539 | BI54: 3605.756 | BJ54: 3626.0684 | BK54: 3646.3809 | BL54: 3666.6933 | BM54: 3687.0058 | BN54: 3707.3182 | BO54: 3727.6307 | BP54: 3747.9431 | BQ54: 3768.2556 | BR54: 3788.568 | BS54: 3810.2831 | BT54: 3830.5956 | BU54: 3850.908 | BV54: 3871.2205
A55: 2700 | B55: 2413.4827 | C55: 2433.7952 | D55: 2454.1076 | E55: 2474.4201 | F55: 2494.7325 | G55: 2515.045 | H55: 2535.347 | I55: 2555.6595 | J55: 2575.9719 | K55: 2596.2844 | L55: 2616.5968 | M55: 2636.9093 | N55: 2657.2217 | O55: 2677.5342 | P55: 2697.8466 | Q55: 2719.5617 | R55: 2739.8742 | S55: 2760.1866 | T55: 2780.4991 | U55: 2821.1136 | V55: 2841.426 | W55: 2882.0405 | X55: 2902.353 | Y55: 2922.6654 | Z55: 2942.9675 | AA55: 2963.28 | AB55: 2983.5924 | AC55: 3003.9048 | AD55: 3024.2173 | AE55: 3044.5297 | AF55: 3064.8422 | AG55: 3085.1546 | AH55: 3105.4671 | AI55: 3127.1926 | AJ55: 3147.4946 | AK55: 3167.8071 | AL55: 3188.1195 | AM55: 3208.432 | AN55: 3228.7445 | AO55: 3249.0569 | AP55: 3269.3693 | AQ55: 3289.6818 | AR55: 3309.9942 | AS55: 3330.2963 | AT55: 3350.6088 | AU55: 3370.9212 | AV55: 3391.2337 | AW55: 3411.5461 | AX55: 3431.8586 | AY55: 3452.171 | AZ55: 3472.4835 | BA55: 3494.2089 | BB55: 3514.511 | BC55: 3534.8235 | BD55: 3555.1359 | BE55: 3575.4484 | BF55: 3595.7608 | BG55: 3616.0733 | BH55: 3636.3857 | BI55: 3656.6982 | BJ55: 3677.0106 | BK55: 3697.3231 | BL55: 3717.6251 | BM55: 3737.9376 | BN55: 3758.25 | BO55: 3778.5625 | BP55: 3798.8749 | BQ55: 3819.1874 | BR55: 3839.4998 | BS55: 3861.2253 | BT55: 3843.3857 | BU55: 3863.6877 | BV55: 3845.8481

Sheet patio_2
A1: type | B1: matrix | C1: patio_2_
A2: ='(patio_costs)'!A3 | B2: ='(patio_costs)'!B3 -> 1500 | C2: ='(patio_costs)'!C3 -> 1600 | D2: ='(patio_costs)'!D3 -> 1700 | E2: ='(patio_costs)'!E3 -> 1800 | F2: ='(patio_costs)'!F3 -> 1900 | G2: ='(patio_costs)'!G3 -> 2000 | H2: ='(patio_costs)'!H3 -> 2100 | ... AK2: ='(patio_costs)'!AK3 -> 5000
A3: ='(patio_costs)'!A4 -> 2000 | B3: {='(patio_costs)'!B4:AK11*(1+MARKUP!$Z$6)} -> 1110.755106 | C3: 1131.7164 | D3: 1152.6778 | E3: 1173.6391 | F3: 1194.6004 | G3: 1215.5618 | H3: 1236.5231 | I3: 1257.4844 | J3: 1278.9774 | K3: 1299.9387 | L3: 1320.9001 | M3: 1341.8614 | N3: 1362.8227 | O3: 1383.7841 | P3: 1404.7376 | Q3: 1425.6989 | R3: 1446.6602 | S3: 1468.1532 | T3: 1489.1146 | U3: 1510.0759 | V3: 1546.3145 | W3: 1567.2759 | X3: 1588.2372 | Y3: 1609.1985 | Z3: 1630.1599 | AA3: 1651.1212 | AB3: 1672.6142 | AC3: 1693.5755 | AD3: 1714.5368 | AE3: 1735.4904 | AF3: 1756.4517 | AG3: 1777.413 | AH3: 1798.3743 | AI3: 1819.3357 | AJ3: 1840.297 | AK3: 1861.79
A4: ='(patio_costs)'!A5 -> 2100 | B4: 1139.4098 | C4: 1160.3711 | D4: 1181.3325 | E4: 1202.2938 | F4: 1223.2551 | G4: 1244.2165 | H4: 1265.1778 | I4: 1286.1391 | J4: 1307.6321 | K4: 1328.5935 | L4: 1349.5548 | M4: 1370.5161 | N4: 1391.4696 | O4: 1412.431 | P4: 1433.3923 | Q4: 1454.3536 | R4: 1475.315 | S4: 1496.8079 | T4: 1533.0466 | U4: 1554.0079 | V4: 1574.9692 | W4: 1595.9306 | X4: 1616.8919 | Y4: 1637.8532 | Z4: 1658.8146 | AA4: 1679.7759 | AB4: 1701.2689 | AC4: 1722.2224 | AD4: 1743.1837 | AE4: 1764.1451 | AF4: 1785.1064 | AG4: 1806.0677 | AH4: 1827.0291 | AI4: 1847.9904 | AJ4: 1868.9517 | AK4: 1890.4447
A5: ='(patio_costs)'!A6 -> 2200 | B5: 1168.0645 | C5: 1189.0259 | D5: 1209.9872 | E5: 1230.9485 | F5: 1251.9099 | G5: 1272.8712 | H5: 1293.8325 | I5: 1314.7938 | J5: 1336.2868 | K5: 1357.2482 | L5: 1378.2017 | M5: 1399.163 | N5: 1420.1243 | O5: 1441.0857 | P5: 1462.047 | Q5: 1483.0083 | R5: 1503.9697 | S5: 1540.74 | T5: 1561.7013 | U5: 1582.6626 | V5: 1603.624 | W5: 1624.5853 | X5: 1645.5466 | Y5: 1666.5079 | Z5: 1687.4693 | AA5: 1708.4228 | AB5: 1729.9158 | AC5: 1750.8771 | AD5: 1771.8384 | AE5: 1792.7998 | AF5: 1813.7611 | AG5: 1834.7224 | AH5: 1855.6838 | AI5: 1876.6451 | AJ5: 1897.6064 | AK5: 1919.0994
A6: ='(patio_costs)'!A7 -> 2300 | B6: 1196.7192 | C6: 1217.6806 | D6: 1238.6419 | E6: 1259.6032 | F6: 1280.5646 | G6: 1301.5259 | H6: 1322.4872 | I6: 1343.4486 | J6: 1364.9337 | K6: 1385.8951 | L6: 1406.8564 | M6: 1427.8177 | N6: 1448.7791 | O6: 1469.7404 | P6: 1490.7017 | Q6: 1526.9403 | R6: 1547.9017 | S6: 1569.3947 | T6: 1590.356 | U6: 1611.3173 | V6: 1632.2787 | W6: 1653.24 | X6: 1674.2013 | Y6: 1695.1548 | Z6: 1716.1162 | AA6: 1737.0775 | AB6: 1758.5705 | AC6: 1779.5318 | AD6: 1800.4932 | AE6: 1821.4545 | AF6: 1842.4158 | AG6: 1863.3771 | AH6: 1884.3385 | AI6: 1905.2998 | AJ6: 1926.2611 | AK6: 1947.7541
A7: ='(patio_costs)'!A8 -> 2400 | B7: 1225.3739 | C7: 1246.3353 | D7: 1267.2966 | E7: 1288.2579 | F7: 1309.2193 | G7: 1330.1806 | H7: 1351.1341 | I7: 1372.0955 | J7: 1393.5884 | K7: 1414.5498 | L7: 1435.5111 | M7: 1456.4724 | N7: 1477.4338 | O7: 1498.3951 | P7: 1534.6337 | Q7: 1555.5951 | R7: 1576.5564 | S7: 1598.0494 | T7: 1619.0107 | U7: 1639.972 | V7: 1660.9256 | W7: 1681.8869 | X7: 1702.8482 | Y7: 1723.8095 | Z7: 1744.7709 | AA7: 1765.7322 | AB7: 1787.2252 | AC7: 1808.1865 | AD7: 1829.1479 | AE7: 1850.1092 | AF7: 1871.0705 | AG7: 1892.0319 | AH7: 1912.9932 | AI7: 1933.9545 | AJ7: 1954.9159 | AK7: 1976.401
A8: ='(patio_costs)'!A9 -> 2500 | B8: 1254.0287 | C8: 1274.99 | D8: 1295.9513 | E8: 1316.9048 | F8: 1337.8662 | G8: 1358.8275 | H8: 1379.7888 | I8: 1400.7502 | J8: 1422.2432 | K8: 1443.2045 | L8: 1464.1658 | M8: 1485.1271 | N8: 1506.0885 | O8: 1542.3271 | P8: 1563.2884 | Q8: 1584.2498 | R8: 1605.2111 | S8: 1626.7041 | T8: 1647.6654 | U8: 1668.6189 | V8: 1689.5803 | W8: 1710.5416 | X8: 1731.5029 | Y8: 1752.4643 | Z8: 1773.4256 | AA8: 1794.3869 | AB8: 1815.8799 | AC8: 1836.8412 | AD8: 1857.8026 | AE8: 1878.7639 | AF8: 1899.7252 | AG8: 1920.6866 | AH8: 1941.6479 | AI8: 1962.6092 | AJ8: 1983.5627 | AK8: 2005.0557
A9: ='(patio_costs)'!A10 -> 2600 | B9: 1282.6834 | C9: 1303.6447 | D9: 1324.5982 | E9: 1345.5595 | F9: 1366.5209 | G9: 1387.4822 | H9: 1408.4435 | I9: 1429.4049 | J9: 1450.8979 | K9: 1471.8592 | L9: 1492.8205 | M9: 1513.7819 | N9: 1550.0205 | O9: 1570.9818 | P9: 1591.9432 | Q9: 1612.9045 | R9: 1633.858 | S9: 1655.351 | T9: 1676.3123 | U9: 1697.2736 | V9: 1718.235 | W9: 1739.1963 | X9: 1760.1576 | Y9: 1781.119 | Z9: 1802.0803 | AA9: 1823.0416 | AB9: 1844.5346 | AC9: 1865.496 | AD9: 1886.4573 | AE9: 1907.4186 | AF9: 1928.3799 | AG9: 1949.3413 | AH9: 1970.2948 | AI9: 1991.2561 | AJ9: 2012.2175 | AK9: 2033.7104
A10: ='(patio_costs)'!A11 -> 2700 | B10: 1311.3303 | C10: 1332.2916 | D10: 1353.2529 | E10: 1374.2143 | F10: 1395.1756 | G10: 1416.1369 | H10: 1437.0983 | I10: 1458.0596 | J10: 1479.5526 | K10: 1500.5139 | L10: 1521.4752 | M10: 1557.7139 | N10: 1578.6752 | O10: 1599.6365 | P10: 1620.59 | Q10: 1641.5514 | R10: 1662.5127 | S10: 1684.0057 | T10: 1704.967 | U10: 1725.9284 | V10: 1746.8897 | W10: 1767.851 | X10: 1788.8124 | Y10: 1809.7737 | Z10: 1830.735 | AA10: 1851.6963 | AB10: 1873.1893 | AC10: 1894.1507 | AD10: 1915.112 | AE10: 1936.0655 | AF10: 1957.0268 | AG10: 1977.9882 | AH10: 1998.9495 | AI10: 2019.9108 | AJ10: 2040.8722 | AK10: 2062.3652

Sheet patio_3
A1: type | B1: matrix | C1: patio_3_
A2: ='(patio_costs)'!A14 | B2: ='(patio_costs)'!B14 -> 2250 | C2: ='(patio_costs)'!C14 -> 2350 | D2: ='(patio_costs)'!D14 -> 2450 | E2: ='(patio_costs)'!E14 -> 2550 | F2: ='(patio_costs)'!F14 -> 2650 | G2: ='(patio_costs)'!G14 -> 2750 | H2: ='(patio_costs)'!H14 -> 2850 | ... BC2: ='(patio_costs)'!BC14 -> 7500
A3: ='(patio_costs)'!A15 -> 2000 | B3: {='(patio_costs)'!B15:BC22*(1+MARKUP!$Z$6)} -> 1648.13453 | C3: 1673.5446 | D3: 1698.9546 | E3: 1724.3647 | F3: 1749.7747 | G3: 1775.1847 | H3: 1800.5948 | I3: 1826.0048 | J3: 1851.4071 | K3: 1876.8171 | L3: 1903.0246 | M3: 1928.4347 | N3: 1953.8447 | O3: 1979.2548 | P3: 2004.6648 | Q3: 2030.067 | R3: 2055.4771 | S3: 2080.8871 | T3: 2106.2972 | U3: 2131.7072 | V3: 2157.1173 | W3: 2182.5273 | X3: 2207.9295 | Y3: 2233.3396 | Z3: 2259.5471 | AA3: 2284.9571 | AB3: 2310.3672 | AC3: 2335.7772 | AD3: 2361.1873 | AE3: 2417.1519 | AF3: 2442.5541 | AG3: 2467.9642 | AH3: 2493.3742 | AI3: 2518.7843 | AJ3: 2544.1943 | AK3: 2569.6044 | AL3: 2595.0144 | AM3: 2621.2141 | AN3: 2646.6242 | AO3: 2672.0342 | AP3: 2697.4442 | AQ3: 2722.8543 | AR3: 2748.2643 | AS3: 2773.6744 | AT3: 2799.0766 | AU3: 2824.4866 | AV3: 2849.8967 | AW3: 2875.3067 | AX3: 2900.7168 | AY3: 2926.1268 | AZ3: 2951.5369 | BA3: 2977.7444 | BB3: 3003.1466 | BC3: 3015.8516
A4: ='(patio_costs)'!A16 -> 2100 | B4: 1688.2277 | C4: 1713.6377 | D4: 1739.0478 | E4: 1764.4578 | F4: 1789.8678 | G4: 1815.2779 | H4: 1840.6801 | I4: 1866.0902 | J4: 1891.5002 | K4: 1916.9102 | L4: 1943.1178 | M4: 1968.5278 | N4: 1993.9379 | O4: 2019.3401 | P4: 2044.7501 | Q4: 2070.1602 | R4: 2095.5702 | S4: 2120.9803 | T4: 2146.3903 | U4: 2171.8003 | V4: 2197.2026 | W4: 2222.6126 | X4: 2248.0227 | Y4: 2273.4327 | Z4: 2299.6402 | AA4: 2325.0503 | AB4: 2365.7376 | AC4: 2406.4171 | AD4: 2431.8272 | AE4: 2457.2372 | AF4: 2482.6473 | AG4: 2508.0573 | AH4: 2533.4674 | AI4: 2558.8774 | AJ4: 2584.2875 | AK4: 2609.6897 | AL4: 2635.0997 | AM4: 2661.3072 | AN4: 2686.7173 | AO4: 2712.1273 | AP4: 2737.5374 | AQ4: 2762.9474 | AR4: 2788.3497 | AS4: 2813.7597 | AT4: 2839.1697 | AU4: 2864.5798 | AV4: 2889.9898 | AW4: 2915.3999 | AX4: 2940.8099 | AY4: 2966.2121 | AZ4: 2991.6222 | BA4: 3017.8297 | BB4: 3043.2398 | BC4: 3055.9448
A5: ='(patio_costs)'!A17 -> 2200 | B5: 1728.3208 | C5: 1753.7309 | D5: 1779.1409 | E5: 1804.5431 | F5: 1829.9532 | G5: 1855.3632 | H5: 1880.7733 | I5: 1906.1833 | J5: 1931.5933 | K5: 1957.0034 | L5: 1983.2031 | M5: 2008.6131 | N5: 2034.0232 | O5: 2059.4332 | P5: 2084.8433 | Q5: 2110.2533 | R5: 2135.6634 | S5: 2161.0656 | T5: 2186.4756 | U5: 2211.8857 | V5: 2237.2957 | W5: 2262.7058 | X5: 2288.1158 | Y5: 2313.5258 | Z5: 2370.288 | AA5: 2395.6902 | AB5: 2421.1002 | AC5: 2446.5103 | AD5: 2471.9203 | AE5: 2497.3304 | AF5: 2522.7404 | AG5: 2548.1505 | AH5: 2573.5605 | AI5: 2598.9627 | AJ5: 2624.3728 | AK5: 2649.7828 | AL5: 2675.1929 | AM5: 2701.4004 | AN5: 2726.8104 | AO5: 2752.2205 | AP5: 2777.6227 | AQ5: 2803.0327 | AR5: 2828.4428 | AS5: 2853.8528 | AT5: 2879.2629 | AU5: 2904.6729 | AV5: 2930.083 | AW5: 2955.4852 | AX5: 2980.8952 | AY5: 3006.3053 | AZ5: 3031.7153 | BA5: 3057.9228 | BB5: 3083.3329 | BC5: 3096.0379
A6: ='(patio_costs)'!A18 -> 2300 | B6: 1768.4139 | C6: 1793.8162 | D6: 1819.2262 | E6: 1844.6363 | F6: 1870.0463 | G6: 1895.4563 | H6: 1920.8664 | I6: 1946.2764 | J6: 1971.6787 | K6: 1997.0887 | L6: 2023.2962 | M6: 2048.7063 | N6: 2074.1163 | O6: 2099.5264 | P6: 2124.9364 | Q6: 2150.3386 | R6: 2175.7487 | S6: 2201.1587 | T6: 2226.5688 | U6: 2251.9788 | V6: 2277.3889 | W6: 2302.7989 | X6: 2358.7557 | Y6: 2384.1658 | Z6: 2410.3733 | AA6: 2435.7833 | AB6: 2461.1934 | AC6: 2486.6034 | AD6: 2512.0135 | AE6: 2537.4235 | AF6: 2562.8257 | AG6: 2588.2358 | AH6: 2613.6458 | AI6: 2639.0559 | AJ6: 2664.4659 | AK6: 2689.876 | AL6: 2715.286 | AM6: 2741.4857 | AN6: 2766.8958 | AO6: 2792.3058 | AP6: 2817.7158 | AQ6: 2843.1259 | AR6: 2868.5359 | AS6: 2893.946 | AT6: 2919.3482 | AU6: 2944.7582 | AV6: 2970.1683 | AW6: 2995.5783 | AX6: 3020.9884 | AY6: 3046.3984 | AZ6: 3071.8085 | BA6: 3098.016 | BB6: 3123.4182 | BC6: 3136.1232
A7: ='(patio_costs)'!A19 -> 2400 | B7: 1808.4993 | C7: 1833.9093 | D7: 1859.3194 | E7: 1884.7294 | F7: 1910.1394 | G7: 1935.5495 | H7: 1960.9517 | I7: 1986.3618 | J7: 2011.7718 | K7: 2037.1818 | L7: 2063.3894 | M7: 2088.7994 | N7: 2114.2095 | O7: 2139.6117 | P7: 2165.0217 | Q7: 2190.4318 | R7: 2215.8418 | S7: 2241.2519 | T7: 2266.6619 | U7: 2292.0719 | V7: 2348.0366 | W7: 2373.4388 | X7: 2398.8489 | Y7: 2424.2589 | Z7: 2450.4664 | AA7: 2475.8765 | AB7: 2501.2865 | AC7: 2526.6887 | AD7: 2552.0988 | AE7: 2577.5088 | AF7: 2602.9189 | AG7: 2628.3289 | AH7: 2653.739 | AI7: 2679.149 | AJ7: 2704.5591 | AK7: 2729.9613 | AL7: 2755.3713 | AM7: 2781.5789 | AN7: 2806.9889 | AO7: 2832.3989 | AP7: 2857.809 | AQ7: 2883.219 | AR7: 2908.6213 | AS7: 2934.0313 | AT7: 2959.4413 | AU7: 2984.8514 | AV7: 3010.2614 | AW7: 3035.6715 | AX7: 3061.0815 | AY7: 3086.4916 | AZ7: 3111.8938 | BA7: 3138.1013 | BB7: 3163.5114 | BC7: 3176.2164
A8: ='(patio_costs)'!A20 -> 2500 | B8: 1848.5924 | C8: 1874.0025 | D8: 1899.4125 | E8: 1924.8147 | F8: 1950.2248 | G8: 1975.6348 | H8: 2001.0449 | I8: 2026.4549 | J8: 2051.8649 | K8: 2077.275 | L8: 2103.4825 | M8: 2128.8847 | N8: 2154.2948 | O8: 2179.7048 | P8: 2205.1149 | Q8: 2230.5249 | R8: 2255.935 | S8: 2281.345 | T8: 2322.0245 | U8: 2362.7119 | V8: 2388.1219 | W8: 2413.532 | X8: 2438.942 | Y8: 2464.352 | Z8: 2490.5596 | AA8: 2515.9618 | AB8: 2541.3718 | AC8: 2566.7819 | AD8: 2592.1919 | AE8: 2617.602 | AF8: 2643.012 | AG8: 2668.4221 | AH8: 2693.8321 | AI8: 2719.2343 | AJ8: 2744.6444 | AK8: 2770.0544 | AL8: 2795.4645 | AM8: 2821.672 | AN8: 2847.082 | AO8: 2872.4921 | AP8: 2897.8943 | AQ8: 2923.3043 | AR8: 2948.7144 | AS8: 2974.1244 | AT8: 2999.5345 | AU8: 3024.9445 | AV8: 3050.3546 | AW8: 3075.7568 | AX8: 3101.1668 | AY8: 3126.5769 | AZ8: 3151.9869 | BA8: 3178.1945 | BB8: 3203.6045 | BC8: 3216.3095
A9: ='(patio_costs)'!A21 -> 2600 | B9: 1888.6856 | C9: 1914.0878 | D9: 1939.4978 | E9: 1964.9079 | F9: 1990.3179 | G9: 2015.728 | H9: 2041.138 | I9: 2066.548 | J9: 2091.9503 | K9: 2117.3603 | L9: 2143.5678 | M9: 2168.9779 | N9: 2194.3879 | O9: 2219.798 | P9: 2245.208 | Q9: 2270.6102 | R9: 2311.2976 | S9: 2351.9849 | T9: 2377.395 | U9: 2402.805 | V9: 2428.2151 | W9: 2453.6251 | X9: 2479.0273 | Y9: 2504.4374 | Z9: 2530.6449 | AA9: 2556.0549 | AB9: 2581.465 | AC9: 2606.875 | AD9: 2632.2851 | AE9: 2657.6951 | AF9: 2683.0973 | AG9: 2708.5074 | AH9: 2733.9174 | AI9: 2759.3275 | AJ9: 2784.7375 | AK9: 2810.1476 | AL9: 2835.5576 | AM9: 2861.7573 | AN9: 2887.1674 | AO9: 2912.5774 | AP9: 2937.9874 | AQ9: 2963.3975 | AR9: 2988.8075 | AS9: 3014.2176 | AT9: 3039.6198 | AU9: 3065.0298 | AV9: 3090.4399 | AW9: 3115.8499 | AX9: 3141.26 | AY9: 3166.67 | AZ9: 3192.0801 | BA9: 3218.2798 | BB9: 3243.6898 | BC9: 3256.3948
A10: ='(patio_costs)'!A22 -> 2700 | B10: 1928.7709 | C10: 1954.1809 | D10: 1979.591 | E10: 2005.001 | F10: 2030.411 | G10: 2055.8211 | H10: 2081.2233 | I10: 2106.6334 | J10: 2132.0434 | K10: 2157.4534 | L10: 2183.661 | M10: 2209.071 | N10: 2234.4811 | O10: 2259.8833 | P10: 2285.2933 | Q10: 2341.258 | R10: 2366.668 | S10: 2392.0781 | T10: 2417.4881 | U10: 2442.8982 | V10: 2468.3004 | W10: 2493.7104 | X10: 2519.1205 | Y10: 2544.5305 | Z10: 2570.738 | AA10: 2596.1481 | AB10: 2621.5581 | AC10: 2646.9603 | AD10: 2672.3704 | AE10: 2697.7804 | AF10: 2723.1905 | AG10: 2748.6005 | AH10: 2774.0106 | AI10: 2799.4206 | AJ10: 2824.8307 | AK10: 2850.2329 | AL10: 2875.6429 | AM10: 2901.8505 | AN10: 2927.2605 | AO10: 2952.6705 | AP10: 2978.0806 | AQ10: 3003.4906 | AR10: 3028.8929 | AS10: 3054.3029 | AT10: 3079.7129 | AU10: 3105.123 | AV10: 3130.533 | AW10: 3155.9431 | AX10: 3181.3531 | AY10: 3206.7632 | AZ10: 3232.1654 | BA10: 3258.3729 | BB10: 3283.783 | BC10: 3267.7785

Sheet patio_4
A1: type | B1: matrix | C1: patio_4_
A2: ='(patio_costs)'!A25 | B2: ='(patio_costs)'!B25 -> 2800 | C2: ='(patio_costs)'!C25 -> 2900 | D2: ='(patio_costs)'!D25 -> 3000 | E2: ='(patio_costs)'!E25 -> 3100 | F2: ='(patio_costs)'!F25 -> 3200 | G2: ='(patio_costs)'!G25 -> 3300 | H2: ='(patio_costs)'!H25 -> 3400 | ... BV2: ='(patio_costs)'!BV25 -> 10000
A3: ='(patio_costs)'!A26 -> 2000 | B3: {='(patio_costs)'!B26:BV33*(1+MARKUP!$Z$6)} -> 1936.362611 | C3: 1957.3239 | D3: 1978.2853 | E3: 1999.2466 | F3: 2020.2079 | G3: 2041.1693 | H3: 2062.1228 | I3: 2083.0841 | J3: 2104.0454 | K3: 2125.0068 | L3: 2145.9681 | M3: 2166.9294 | N3: 2187.8908 | O3: 2208.8521 | P3: 2229.8134 | Q3: 2250.7748 | R3: 2272.7994 | S3: 2293.7607 | T3: 2314.7221 | U3: 2335.6834 | V3: 2356.6447 | W3: 2377.5982 | X3: 2398.5596 | Y3: 2419.5209 | Z3: 2440.4822 | AA3: 2461.4436 | AB3: 2482.4049 | AC3: 2503.3662 | AD3: 2524.3276 | AE3: 2545.2889 | AF3: 2566.2502 | AG3: 2587.2116 | AH3: 2608.1729 | AI3: 2629.1342 | AJ3: 2651.1589 | AK3: 2672.1202 | AL3: 2693.0737 | AM3: 2714.035 | AN3: 2734.9964 | AO3: 2771.235 | AP3: 2792.1963 | AQ3: 2828.435 | AR3: 2849.3963 | AS3: 2870.3576 | AT3: 2891.319 | AU3: 2912.2803 | AV3: 2933.2416 | AW3: 2954.203 | AX3: 2975.1643 | AY3: 2996.1256 | AZ3: 3017.0791 | BA3: 3038.0405 | BB3: 3060.0651 | BC3: 3081.0264 | BD3: 3101.9878 | BE3: 3122.9491 | BF3: 3143.9104 | BG3: 3164.8718 | BH3: 3185.8331 | BI3: 3206.7944 | BJ3: 3227.7558 | BK3: 3248.7171 | BL3: 3269.6784 | BM3: 3290.6398 | BN3: 3311.5933 | BO3: 3332.5624 | BP3: 3353.5159 | BQ3: 3374.4773 | BR3: 3395.4386 | BS3: 3416.3999 | BT3: 3438.4246 | BU3: 3459.3859 | BV3: 3480.3472
A4: ='(patio_costs)'!A27 -> 2100 | B4: 1984.196 | C4: 2005.1574 | D4: 2026.1187 | E4: 2047.08 | F4: 2068.0414 | G4: 2089.0027 | H4: 2109.964 | I4: 2130.9254 | J4: 2151.8867 | K4: 2172.848 | L4: 2193.8015 | M4: 2214.7629 | N4: 2235.7242 | O4: 2256.6855 | P4: 2277.6469 | Q4: 2298.6082 | R4: 2320.6328 | S4: 2341.5942 | T4: 2362.5555 | U4: 2383.5168 | V4: 2404.4782 | W4: 2425.4395 | X4: 2446.4008 | Y4: 2467.3622 | Z4: 2488.3157 | AA4: 2509.277 | AB4: 2530.2383 | AC4: 2551.1997 | AD4: 2572.161 | AE4: 2593.1223 | AF4: 2614.0837 | AG4: 2635.045 | AH4: 2656.0063 | AI4: 2676.9677 | AJ4: 2698.9923 | AK4: 2735.2309 | AL4: 2756.1923 | AM4: 2792.4309 | AN4: 2813.3844 | AO4: 2834.3536 | AP4: 2855.3071 | AQ4: 2876.2684 | AR4: 2897.2297 | AS4: 2918.1911 | AT4: 2939.1524 | AU4: 2960.1137 | AV4: 2981.0751 | AW4: 3002.0364 | AX4: 3022.9977 | AY4: 3043.9591 | AZ4: 3064.9204 | BA4: 3085.8817 | BB4: 3107.9064 | BC4: 3128.8677 | BD4: 3149.8212 | BE4: 3170.7825 | BF4: 3191.7439 | BG4: 3212.7052 | BH4: 3233.6665 | BI4: 3254.6279 | BJ4: 3275.5892 | BK4: 3296.5505 | BL4: 3317.5119 | BM4: 3338.4732 | BN4: 3359.4345 | BO4: 3380.3959 | BP4: 3401.3572 | BQ4: 3422.3185 | BR4: 3443.2798 | BS4: 3464.2334 | BT4: 3486.2658 | BU4: 3507.2193 | BV4: 3528.1807
A5: ='(patio_costs)'!A28 -> 2200 | B5: 2032.0295 | C5: 2052.9908 | D5: 2073.9521 | E5: 2094.9135 | F5: 2115.8748 | G5: 2136.8361 | H5: 2157.7975 | I5: 2178.7588 | J5: 2199.7201 | K5: 2220.6815 | L5: 2241.6428 | M5: 2262.6041 | N5: 2283.5654 | O5: 2304.5268 | P5: 2325.4803 | Q5: 2346.4494 | R5: 2368.4663 | S5: 2389.4276 | T5: 2410.3889 | U5: 2431.3503 | V5: 2452.3116 | W5: 2473.2729 | X5: 2494.2343 | Y5: 2515.1956 | Z5: 2536.1569 | AA5: 2557.1183 | AB5: 2578.0796 | AC5: 2599.0409 | AD5: 2619.9944 | AE5: 2640.9558 | AF5: 2661.9171 | AG5: 2682.8784 | AH5: 2719.1171 | AI5: 2740.0784 | AJ5: 2777.3803 | AK5: 2798.3417 | AL5: 2819.303 | AM5: 2840.2643 | AN5: 2861.2257 | AO5: 2882.187 | AP5: 2903.1483 | AQ5: 2924.1096 | AR5: 2945.071 | AS5: 2966.0323 | AT5: 2986.9936 | AU5: 3007.9472 | AV5: 3028.9085 | AW5: 3049.8698 | AX5: 3070.8312 | AY5: 3091.7925 | AZ5: 3112.7538 | BA5: 3133.7151 | BB5: 3155.7398 | BC5: 3176.7011 | BD5: 3197.6625 | BE5: 3218.6238 | BF5: 3239.5851 | BG5: 3260.5464 | BH5: 3281.5078 | BI5: 3302.4613 | BJ5: 3323.4226 | BK5: 3344.384 | BL5: 3365.3453 | BM5: 3386.3066 | BN5: 3407.2679 | BO5: 3428.2293 | BP5: 3449.1906 | BQ5: 3470.1519 | BR5: 3491.1133 | BS5: 3512.0746 | BT5: 3534.0993 | BU5: 3555.0606 | BV5: 3576.0219
A6: ='(patio_costs)'!A29 -> 2300 | B6: 2079.8707 | C6: 2100.8321 | D6: 2121.7934 | E6: 2142.7469 | F6: 2163.7082 | G6: 2184.6696 | H6: 2205.6309 | I6: 2226.5922 | J6: 2247.5536 | K6: 2268.5149 | L6: 2289.4762 | M6: 2310.4375 | N6: 2331.3989 | O6: 2352.3602 | P6: 2373.3215 | Q6: 2394.2829 | R6: 2416.3075 | S6: 2437.261 | T6: 2458.2302 | U6: 2479.1837 | V6: 2500.145 | W6: 2521.1064 | X6: 2542.0677 | Y6: 2563.029 | Z6: 2583.9904 | AA6: 2604.9517 | AB6: 2625.913 | AC6: 2646.8743 | AD6: 2667.8357 | AE6: 2704.0743 | AF6: 2725.0356 | AG6: 2761.2743 | AH6: 2782.2356 | AI6: 2803.1891 | AJ6: 2825.2216 | AK6: 2846.1751 | AL6: 2867.1364 | AM6: 2888.0978 | AN6: 2909.0591 | AO6: 2930.0204 | AP6: 2950.9817 | AQ6: 2971.9431 | AR6: 2992.9044 | AS6: 3013.8657 | AT6: 3034.8271 | AU6: 3055.7884 | AV6: 3076.7497 | AW6: 3097.7033 | AX6: 3118.6724 | AY6: 3139.6259 | AZ6: 3160.5872 | BA6: 3181.5486 | BB6: 3203.5732 | BC6: 3224.5346 | BD6: 3245.4959 | BE6: 3266.4572 | BF6: 3287.4185 | BG6: 3308.3799 | BH6: 3329.3412 | BI6: 3350.3025 | BJ6: 3371.2639 | BK6: 3392.2252 | BL6: 3413.1787 | BM6: 3434.14 | BN6: 3455.1014 | BO6: 3476.0627 | BP6: 3497.024 | BQ6: 3517.9854 | BR6: 3538.9467 | BS6: 3559.908 | BT6: 3581.9327 | BU6: 3602.894 | BV6: 3623.8553
A7: ='(patio_costs)'!A30 -> 2400 | B7: 2127.7041 | C7: 2148.6655 | D7: 2169.6268 | E7: 2190.5881 | F7: 2211.5495 | G7: 2232.5108 | H7: 2253.4721 | I7: 2274.4257 | J7: 2295.387 | K7: 2316.3483 | L7: 2337.3096 | M7: 2358.271 | N7: 2379.2323 | O7: 2400.1936 | P7: 2421.155 | Q7: 2442.1163 | R7: 2464.1409 | S7: 2485.1023 | T7: 2506.0636 | U7: 2527.0249 | V7: 2547.9863 | W7: 2568.9476 | X7: 2589.9011 | Y7: 2610.8624 | Z7: 2631.8238 | AA7: 2652.7851 | AB7: 2673.7464 | AC7: 2709.9851 | AD7: 2730.9464 | AE7: 2767.185 | AF7: 2788.1464 | AG7: 2809.1077 | AH7: 2830.069 | AI7: 2851.0304 | AJ7: 2873.055 | AK7: 2894.0163 | AL7: 2914.9777 | AM7: 2935.9312 | AN7: 2956.8925 | AO7: 2977.8538 | AP7: 2998.8152 | AQ7: 3019.7765 | AR7: 3040.7378 | AS7: 3061.6992 | AT7: 3082.6605 | AU7: 3103.6218 | AV7: 3124.5832 | AW7: 3145.5445 | AX7: 3166.5058 | AY7: 3187.4672 | AZ7: 3208.4285 | BA7: 3229.3898 | BB7: 3251.4067 | BC7: 3272.3758 | BD7: 3293.3293 | BE7: 3314.2906 | BF7: 3335.252 | BG7: 3356.2133 | BH7: 3377.1746 | BI7: 3398.136 | BJ7: 3419.0973 | BK7: 3440.0586 | BL7: 3461.02 | BM7: 3481.9813 | BN7: 3502.9426 | BO7: 3523.904 | BP7: 3544.8653 | BQ7: 3565.8266 | BR7: 3586.7801 | BS7: 3607.7415 | BT7: 3629.7661 | BU7: 3650.7274 | BV7: 3671.6888
A8: ='(patio_costs)'!A31 -> 2500 | B8: 2175.5376 | C8: 2196.4989 | D8: 2217.4602 | E8: 2238.4216 | F8: 2259.3829 | G8: 2280.3442 | H8: 2301.3056 | I8: 2322.2669 | J8: 2343.2282 | K8: 2364.1896 | L8: 2385.1509 | M8: 2406.1122 | N8: 2427.0657 | O8: 2448.0271 | P8: 2468.9884 | Q8: 2489.9497 | R8: 2511.9744 | S8: 2532.9357 | T8: 2553.897 | U8: 2574.8584 | V8: 2595.8197 | W8: 2616.781 | X8: 2637.7424 | Y8: 2658.7037 | Z8: 2694.9423 | AA8: 2715.9037 | AB8: 2752.1423 | AC8: 2773.1036 | AD8: 2794.0571 | AE8: 2815.0185 | AF8: 2835.9798 | AG8: 2856.9411 | AH8: 2877.9025 | AI8: 2898.8638 | AJ8: 2920.8884 | AK8: 2941.8498 | AL8: 2962.8111 | AM8: 2983.7724 | AN8: 3004.7338 | AO8: 3025.6951 | AP8: 3046.6564 | AQ8: 3067.6178 | AR8: 3088.5713 | AS8: 3109.5326 | AT8: 3130.4939 | AU8: 3151.4553 | AV8: 3172.4166 | AW8: 3193.3779 | AX8: 3214.3393 | AY8: 3235.3006 | AZ8: 3256.2619 | BA8: 3277.2233 | BB8: 3299.2479 | BC8: 3320.2092 | BD8: 3341.1706 | BE8: 3362.1241 | BF8: 3383.0854 | BG8: 3404.0467 | BH8: 3425.0081 | BI8: 3445.9694 | BJ8: 3466.9307 | BK8: 3487.8921 | BL8: 3508.8534 | BM8: 3529.8147 | BN8: 3550.7761 | BO8: 3571.7374 | BP8: 3592.6987 | BQ8: 3613.6601 | BR8: 3634.6214 | BS8: 3655.5827 | BT8: 3677.6074 | BU8: 3698.5609 | BV8: 3719.5222
A9: ='(patio_costs)'!A32 -> 2600 | B9: 2223.3788 | C9: 2244.3323 | D9: 2265.2937 | E9: 2286.255 | F9: 2307.2163 | G9: 2328.1777 | H9: 2349.139 | I9: 2370.1003 | J9: 2391.0617 | K9: 2412.023 | L9: 2432.9843 | M9: 2453.9457 | N9: 2474.907 | O9: 2495.8683 | P9: 2516.8218 | Q9: 2537.791 | R9: 2559.8078 | S9: 2580.7691 | T9: 2601.7305 | U9: 2622.6918 | V9: 2643.6531 | W9: 2664.6145 | X9: 2700.8531 | Y9: 2721.8144 | Z9: 2758.0531 | AA9: 2779.0144 | AB9: 2799.9757 | AC9: 2820.9371 | AD9: 2841.8984 | AE9: 2862.8519 | AF9: 2883.821 | AG9: 2904.7746 | AH9: 2925.7359 | AI9: 2946.6972 | AJ9: 2968.7219 | AK9: 2989.6832 | AL9: 3010.6445 | AM9: 3031.6059 | AN9: 3052.5672 | AO9: 3073.5285 | AP9: 3094.4899 | AQ9: 3115.4512 | AR9: 3136.4125 | AS9: 3157.3739 | AT9: 3178.3352 | AU9: 3199.2887 | AV9: 3220.25 | AW9: 3241.2114 | AX9: 3262.1727 | AY9: 3283.134 | AZ9: 3304.0954 | BA9: 3325.0567 | BB9: 3347.0813 | BC9: 3368.0427 | BD9: 3389.004 | BE9: 3409.9653 | BF9: 3430.9267 | BG9: 3451.888 | BH9: 3472.8493 | BI9: 3493.8106 | BJ9: 3514.772 | BK9: 3535.7255 | BL9: 3556.6868 | BM9: 3577.6482 | BN9: 3598.6095 | BO9: 3619.5708 | BP9: 3640.5322 | BQ9: 3661.4935 | BR9: 3682.4548 | BS9: 3703.4161 | BT9: 3725.4408 | BU9: 3746.4021 | BV9: 3767.3635
A10: ='(patio_costs)'!A33 -> 2700 | B10: 2271.2123 | C10: 2292.1736 | D10: 2313.1349 | E10: 2334.0963 | F10: 2355.0576 | G10: 2376.0111 | H10: 2396.9724 | I10: 2417.9338 | J10: 2438.8951 | K10: 2459.8564 | L10: 2480.8178 | M10: 2501.7791 | N10: 2522.7404 | O10: 2543.7017 | P10: 2564.6631 | Q10: 2585.6244 | R10: 2607.6491 | S10: 2628.6104 | T10: 2649.5717 | U10: 2670.5252 | V10: 2706.7717 | W10: 2727.7252 | X10: 2763.9638 | Y10: 2784.9252 | Z10: 2805.8865 | AA10: 2826.8478 | AB10: 2847.8092 | AC10: 2868.7705 | AD10: 2889.7318 | AE10: 2910.6931 | AF10: 2931.6545 | AG10: 2952.6158 | AH10: 2973.5771 | AI10: 2994.5385 | AJ10: 3016.5631 | AK10: 3037.5244 | AL10: 3058.478 | AM10: 3079.4393 | AN10: 3100.4006 | AO10: 3121.362 | AP10: 3142.3233 | AQ10: 3163.2846 | AR10: 3184.246 | AS10: 3205.2073 | AT10: 3226.1686 | AU10: 3247.1299 | AV10: 3268.0913 | AW10: 3289.0526 | AX10: 3310.0139 | AY10: 3330.9753 | AZ10: 3351.9288 | BA10: 3372.8901 | BB10: 3394.9148 | BC10: 3415.8761 | BD10: 3436.8374 | BE10: 3457.7988 | BF10: 3478.7601 | BG10: 3499.7214 | BH10: 3520.6827 | BI10: 3541.6441 | BJ10: 3562.6054 | BK10: 3583.5667 | BL10: 3604.5281 | BM10: 3625.4894 | BN10: 3646.4429 | BO10: 3667.4042 | BP10: 3688.3656 | BQ10: 3709.3269 | BR10: 3730.2882 | BS10: 3751.2496 | BT10: 3773.2742 | BU10: 3765.5261 | BV10: 3786.4874

Sheet Ultra_patio_2
A1: type | B1: matrix | C1: cortizo_patio_2_
A2: ='(patio_costs)'!A3 | B2: ='(patio_costs)'!B3 -> 1500 | C2: ='(patio_costs)'!C3 -> 1600 | D2: ='(patio_costs)'!D3 -> 1700 | E2: ='(patio_costs)'!E3 -> 1800 | F2: ='(patio_costs)'!F3 -> 1900 | G2: ='(patio_costs)'!G3 -> 2000 | H2: ='(patio_costs)'!H3 -> 2100 | ... AK2: ='(patio_costs)'!AK3 -> 5000
A3: ='(patio_costs)'!A4 -> 2000 | B3: {='(patio_costs)'!B4:AK11*(1+MARKUP!$Z$6)} -> 1110.755106 | C3: 1131.7164 | D3: 1152.6778 | E3: 1173.6391 | F3: 1194.6004 | G3: 1215.5618 | H3: 1236.5231 | I3: 1257.4844 | J3: 1278.9774 | K3: 1299.9387 | L3: 1320.9001 | M3: 1341.8614 | N3: 1362.8227 | O3: 1383.7841 | P3: 1404.7376 | Q3: 1425.6989 | R3: 1446.6602 | S3: 1468.1532 | T3: 1489.1146 | U3: 1510.0759 | V3: 1546.3145 | W3: 1567.2759 | X3: 1588.2372 | Y3: 1609.1985 | Z3: 1630.1599 | AA3: 1651.1212 | AB3: 1672.6142 | AC3: 1693.5755 | AD3: 1714.5368 | AE3: 1735.4904 | AF3: 1756.4517 | AG3: 1777.413 | AH3: 1798.3743 | AI3: 1819.3357 | AJ3: 1840.297 | AK3: 1861.79
A4: ='(patio_costs)'!A5 -> 2100 | B4: 1139.4098 | C4: 1160.3711 | D4: 1181.3325 | E4: 1202.2938 | F4: 1223.2551 | G4: 1244.2165 | H4: 1265.1778 | I4: 1286.1391 | J4: 1307.6321 | K4: 1328.5935 | L4: 1349.5548 | M4: 1370.5161 | N4: 1391.4696 | O4: 1412.431 | P4: 1433.3923 | Q4: 1454.3536 | R4: 1475.315 | S4: 1496.8079 | T4: 1533.0466 | U4: 1554.0079 | V4: 1574.9692 | W4: 1595.9306 | X4: 1616.8919 | Y4: 1637.8532 | Z4: 1658.8146 | AA4: 1679.7759 | AB4: 1701.2689 | AC4: 1722.2224 | AD4: 1743.1837 | AE4: 1764.1451 | AF4: 1785.1064 | AG4: 1806.0677 | AH4: 1827.0291 | AI4: 1847.9904 | AJ4: 1868.9517 | AK4: 1890.4447
A5: ='(patio_costs)'!A6 -> 2200 | B5: 1168.0645 | C5: 1189.0259 | D5: 1209.9872 | E5: 1230.9485 | F5: 1251.9099 | G5: 1272.8712 | H5: 1293.8325 | I5: 1314.7938 | J5: 1336.2868 | K5: 1357.2482 | L5: 1378.2017 | M5: 1399.163 | N5: 1420.1243 | O5: 1441.0857 | P5: 1462.047 | Q5: 1483.0083 | R5: 1503.9697 | S5: 1540.74 | T5: 1561.7013 | U5: 1582.6626 | V5: 1603.624 | W5: 1624.5853 | X5: 1645.5466 | Y5: 1666.5079 | Z5: 1687.4693 | AA5: 1708.4228 | AB5: 1729.9158 | AC5: 1750.8771 | AD5: 1771.8384 | AE5: 1792.7998 | AF5: 1813.7611 | AG5: 1834.7224 | AH5: 1855.6838 | AI5: 1876.6451 | AJ5: 1897.6064 | AK5: 1919.0994
A6: ='(patio_costs)'!A7 -> 2300 | B6: 1196.7192 | C6: 1217.6806 | D6: 1238.6419 | E6: 1259.6032 | F6: 1280.5646 | G6: 1301.5259 | H6: 1322.4872 | I6: 1343.4486 | J6: 1364.9337 | K6: 1385.8951 | L6: 1406.8564 | M6: 1427.8177 | N6: 1448.7791 | O6: 1469.7404 | P6: 1490.7017 | Q6: 1526.9403 | R6: 1547.9017 | S6: 1569.3947 | T6: 1590.356 | U6: 1611.3173 | V6: 1632.2787 | W6: 1653.24 | X6: 1674.2013 | Y6: 1695.1548 | Z6: 1716.1162 | AA6: 1737.0775 | AB6: 1758.5705 | AC6: 1779.5318 | AD6: 1800.4932 | AE6: 1821.4545 | AF6: 1842.4158 | AG6: 1863.3771 | AH6: 1884.3385 | AI6: 1905.2998 | AJ6: 1926.2611 | AK6: 1947.7541
A7: ='(patio_costs)'!A8 -> 2400 | B7: 1225.3739 | C7: 1246.3353 | D7: 1267.2966 | E7: 1288.2579 | F7: 1309.2193 | G7: 1330.1806 | H7: 1351.1341 | I7: 1372.0955 | J7: 1393.5884 | K7: 1414.5498 | L7: 1435.5111 | M7: 1456.4724 | N7: 1477.4338 | O7: 1498.3951 | P7: 1534.6337 | Q7: 1555.5951 | R7: 1576.5564 | S7: 1598.0494 | T7: 1619.0107 | U7: 1639.972 | V7: 1660.9256 | W7: 1681.8869 | X7: 1702.8482 | Y7: 1723.8095 | Z7: 1744.7709 | AA7: 1765.7322 | AB7: 1787.2252 | AC7: 1808.1865 | AD7: 1829.1479 | AE7: 1850.1092 | AF7: 1871.0705 | AG7: 1892.0319 | AH7: 1912.9932 | AI7: 1933.9545 | AJ7: 1954.9159 | AK7: 1976.401
A8: ='(patio_costs)'!A9 -> 2500 | B8: 1254.0287 | C8: 1274.99 | D8: 1295.9513 | E8: 1316.9048 | F8: 1337.8662 | G8: 1358.8275 | H8: 1379.7888 | I8: 1400.7502 | J8: 1422.2432 | K8: 1443.2045 | L8: 1464.1658 | M8: 1485.1271 | N8: 1506.0885 | O8: 1542.3271 | P8: 1563.2884 | Q8: 1584.2498 | R8: 1605.2111 | S8: 1626.7041 | T8: 1647.6654 | U8: 1668.6189 | V8: 1689.5803 | W8: 1710.5416 | X8: 1731.5029 | Y8: 1752.4643 | Z8: 1773.4256 | AA8: 1794.3869 | AB8: 1815.8799 | AC8: 1836.8412 | AD8: 1857.8026 | AE8: 1878.7639 | AF8: 1899.7252 | AG8: 1920.6866 | AH8: 1941.6479 | AI8: 1962.6092 | AJ8: 1983.5627 | AK8: 2005.0557
A9: ='(patio_costs)'!A10 -> 2600 | B9: 1282.6834 | C9: 1303.6447 | D9: 1324.5982 | E9: 1345.5595 | F9: 1366.5209 | G9: 1387.4822 | H9: 1408.4435 | I9: 1429.4049 | J9: 1450.8979 | K9: 1471.8592 | L9: 1492.8205 | M9: 1513.7819 | N9: 1550.0205 | O9: 1570.9818 | P9: 1591.9432 | Q9: 1612.9045 | R9: 1633.858 | S9: 1655.351 | T9: 1676.3123 | U9: 1697.2736 | V9: 1718.235 | W9: 1739.1963 | X9: 1760.1576 | Y9: 1781.119 | Z9: 1802.0803 | AA9: 1823.0416 | AB9: 1844.5346 | AC9: 1865.496 | AD9: 1886.4573 | AE9: 1907.4186 | AF9: 1928.3799 | AG9: 1949.3413 | AH9: 1970.2948 | AI9: 1991.2561 | AJ9: 2012.2175 | AK9: 2033.7104
A10: ='(patio_costs)'!A11 -> 2700 | B10: 1311.3303 | C10: 1332.2916 | D10: 1353.2529 | E10: 1374.2143 | F10: 1395.1756 | G10: 1416.1369 | H10: 1437.0983 | I10: 1458.0596 | J10: 1479.5526 | K10: 1500.5139 | L10: 1521.4752 | M10: 1557.7139 | N10: 1578.6752 | O10: 1599.6365 | P10: 1620.59 | Q10: 1641.5514 | R10: 1662.5127 | S10: 1684.0057 | T10: 1704.967 | U10: 1725.9284 | V10: 1746.8897 | W10: 1767.851 | X10: 1788.8124 | Y10: 1809.7737 | Z10: 1830.735 | AA10: 1851.6963 | AB10: 1873.1893 | AC10: 1894.1507 | AD10: 1915.112 | AE10: 1936.0655 | AF10: 1957.0268 | AG10: 1977.9882 | AH10: 1998.9495 | AI10: 2019.9108 | AJ10: 2040.8722 | AK10: 2062.3652

Sheet Ultra_patio_3
A1: type | B1: matrix | C1: cortizo_patio_3_
A2: ='(patio_costs)'!A14 | B2: ='(patio_costs)'!B14 -> 2250 | C2: ='(patio_costs)'!C14 -> 2350 | D2: ='(patio_costs)'!D14 -> 2450 | E2: ='(patio_costs)'!E14 -> 2550 | F2: ='(patio_costs)'!F14 -> 2650 | G2: ='(patio_costs)'!G14 -> 2750 | H2: ='(patio_costs)'!H14 -> 2850 | ... BC2: ='(patio_costs)'!BC14 -> 7500
A3: ='(patio_costs)'!A15 -> 2000 | B3: {='(patio_costs)'!B15:BC22*(1+MARKUP!$Z$6)} -> 1648.13453 | C3: 1673.5446 | D3: 1698.9546 | E3: 1724.3647 | F3: 1749.7747 | G3: 1775.1847 | H3: 1800.5948 | I3: 1826.0048 | J3: 1851.4071 | K3: 1876.8171 | L3: 1903.0246 | M3: 1928.4347 | N3: 1953.8447 | O3: 1979.2548 | P3: 2004.6648 | Q3: 2030.067 | R3: 2055.4771 | S3: 2080.8871 | T3: 2106.2972 | U3: 2131.7072 | V3: 2157.1173 | W3: 2182.5273 | X3: 2207.9295 | Y3: 2233.3396 | Z3: 2259.5471 | AA3: 2284.9571 | AB3: 2310.3672 | AC3: 2335.7772 | AD3: 2361.1873 | AE3: 2417.1519 | AF3: 2442.5541 | AG3: 2467.9642 | AH3: 2493.3742 | AI3: 2518.7843 | AJ3: 2544.1943 | AK3: 2569.6044 | AL3: 2595.0144 | AM3: 2621.2141 | AN3: 2646.6242 | AO3: 2672.0342 | AP3: 2697.4442 | AQ3: 2722.8543 | AR3: 2748.2643 | AS3: 2773.6744 | AT3: 2799.0766 | AU3: 2824.4866 | AV3: 2849.8967 | AW3: 2875.3067 | AX3: 2900.7168 | AY3: 2926.1268 | AZ3: 2951.5369 | BA3: 2977.7444 | BB3: 3003.1466 | BC3: 3015.8516
A4: ='(patio_costs)'!A16 -> 2100 | B4: 1688.2277 | C4: 1713.6377 | D4: 1739.0478 | E4: 1764.4578 | F4: 1789.8678 | G4: 1815.2779 | H4: 1840.6801 | I4: 1866.0902 | J4: 1891.5002 | K4: 1916.9102 | L4: 1943.1178 | M4: 1968.5278 | N4: 1993.9379 | O4: 2019.3401 | P4: 2044.7501 | Q4: 2070.1602 | R4: 2095.5702 | S4: 2120.9803 | T4: 2146.3903 | U4: 2171.8003 | V4: 2197.2026 | W4: 2222.6126 | X4: 2248.0227 | Y4: 2273.4327 | Z4: 2299.6402 | AA4: 2325.0503 | AB4: 2365.7376 | AC4: 2406.4171 | AD4: 2431.8272 | AE4: 2457.2372 | AF4: 2482.6473 | AG4: 2508.0573 | AH4: 2533.4674 | AI4: 2558.8774 | AJ4: 2584.2875 | AK4: 2609.6897 | AL4: 2635.0997 | AM4: 2661.3072 | AN4: 2686.7173 | AO4: 2712.1273 | AP4: 2737.5374 | AQ4: 2762.9474 | AR4: 2788.3497 | AS4: 2813.7597 | AT4: 2839.1697 | AU4: 2864.5798 | AV4: 2889.9898 | AW4: 2915.3999 | AX4: 2940.8099 | AY4: 2966.2121 | AZ4: 2991.6222 | BA4: 3017.8297 | BB4: 3043.2398 | BC4: 3055.9448
A5: ='(patio_costs)'!A17 -> 2200 | B5: 1728.3208 | C5: 1753.7309 | D5: 1779.1409 | E5: 1804.5431 | F5: 1829.9532 | G5: 1855.3632 | H5: 1880.7733 | I5: 1906.1833 | J5: 1931.5933 | K5: 1957.0034 | L5: 1983.2031 | M5: 2008.6131 | N5: 2034.0232 | O5: 2059.4332 | P5: 2084.8433 | Q5: 2110.2533 | R5: 2135.6634 | S5: 2161.0656 | T5: 2186.4756 | U5: 2211.8857 | V5: 2237.2957 | W5: 2262.7058 | X5: 2288.1158 | Y5: 2313.5258 | Z5: 2370.288 | AA5: 2395.6902 | AB5: 2421.1002 | AC5: 2446.5103 | AD5: 2471.9203 | AE5: 2497.3304 | AF5: 2522.7404 | AG5: 2548.1505 | AH5: 2573.5605 | AI5: 2598.9627 | AJ5: 2624.3728 | AK5: 2649.7828 | AL5: 2675.1929 | AM5: 2701.4004 | AN5: 2726.8104 | AO5: 2752.2205 | AP5: 2777.6227 | AQ5: 2803.0327 | AR5: 2828.4428 | AS5: 2853.8528 | AT5: 2879.2629 | AU5: 2904.6729 | AV5: 2930.083 | AW5: 2955.4852 | AX5: 2980.8952 | AY5: 3006.3053 | AZ5: 3031.7153 | BA5: 3057.9228 | BB5: 3083.3329 | BC5: 3096.0379
A6: ='(patio_costs)'!A18 -> 2300 | B6: 1768.4139 | C6: 1793.8162 | D6: 1819.2262 | E6: 1844.6363 | F6: 1870.0463 | G6: 1895.4563 | H6: 1920.8664 | I6: 1946.2764 | J6: 1971.6787 | K6: 1997.0887 | L6: 2023.2962 | M6: 2048.7063 | N6: 2074.1163 | O6: 2099.5264 | P6: 2124.9364 | Q6: 2150.3386 | R6: 2175.7487 | S6: 2201.1587 | T6: 2226.5688 | U6: 2251.9788 | V6: 2277.3889 | W6: 2302.7989 | X6: 2358.7557 | Y6: 2384.1658 | Z6: 2410.3733 | AA6: 2435.7833 | AB6: 2461.1934 | AC6: 2486.6034 | AD6: 2512.0135 | AE6: 2537.4235 | AF6: 2562.8257 | AG6: 2588.2358 | AH6: 2613.6458 | AI6: 2639.0559 | AJ6: 2664.4659 | AK6: 2689.876 | AL6: 2715.286 | AM6: 2741.4857 | AN6: 2766.8958 | AO6: 2792.3058 | AP6: 2817.7158 | AQ6: 2843.1259 | AR6: 2868.5359 | AS6: 2893.946 | AT6: 2919.3482 | AU6: 2944.7582 | AV6: 2970.1683 | AW6: 2995.5783 | AX6: 3020.9884 | AY6: 3046.3984 | AZ6: 3071.8085 | BA6: 3098.016 | BB6: 3123.4182 | BC6: 3136.1232
A7: ='(patio_costs)'!A19 -> 2400 | B7: 1808.4993 | C7: 1833.9093 | D7: 1859.3194 | E7: 1884.7294 | F7: 1910.1394 | G7: 1935.5495 | H7: 1960.9517 | I7: 1986.3618 | J7: 2011.7718 | K7: 2037.1818 | L7: 2063.3894 | M7: 2088.7994 | N7: 2114.2095 | O7: 2139.6117 | P7: 2165.0217 | Q7: 2190.4318 | R7: 2215.8418 | S7: 2241.2519 | T7: 2266.6619 | U7: 2292.0719 | V7: 2348.0366 | W7: 2373.4388 | X7: 2398.8489 | Y7: 2424.2589 | Z7: 2450.4664 | AA7: 2475.8765 | AB7: 2501.2865 | AC7: 2526.6887 | AD7: 2552.0988 | AE7: 2577.5088 | AF7: 2602.9189 | AG7: 2628.3289 | AH7: 2653.739 | AI7: 2679.149 | AJ7: 2704.5591 | AK7: 2729.9613 | AL7: 2755.3713 | AM7: 2781.5789 | AN7: 2806.9889 | AO7: 2832.3989 | AP7: 2857.809 | AQ7: 2883.219 | AR7: 2908.6213 | AS7: 2934.0313 | AT7: 2959.4413 | AU7: 2984.8514 | AV7: 3010.2614 | AW7: 3035.6715 | AX7: 3061.0815 | AY7: 3086.4916 | AZ7: 3111.8938 | BA7: 3138.1013 | BB7: 3163.5114 | BC7: 3176.2164
A8: ='(patio_costs)'!A20 -> 2500 | B8: 1848.5924 | C8: 1874.0025 | D8: 1899.4125 | E8: 1924.8147 | F8: 1950.2248 | G8: 1975.6348 | H8: 2001.0449 | I8: 2026.4549 | J8: 2051.8649 | K8: 2077.275 | L8: 2103.4825 | M8: 2128.8847 | N8: 2154.2948 | O8: 2179.7048 | P8: 2205.1149 | Q8: 2230.5249 | R8: 2255.935 | S8: 2281.345 | T8: 2322.0245 | U8: 2362.7119 | V8: 2388.1219 | W8: 2413.532 | X8: 2438.942 | Y8: 2464.352 | Z8: 2490.5596 | AA8: 2515.9618 | AB8: 2541.3718 | AC8: 2566.7819 | AD8: 2592.1919 | AE8: 2617.602 | AF8: 2643.012 | AG8: 2668.4221 | AH8: 2693.8321 | AI8: 2719.2343 | AJ8: 2744.6444 | AK8: 2770.0544 | AL8: 2795.4645 | AM8: 2821.672 | AN8: 2847.082 | AO8: 2872.4921 | AP8: 2897.8943 | AQ8: 2923.3043 | AR8: 2948.7144 | AS8: 2974.1244 | AT8: 2999.5345 | AU8: 3024.9445 | AV8: 3050.3546 | AW8: 3075.7568 | AX8: 3101.1668 | AY8: 3126.5769 | AZ8: 3151.9869 | BA8: 3178.1945 | BB8: 3203.6045 | BC8: 3216.3095
A9: ='(patio_costs)'!A21 -> 2600 | B9: 1888.6856 | C9: 1914.0878 | D9: 1939.4978 | E9: 1964.9079 | F9: 1990.3179 | G9: 2015.728 | H9: 2041.138 | I9: 2066.548 | J9: 2091.9503 | K9: 2117.3603 | L9: 2143.5678 | M9: 2168.9779 | N9: 2194.3879 | O9: 2219.798 | P9: 2245.208 | Q9: 2270.6102 | R9: 2311.2976 | S9: 2351.9849 | T9: 2377.395 | U9: 2402.805 | V9: 2428.2151 | W9: 2453.6251 | X9: 2479.0273 | Y9: 2504.4374 | Z9: 2530.6449 | AA9: 2556.0549 | AB9: 2581.465 | AC9: 2606.875 | AD9: 2632.2851 | AE9: 2657.6951 | AF9: 2683.0973 | AG9: 2708.5074 | AH9: 2733.9174 | AI9: 2759.3275 | AJ9: 2784.7375 | AK9: 2810.1476 | AL9: 2835.5576 | AM9: 2861.7573 | AN9: 2887.1674 | AO9: 2912.5774 | AP9: 2937.9874 | AQ9: 2963.3975 | AR9: 2988.8075 | AS9: 3014.2176 | AT9: 3039.6198 | AU9: 3065.0298 | AV9: 3090.4399 | AW9: 3115.8499 | AX9: 3141.26 | AY9: 3166.67 | AZ9: 3192.0801 | BA9: 3218.2798 | BB9: 3243.6898 | BC9: 3256.3948
A10: ='(patio_costs)'!A22 -> 2700 | B10: 1928.7709 | C10: 1954.1809 | D10: 1979.591 | E10: 2005.001 | F10: 2030.411 | G10: 2055.8211 | H10: 2081.2233 | I10: 2106.6334 | J10: 2132.0434 | K10: 2157.4534 | L10: 2183.661 | M10: 2209.071 | N10: 2234.4811 | O10: 2259.8833 | P10: 2285.2933 | Q10: 2341.258 | R10: 2366.668 | S10: 2392.0781 | T10: 2417.4881 | U10: 2442.8982 | V10: 2468.3004 | W10: 2493.7104 | X10: 2519.1205 | Y10: 2544.5305 | Z10: 2570.738 | AA10: 2596.1481 | AB10: 2621.5581 | AC10: 2646.9603 | AD10: 2672.3704 | AE10: 2697.7804 | AF10: 2723.1905 | AG10: 2748.6005 | AH10: 2774.0106 | AI10: 2799.4206 | AJ10: 2824.8307 | AK10: 2850.2329 | AL10: 2875.6429 | AM10: 2901.8505 | AN10: 2927.2605 | AO10: 2952.6705 | AP10: 2978.0806 | AQ10: 3003.4906 | AR10: 3028.8929 | AS10: 3054.3029 | AT10: 3079.7129 | AU10: 3105.123 | AV10: 3130.533 | AW10: 3155.9431 | AX10: 3181.3531 | AY10: 3206.7632 | AZ10: 3232.1654 | BA10: 3258.3729 | BB10: 3283.783 | BC10: 3267.7785

Sheet Ultra_patio_4
A1: type | B1: matrix | C1: cortizo_patio_4_
A2: ='(patio_costs)'!A25 | B2: ='(patio_costs)'!B25 -> 2800 | C2: ='(patio_costs)'!C25 -> 2900 | D2: ='(patio_costs)'!D25 -> 3000 | E2: ='(patio_costs)'!E25 -> 3100 | F2: ='(patio_costs)'!F25 -> 3200 | G2: ='(patio_costs)'!G25 -> 3300 | H2: ='(patio_costs)'!H25 -> 3400 | ... BV2: ='(patio_costs)'!BV25 -> 10000
A3: ='(patio_costs)'!A26 -> 2000 | B3: {='(patio_costs)'!B26:BV33*(1+MARKUP!$Z$6)} -> 1936.362611 | C3: 1957.3239 | D3: 1978.2853 | E3: 1999.2466 | F3: 2020.2079 | G3: 2041.1693 | H3: 2062.1228 | I3: 2083.0841 | J3: 2104.0454 | K3: 2125.0068 | L3: 2145.9681 | M3: 2166.9294 | N3: 2187.8908 | O3: 2208.8521 | P3: 2229.8134 | Q3: 2250.7748 | R3: 2272.7994 | S3: 2293.7607 | T3: 2314.7221 | U3: 2335.6834 | V3: 2356.6447 | W3: 2377.5982 | X3: 2398.5596 | Y3: 2419.5209 | Z3: 2440.4822 | AA3: 2461.4436 | AB3: 2482.4049 | AC3: 2503.3662 | AD3: 2524.3276 | AE3: 2545.2889 | AF3: 2566.2502 | AG3: 2587.2116 | AH3: 2608.1729 | AI3: 2629.1342 | AJ3: 2651.1589 | AK3: 2672.1202 | AL3: 2693.0737 | AM3: 2714.035 | AN3: 2734.9964 | AO3: 2771.235 | AP3: 2792.1963 | AQ3: 2828.435 | AR3: 2849.3963 | AS3: 2870.3576 | AT3: 2891.319 | AU3: 2912.2803 | AV3: 2933.2416 | AW3: 2954.203 | AX3: 2975.1643 | AY3: 2996.1256 | AZ3: 3017.0791 | BA3: 3038.0405 | BB3: 3060.0651 | BC3: 3081.0264 | BD3: 3101.9878 | BE3: 3122.9491 | BF3: 3143.9104 | BG3: 3164.8718 | BH3: 3185.8331 | BI3: 3206.7944 | BJ3: 3227.7558 | BK3: 3248.7171 | BL3: 3269.6784 | BM3: 3290.6398 | BN3: 3311.5933 | BO3: 3332.5624 | BP3: 3353.5159 | BQ3: 3374.4773 | BR3: 3395.4386 | BS3: 3416.3999 | BT3: 3438.4246 | BU3: 3459.3859 | BV3: 3480.3472
A4: ='(patio_costs)'!A27 -> 2100 | B4: 1984.196 | C4: 2005.1574 | D4: 2026.1187 | E4: 2047.08 | F4: 2068.0414 | G4: 2089.0027 | H4: 2109.964 | I4: 2130.9254 | J4: 2151.8867 | K4: 2172.848 | L4: 2193.8015 | M4: 2214.7629 | N4: 2235.7242 | O4: 2256.6855 | P4: 2277.6469 | Q4: 2298.6082 | R4: 2320.6328 | S4: 2341.5942 | T4: 2362.5555 | U4: 2383.5168 | V4: 2404.4782 | W4: 2425.4395 | X4: 2446.4008 | Y4: 2467.3622 | Z4: 2488.3157 | AA4: 2509.277 | AB4: 2530.2383 | AC4: 2551.1997 | AD4: 2572.161 | AE4: 2593.1223 | AF4: 2614.0837 | AG4: 2635.045 | AH4: 2656.0063 | AI4: 2676.9677 | AJ4: 2698.9923 | AK4: 2735.2309 | AL4: 2756.1923 | AM4: 2792.4309 | AN4: 2813.3844 | AO4: 2834.3536 | AP4: 2855.3071 | AQ4: 2876.2684 | AR4: 2897.2297 | AS4: 2918.1911 | AT4: 2939.1524 | AU4: 2960.1137 | AV4: 2981.0751 | AW4: 3002.0364 | AX4: 3022.9977 | AY4: 3043.9591 | AZ4: 3064.9204 | BA4: 3085.8817 | BB4: 3107.9064 | BC4: 3128.8677 | BD4: 3149.8212 | BE4: 3170.7825 | BF4: 3191.7439 | BG4: 3212.7052 | BH4: 3233.6665 | BI4: 3254.6279 | BJ4: 3275.5892 | BK4: 3296.5505 | BL4: 3317.5119 | BM4: 3338.4732 | BN4: 3359.4345 | BO4: 3380.3959 | BP4: 3401.3572 | BQ4: 3422.3185 | BR4: 3443.2798 | BS4: 3464.2334 | BT4: 3486.2658 | BU4: 3507.2193 | BV4: 3528.1807
A5: ='(patio_costs)'!A28 -> 2200 | B5: 2032.0295 | C5: 2052.9908 | D5: 2073.9521 | E5: 2094.9135 | F5: 2115.8748 | G5: 2136.8361 | H5: 2157.7975 | I5: 2178.7588 | J5: 2199.7201 | K5: 2220.6815 | L5: 2241.6428 | M5: 2262.6041 | N5: 2283.5654 | O5: 2304.5268 | P5: 2325.4803 | Q5: 2346.4494 | R5: 2368.4663 | S5: 2389.4276 | T5: 2410.3889 | U5: 2431.3503 | V5: 2452.3116 | W5: 2473.2729 | X5: 2494.2343 | Y5: 2515.1956 | Z5: 2536.1569 | AA5: 2557.1183 | AB5: 2578.0796 | AC5: 2599.0409 | AD5: 2619.9944 | AE5: 2640.9558 | AF5: 2661.9171 | AG5: 2682.8784 | AH5: 2719.1171 | AI5: 2740.0784 | AJ5: 2777.3803 | AK5: 2798.3417 | AL5: 2819.303 | AM5: 2840.2643 | AN5: 2861.2257 | AO5: 2882.187 | AP5: 2903.1483 | AQ5: 2924.1096 | AR5: 2945.071 | AS5: 2966.0323 | AT5: 2986.9936 | AU5: 3007.9472 | AV5: 3028.9085 | AW5: 3049.8698 | AX5: 3070.8312 | AY5: 3091.7925 | AZ5: 3112.7538 | BA5: 3133.7151 | BB5: 3155.7398 | BC5: 3176.7011 | BD5: 3197.6625 | BE5: 3218.6238 | BF5: 3239.5851 | BG5: 3260.5464 | BH5: 3281.5078 | BI5: 3302.4613 | BJ5: 3323.4226 | BK5: 3344.384 | BL5: 3365.3453 | BM5: 3386.3066 | BN5: 3407.2679 | BO5: 3428.2293 | BP5: 3449.1906 | BQ5: 3470.1519 | BR5: 3491.1133 | BS5: 3512.0746 | BT5: 3534.0993 | BU5: 3555.0606 | BV5: 3576.0219
A6: ='(patio_costs)'!A29 -> 2300 | B6: 2079.8707 | C6: 2100.8321 | D6: 2121.7934 | E6: 2142.7469 | F6: 2163.7082 | G6: 2184.6696 | H6: 2205.6309 | I6: 2226.5922 | J6: 2247.5536 | K6: 2268.5149 | L6: 2289.4762 | M6: 2310.4375 | N6: 2331.3989 | O6: 2352.3602 | P6: 2373.3215 | Q6: 2394.2829 | R6: 2416.3075 | S6: 2437.261 | T6: 2458.2302 | U6: 2479.1837 | V6: 2500.145 | W6: 2521.1064 | X6: 2542.0677 | Y6: 2563.029 | Z6: 2583.9904 | AA6: 2604.9517 | AB6: 2625.913 | AC6: 2646.8743 | AD6: 2667.8357 | AE6: 2704.0743 | AF6: 2725.0356 | AG6: 2761.2743 | AH6: 2782.2356 | AI6: 2803.1891 | AJ6: 2825.2216 | AK6: 2846.1751 | AL6: 2867.1364 | AM6: 2888.0978 | AN6: 2909.0591 | AO6: 2930.0204 | AP6: 2950.9817 | AQ6: 2971.9431 | AR6: 2992.9044 | AS6: 3013.8657 | AT6: 3034.8271 | AU6: 3055.7884 | AV6: 3076.7497 | AW6: 3097.7033 | AX6: 3118.6724 | AY6: 3139.6259 | AZ6: 3160.5872 | BA6: 3181.5486 | BB6: 3203.5732 | BC6: 3224.5346 | BD6: 3245.4959 | BE6: 3266.4572 | BF6: 3287.4185 | BG6: 3308.3799 | BH6: 3329.3412 | BI6: 3350.3025 | BJ6: 3371.2639 | BK6: 3392.2252 | BL6: 3413.1787 | BM6: 3434.14 | BN6: 3455.1014 | BO6: 3476.0627 | BP6: 3497.024 | BQ6: 3517.9854 | BR6: 3538.9467 | BS6: 3559.908 | BT6: 3581.9327 | BU6: 3602.894 | BV6: 3623.8553
A7: ='(patio_costs)'!A30 -> 2400 | B7: 2127.7041 | C7: 2148.6655 | D7: 2169.6268 | E7: 2190.5881 | F7: 2211.5495 | G7: 2232.5108 | H7: 2253.4721 | I7: 2274.4257 | J7: 2295.387 | K7: 2316.3483 | L7: 2337.3096 | M7: 2358.271 | N7: 2379.2323 | O7: 2400.1936 | P7: 2421.155 | Q7: 2442.1163 | R7: 2464.1409 | S7: 2485.1023 | T7: 2506.0636 | U7: 2527.0249 | V7: 2547.9863 | W7: 2568.9476 | X7: 2589.9011 | Y7: 2610.8624 | Z7: 2631.8238 | AA7: 2652.7851 | AB7: 2673.7464 | AC7: 2709.9851 | AD7: 2730.9464 | AE7: 2767.185 | AF7: 2788.1464 | AG7: 2809.1077 | AH7: 2830.069 | AI7: 2851.0304 | AJ7: 2873.055 | AK7: 2894.0163 | AL7: 2914.9777 | AM7: 2935.9312 | AN7: 2956.8925 | AO7: 2977.8538 | AP7: 2998.8152 | AQ7: 3019.7765 | AR7: 3040.7378 | AS7: 3061.6992 | AT7: 3082.6605 | AU7: 3103.6218 | AV7: 3124.5832 | AW7: 3145.5445 | AX7: 3166.5058 | AY7: 3187.4672 | AZ7: 3208.4285 | BA7: 3229.3898 | BB7: 3251.4067 | BC7: 3272.3758 | BD7: 3293.3293 | BE7: 3314.2906 | BF7: 3335.252 | BG7: 3356.2133 | BH7: 3377.1746 | BI7: 3398.136 | BJ7: 3419.0973 | BK7: 3440.0586 | BL7: 3461.02 | BM7: 3481.9813 | BN7: 3502.9426 | BO7: 3523.904 | BP7: 3544.8653 | BQ7: 3565.8266 | BR7: 3586.7801 | BS7: 3607.7415 | BT7: 3629.7661 | BU7: 3650.7274 | BV7: 3671.6888
A8: ='(patio_costs)'!A31 -> 2500 | B8: 2175.5376 | C8: 2196.4989 | D8: 2217.4602 | E8: 2238.4216 | F8: 2259.3829 | G8: 2280.3442 | H8: 2301.3056 | I8: 2322.2669 | J8: 2343.2282 | K8: 2364.1896 | L8: 2385.1509 | M8: 2406.1122 | N8: 2427.0657 | O8: 2448.0271 | P8: 2468.9884 | Q8: 2489.9497 | R8: 2511.9744 | S8: 2532.9357 | T8: 2553.897 | U8: 2574.8584 | V8: 2595.8197 | W8: 2616.781 | X8: 2637.7424 | Y8: 2658.7037 | Z8: 2694.9423 | AA8: 2715.9037 | AB8: 2752.1423 | AC8: 2773.1036 | AD8: 2794.0571 | AE8: 2815.0185 | AF8: 2835.9798 | AG8: 2856.9411 | AH8: 2877.9025 | AI8: 2898.8638 | AJ8: 2920.8884 | AK8: 2941.8498 | AL8: 2962.8111 | AM8: 2983.7724 | AN8: 3004.7338 | AO8: 3025.6951 | AP8: 3046.6564 | AQ8: 3067.6178 | AR8: 3088.5713 | AS8: 3109.5326 | AT8: 3130.4939 | AU8: 3151.4553 | AV8: 3172.4166 | AW8: 3193.3779 | AX8: 3214.3393 | AY8: 3235.3006 | AZ8: 3256.2619 | BA8: 3277.2233 | BB8: 3299.2479 | BC8: 3320.2092 | BD8: 3341.1706 | BE8: 3362.1241 | BF8: 3383.0854 | BG8: 3404.0467 | BH8: 3425.0081 | BI8: 3445.9694 | BJ8: 3466.9307 | BK8: 3487.8921 | BL8: 3508.8534 | BM8: 3529.8147 | BN8: 3550.7761 | BO8: 3571.7374 | BP8: 3592.6987 | BQ8: 3613.6601 | BR8: 3634.6214 | BS8: 3655.5827 | BT8: 3677.6074 | BU8: 3698.5609 | BV8: 3719.5222
A9: ='(patio_costs)'!A32 -> 2600 | B9: 2223.3788 | C9: 2244.3323 | D9: 2265.2937 | E9: 2286.255 | F9: 2307.2163 | G9: 2328.1777 | H9: 2349.139 | I9: 2370.1003 | J9: 2391.0617 | K9: 2412.023 | L9: 2432.9843 | M9: 2453.9457 | N9: 2474.907 | O9: 2495.8683 | P9: 2516.8218 | Q9: 2537.791 | R9: 2559.8078 | S9: 2580.7691 | T9: 2601.7305 | U9: 2622.6918 | V9: 2643.6531 | W9: 2664.6145 | X9: 2700.8531 | Y9: 2721.8144 | Z9: 2758.0531 | AA9: 2779.0144 | AB9: 2799.9757 | AC9: 2820.9371 | AD9: 2841.8984 | AE9: 2862.8519 | AF9: 2883.821 | AG9: 2904.7746 | AH9: 2925.7359 | AI9: 2946.6972 | AJ9: 2968.7219 | AK9: 2989.6832 | AL9: 3010.6445 | AM9: 3031.6059 | AN9: 3052.5672 | AO9: 3073.5285 | AP9: 3094.4899 | AQ9: 3115.4512 | AR9: 3136.4125 | AS9: 3157.3739 | AT9: 3178.3352 | AU9: 3199.2887 | AV9: 3220.25 | AW9: 3241.2114 | AX9: 3262.1727 | AY9: 3283.134 | AZ9: 3304.0954 | BA9: 3325.0567 | BB9: 3347.0813 | BC9: 3368.0427 | BD9: 3389.004 | BE9: 3409.9653 | BF9: 3430.9267 | BG9: 3451.888 | BH9: 3472.8493 | BI9: 3493.8106 | BJ9: 3514.772 | BK9: 3535.7255 | BL9: 3556.6868 | BM9: 3577.6482 | BN9: 3598.6095 | BO9: 3619.5708 | BP9: 3640.5322 | BQ9: 3661.4935 | BR9: 3682.4548 | BS9: 3703.4161 | BT9: 3725.4408 | BU9: 3746.4021 | BV9: 3767.3635
A10: ='(patio_costs)'!A33 -> 2700 | B10: 2271.2123 | C10: 2292.1736 | D10: 2313.1349 | E10: 2334.0963 | F10: 2355.0576 | G10: 2376.0111 | H10: 2396.9724 | I10: 2417.9338 | J10: 2438.8951 | K10: 2459.8564 | L10: 2480.8178 | M10: 2501.7791 | N10: 2522.7404 | O10: 2543.7017 | P10: 2564.6631 | Q10: 2585.6244 | R10: 2607.6491 | S10: 2628.6104 | T10: 2649.5717 | U10: 2670.5252 | V10: 2706.7717 | W10: 2727.7252 | X10: 2763.9638 | Y10: 2784.9252 | Z10: 2805.8865 | AA10: 2826.8478 | AB10: 2847.8092 | AC10: 2868.7705 | AD10: 2889.7318 | AE10: 2910.6931 | AF10: 2931.6545 | AG10: 2952.6158 | AH10: 2973.5771 | AI10: 2994.5385 | AJ10: 3016.5631 | AK10: 3037.5244 | AL10: 3058.478 | AM10: 3079.4393 | AN10: 3100.4006 | AO10: 3121.362 | AP10: 3142.3233 | AQ10: 3163.2846 | AR10: 3184.246 | AS10: 3205.2073 | AT10: 3226.1686 | AU10: 3247.1299 | AV10: 3268.0913 | AW10: 3289.0526 | AX10: 3310.0139 | AY10: 3330.9753 | AZ10: 3351.9288 | BA10: 3372.8901 | BB10: 3394.9148 | BC10: 3415.8761 | BD10: 3436.8374 | BE10: 3457.7988 | BF10: 3478.7601 | BG10: 3499.7214 | BH10: 3520.6827 | BI10: 3541.6441 | BJ10: 3562.6054 | BK10: 3583.5667 | BL10: 3604.5281 | BM10: 3625.4894 | BN10: 3646.4429 | BO10: 3667.4042 | BP10: 3688.3656 | BQ10: 3709.3269 | BR10: 3730.2882 | BS10: 3751.2496 | BT10: 3773.2742 | BU10: 3765.5261 | BV10: 3786.4874

Sheet five
A1: type | B1: matrix | C1: shaped_s5_
B2: 400 | C2: 500 | D2: 600 | E2: 700 | F2: 800 | G2: 900 | H2: 1000 | I2: 1100 | J2: 1200 | K2: 1300 | L2: 1400 | M2: 1500 | N2: 1600 | O2: 1700 | P2: 1800 | Q2: 1900 | R2: 2000 | S2: 2100 | T2: 2200 | U2: 2300 | V2: 2400 | W2: 2500 | X2: 2600 | Y2: 2700 | Z2: 2800 | AA2: 2900 | AB2: 3000 | AC2: 3100 | AD2: 3200 | AE2: 3300 | AF2: 3400 | AG2: 3500 | AH2: 3600 | AI2: 3700 | AJ2: 3800 | AK2: 3900 | AL2: 4000 | AM2: 4100 | AN2: 4200 | AO2: 4300 | AP2: 4400 | AQ2: 4500 | AR2: 4600 | AS2: 4700 | AT2: 4800 | AU2: 4900 | AV2: 5000
A3: 400 | B3: 320 | C3: 330 | D3: 338 | E3: 346 | F3: 355 | G3: 364 | H3: 373 | I3: 381 | J3: 389 | K3: 399 | L3: 407 | M3: 416 | N3: 424 | O3: 432 | P3: 442 | Q3: 450 | R3: 459 | S3: 467 | T3: 476 | U3: 485 | V3: 493 | W3: 502 | X3: 511 | Y3: 519 | Z3: 528 | AA3: 536 | AB3: 546 | AC3: 554 | AD3: 562 | AE3: 571 | AF3: 580 | AG3: 589 | AH3: 597 | AI3: 605 | AJ3: 615 | AK3: 623 | AL3: 632 | AM3: 640 | AN3: 649 | AO3: 658 | AP3: 666 | AQ3: 675 | AR3: 684 | AS3: 692 | AT3: 701 | AU3: 709 | AV3: 719
A4: 500 | B4: 328 | C4: 338 | D4: 346 | E4: 354 | F4: 364 | G4: 372 | H4: 381 | I4: 389 | J4: 397 | K4: 407 | L4: 415 | M4: 424 | N4: 432 | O4: 441 | P4: 450 | Q4: 458 | R4: 467 | S4: 476 | T4: 484 | U4: 493 | V4: 501 | W4: 511 | X4: 519 | Y4: 527 | Z4: 536 | AA4: 545 | AB4: 554 | AC4: 562 | AD4: 570 | AE4: 580 | AF4: 588 | AG4: 597 | AH4: 605 | AI4: 614 | AJ4: 623 | AK4: 631 | AL4: 640 | AM4: 649 | AN4: 657 | AO4: 666 | AP4: 674 | AQ4: 684 | AR4: 692 | AS4: 700 | AT4: 709 | AU4: 717 | AV4: 727
A5: 600 | B5: 337 | C5: 346 | D5: 354 | E5: 363 | F5: 372 | G5: 380 | H5: 389 | I5: 398 | J5: 406 | K5: 415 | L5: 423 | M5: 432 | N5: 441 | O5: 449 | P5: 458 | Q5: 466 | R5: 476 | S5: 484 | T5: 492 | U5: 501 | V5: 510 | W5: 519 | X5: 527 | Y5: 535 | Z5: 545 | AA5: 553 | AB5: 562 | AC5: 570 | AD5: 579 | AE5: 588 | AF5: 596 | AG5: 605 | AH5: 614 | AI5: 622 | AJ5: 631 | AK5: 639 | AL5: 649 | AM5: 657 | AN5: 665 | AO5: 674 | AP5: 682 | AQ5: 692 | AR5: 700 | AS5: 708 | AT5: 717 | AU5: 726 | AV5: 735
A6: 700 | B6: 345 | C6: 354 | D6: 363 | E6: 371 | F6: 380 | G6: 388 | H6: 397 | I6: 406 | J6: 414 | K6: 423 | L6: 431 | M6: 441 | N6: 449 | O6: 457 | P6: 466 | Q6: 475 | R6: 484 | S6: 492 | T6: 500 | U6: 510 | V6: 518 | W6: 527 | X6: 535 | Y6: 544 | Z6: 553 | AA6: 561 | AB6: 570 | AC6: 579 | AD6: 587 | AE6: 596 | AF6: 604 | AG6: 614 | AH6: 622 | AI6: 630 | AJ6: 639 | AK6: 647 | AL6: 657 | AM6: 665 | AN6: 673 | AO6: 683 | AP6: 691 | AQ6: 700 | AR6: 708 | AS6: 716 | AT6: 726 | AU6: 734 | AV6: 743
A7: 800 | B7: 353 | C7: 363 | D7: 371 | E7: 379 | F7: 388 | G7: 396 | H7: 406 | I7: 414 | J7: 422 | K7: 431 | L7: 440 | M7: 449 | N7: 457 | O7: 465 | P7: 475 | Q7: 483 | R7: 492 | S7: 500 | T7: 509 | U7: 518 | V7: 526 | W7: 535 | X7: 544 | Y7: 552 | Z7: 561 | AA7: 569 | AB7: 579 | AC7: 587 | AD7: 595 | AE7: 604 | AF7: 613 | AG7: 622 | AH7: 630 | AI7: 638 | AJ7: 648 | AK7: 656 | AL7: 665 | AM7: 673 | AN7: 681 | AO7: 691 | AP7: 699 | AQ7: 708 | AR7: 716 | AS7: 725 | AT7: 734 | AU7: 742 | AV7: 751
A8: 900 | B8: 361 | C8: 371 | D8: 379 | E8: 387 | F8: 396 | G8: 405 | H8: 414 | I8: 422 | J8: 430 | K8: 440 | L8: 448 | M8: 457 | N8: 465 | O8: 474 | P8: 483 | Q8: 491 | R8: 500 | S8: 509 | T8: 517 | U8: 526 | V8: 534 | W8: 544 | X8: 552 | Y8: 560 | Z8: 569 | AA8: 577 | AB8: 587 | AC8: 595 | AD8: 603 | AE8: 612 | AF8: 621 | AG8: 630 | AH8: 638 | AI8: 646 | AJ8: 656 | AK8: 664 | AL8: 673 | AM8: 681 | AN8: 690 | AO8: 699 | AP8: 707 | AQ8: 716 | AR8: 725 | AS8: 733 | AT8: 742 | AU8: 750 | AV8: 760
A9: 1000 | B9: 369 | C9: 379 | D9: 387 | E9: 395 | F9: 405 | G9: 413 | H9: 422 | I9: 430 | J9: 439 | K9: 448 | L9: 456 | M9: 465 | N9: 474 | O9: 482 | P9: 491 | Q9: 499 | R9: 509 | S9: 517 | T9: 525 | U9: 534 | V9: 543 | W9: 552 | X9: 560 | Y9: 568 | Z9: 577 | AA9: 586 | AB9: 595 | AC9: 603 | AD9: 611 | AE9: 621 | AF9: 629 | AG9: 638 | AH9: 646 | AI9: 655 | AJ9: 664 | AK9: 672 | AL9: 681 | AM9: 690 | AN9: 698 | AO9: 707 | AP9: 715 | AQ9: 725 | AR9: 733 | AS9: 741 | AT9: 750 | AU9: 759 | AV9: 768
A10: 1100 | B10: 378 | C10: 387 | D10: 395 | E10: 404 | F10: 413 | G10: 421 | H10: 430 | I10: 439 | J10: 447 | K10: 456 | L10: 464 | M10: 474 | N10: 482 | O10: 490 | P10: 499 | Q10: 508 | R10: 517 | S10: 525 | T10: 533 | U10: 543 | V10: 551 | W10: 560 | X10: 568 | Y10: 576 | Z10: 586 | AA10: 594 | AB10: 603 | AC10: 611 | AD10: 620 | AE10: 629 | AF10: 637 | AG10: 646 | AH10: 655 | AI10: 663 | AJ10: 672 | AK10: 680 | AL10: 690 | AM10: 698 | AN10: 707 | AO10: 716 | AP10: 724 | AQ10: 733 | AR10: 741 | AS10: 749 | AT10: 759 | AU10: 767 | AV10: 776
A11: 1200 | B11: 386 | C11: 395 | D11: 404 | E11: 412 | F11: 421 | G11: 429 | H11: 439 | I11: 447 | J11: 455 | K11: 464 | L11: 473 | M11: 482 | N11: 490 | O11: 498 | P11: 508 | Q11: 516 | R11: 525 | S11: 533 | T11: 541 | U11: 551 | V11: 559 | W11: 568 | X11: 576 | Y11: 585 | Z11: 594 | AA11: 602 | AB11: 611 | AC11: 620 | AD11: 628 | AE11: 637 | AF11: 645 | AG11: 655 | AH11: 663 | AI11: 671 | AJ11: 680 | AK11: 689 | AL11: 698 | AM11: 706 | AN11: 714 | AO11: 724 | AP11: 732 | AQ11: 741 | AR11: 749 | AS11: 758 | AT11: 767 | AU11: 775 | AV11: 784
A12: 1300 | B12: 394 | C12: 404 | D12: 412 | E12: 420 | F12: 429 | G12: 438 | H12: 447 | I12: 455 | J12: 463 | K12: 473 | L12: 481 | M12: 490 | N12: 498 | O12: 507 | P12: 516 | Q12: 524 | R12: 533 | S12: 542 | T12: 550 | U12: 559 | V12: 567 | W12: 577 | X12: 585 | Y12: 593 | Z12: 602 | AA12: 610 | AB12: 620 | AC12: 628 | AD12: 636 | AE12: 645 | AF12: 654 | AG12: 663 | AH12: 671 | AI12: 679 | AJ12: 689 | AK12: 697 | AL12: 706 | AM12: 714 | AN12: 723 | AO12: 732 | AP12: 740 | AQ12: 749 | AR12: 758 | AS12: 766 | AT12: 775 | AU12: 783 | AV12: 793
A13: 1400 | B13: 402 | C13: 412 | D13: 420 | E13: 428 | F13: 438 | G13: 446 | H13: 455 | I13: 463 | J13: 471 | K13: 481 | L13: 489 | M13: 498 | N13: 506 | O13: 515 | P13: 524 | Q13: 532 | R13: 541 | S13: 550 | T13: 558 | U13: 567 | V13: 575 | W13: 585 | X13: 593 | Y13: 601 | Z13: 610 | AA13: 619 | AB13: 628 | AC13: 636 | AD13: 644 | AE13: 654 | AF13: 662 | AG13: 671 | AH13: 679 | AI13: 688 | AJ13: 697 | AK13: 705 | AL13: 714 | AM13: 723 | AN13: 731 | AO13: 740 | AP13: 748 | AQ13: 758 | AR13: 766 | AS13: 774 | AT13: 783 | AU13: 791 | AV13: 801
A14: 1500 | B14: 411 | C14: 420 | D14: 428 | E14: 436 | F14: 446 | G14: 454 | H14: 463 | I14: 471 | J14: 480 | K14: 489 | L14: 497 | M14: 506 | N14: 515 | O14: 523 | P14: 532 | Q14: 540 | R14: 550 | S14: 558 | T14: 566 | U14: 575 | V14: 584 | W14: 593 | X14: 601 | Y14: 609 | Z14: 619 | AA14: 627 | AB14: 636 | AC14: 644 | AD14: 653 | AE14: 662 | AF14: 670 | AG14: 679 | AH14: 688 | AI14: 696 | AJ14: 705 | AK14: 713 | AL14: 723 | AM14: 731 | AN14: 739 | AO14: 748 | AP14: 756 | AQ14: 766 | AR14: 774 | AS14: 782 | AT14: 791 | AU14: 800 | AV14: 809
... A22: 2300 | B22: 476 | C22: 486 | D22: 494 | E22: 502 | F22: 512 | G22: 520 | H22: 529 | I22: 537 | J22: 546 | K22: 555 | L22: 563 | M22: 572 | N22: 581 | O22: 589 | P22: 598 | Q22: 606 | R22: 616 | S22: 624 | T22: 632 | U22: 641 | V22: 649 | W22: 659 | X22: 667 | Y22: 675 | Z22: 684 | AA22: 693 | AB22: 702 | AC22: 710 | AD22: 718 | AE22: 728 | AF22: 736 | AG22: 745 | AH22: 753 | AI22: 762 | AJ22: 771 | AK22: 779 | AL22: 788 | AM22: 797 | AN22: 805 | AO22: 814 | AP22: 822 | AQ22: 832 | AR22: 840 | AS22: 848 | AT22: 857 | AU22: 866 | AV22: 875

Sheet four
A1: type | B1: matrix | C1: shaped_s4_
B2: 400 | C2: 500 | D2: 600 | E2: 700 | F2: 800 | G2: 900 | H2: 1000 | I2: 1100 | J2: 1200 | K2: 1300 | L2: 1400 | M2: 1500 | N2: 1600 | O2: 1700 | P2: 1800 | Q2: 1900 | R2: 2000 | S2: 2100 | T2: 2200 | U2: 2300 | V2: 2400 | W2: 2500
A3: 400 | B3: 245 | C3: 254 | D3: 263 | E3: 271 | F3: 280 | G3: 288 | H3: 298 | I3: 306 | J3: 314 | K3: 323 | L3: 331 | M3: 341 | N3: 349 | O3: 357 | P3: 366 | Q3: 375 | R3: 384 | S3: 392 | T3: 400 | U3: 410 | V3: 418 | W3: 427
A4: 500 | B4: 253 | C4: 263 | D4: 271 | E4: 279 | F4: 288 | G4: 296 | H4: 306 | I4: 314 | J4: 322 | K4: 331 | L4: 340 | M4: 349 | N4: 357 | O4: 365 | P4: 375 | Q4: 383 | R4: 392 | S4: 400 | T4: 409 | U4: 418 | V4: 426 | W4: 435
A5: 600 | B5: 261 | C5: 271 | D5: 279 | E5: 287 | F5: 296 | G5: 305 | H5: 314 | I5: 322 | J5: 330 | K5: 340 | L5: 348 | M5: 357 | N5: 365 | O5: 374 | P5: 383 | Q5: 391 | R5: 400 | S5: 409 | T5: 417 | U5: 426 | V5: 434 | W5: 444
A6: 700 | B6: 269 | C6: 279 | D6: 287 | E6: 295 | F6: 305 | G6: 313 | H6: 322 | I6: 330 | J6: 339 | K6: 348 | L6: 356 | M6: 365 | N6: 374 | O6: 382 | P6: 391 | Q6: 399 | R6: 409 | S6: 417 | T6: 425 | U6: 434 | V6: 443 | W6: 452
A7: 800 | B7: 278 | C7: 287 | D7: 295 | E7: 304 | F7: 313 | G7: 321 | H7: 330 | I7: 339 | J7: 347 | K7: 356 | L7: 364 | M7: 374 | N7: 382 | O7: 390 | P7: 399 | Q7: 408 | R7: 417 | S7: 425 | T7: 433 | U7: 443 | V7: 451 | W7: 460
A8: 900 | B8: 286 | C8: 295 | D8: 304 | E8: 312 | F8: 321 | G8: 329 | H8: 339 | I8: 347 | J8: 355 | K8: 364 | L8: 373 | M8: 382 | N8: 390 | O8: 398 | P8: 408 | Q8: 416 | R8: 425 | S8: 433 | T8: 442 | U8: 451 | V8: 459 | W8: 468
A9: 1000 | B9: 294 | C9: 304 | D9: 312 | E9: 320 | F9: 329 | G9: 338 | H9: 347 | I9: 355 | J9: 363 | K9: 373 | L9: 381 | M9: 390 | N9: 398 | O9: 407 | P9: 416 | Q9: 424 | R9: 433 | S9: 442 | T9: 450 | U9: 459 | V9: 467 | W9: 477
A10: 1100 | B10: 302 | C10: 312 | D10: 320 | E10: 328 | F10: 338 | G10: 346 | H10: 355 | I10: 363 | J10: 372 | K10: 381 | L10: 389 | M10: 398 | N10: 407 | O10: 415 | P10: 424 | Q10: 432 | R10: 442 | S10: 450 | T10: 458 | U10: 467 | V10: 475 | W10: 485
A11: 1200 | B11: 311 | C11: 320 | D11: 328 | E11: 337 | F11: 346 | G11: 354 | H11: 363 | I11: 372 | J11: 380 | K11: 389 | L11: 397 | M11: 407 | N11: 415 | O11: 423 | P11: 432 | Q11: 440 | R11: 450 | S11: 458 | T11: 466 | U11: 475 | V11: 484 | W11: 493
A12: 1300 | B12: 319 | C12: 328 | D12: 337 | E12: 345 | F12: 354 | G12: 362 | H12: 372 | I12: 380 | J12: 388 | K12: 397 | L12: 405 | M12: 415 | N12: 423 | O12: 431 | P12: 440 | Q12: 449 | R12: 458 | S12: 466 | T12: 474 | U12: 484 | V12: 492 | W12: 501
A13: 1400 | B13: 327 | C13: 337 | D13: 345 | E13: 353 | F13: 362 | G13: 370 | H13: 380 | I13: 388 | J13: 396 | K13: 405 | L13: 414 | M13: 423 | N13: 431 | O13: 439 | P13: 449 | Q13: 457 | R13: 466 | S13: 474 | T13: 483 | U13: 492 | V13: 500 | W13: 509
A14: 1500 | B14: 335 | C14: 345 | D14: 353 | E14: 361 | F14: 370 | G14: 379 | H14: 388 | I14: 396 | J14: 404 | K14: 414 | L14: 422 | M14: 431 | N14: 439 | O14: 448 | P14: 457 | Q14: 465 | R14: 474 | S14: 483 | T14: 491 | U14: 500 | V14: 508 | W14: 518
... A22: 2300 | B22: 401 | C22: 411 | D22: 419 | E22: 427 | F22: 436 | G22: 445 | H22: 454 | I22: 462 | J22: 470 | K22: 479 | L22: 488 | M22: 497 | N22: 505 | O22: 513 | P22: 523 | Q22: 531 | R22: 540 | S22: 548 | T22: 557 | U22: 566 | V22: 574 | W22: 583

Sheet three
A1: type | B1: matrix | C1: shaped_s3_
B2: 400 | C2: 500 | D2: 600 | E2: 700 | F2: 800 | G2: 900 | H2: 1000 | I2: 1100 | J2: 1200 | K2: 1300 | L2: 1400 | M2: 1500 | N2: 1600 | O2: 1700 | P2: 1800 | Q2: 1900 | R2: 2000 | S2: 2100 | T2: 2200 | U2: 2300 | V2: 2400 | W2: 2500 | X2: 2600 | Y2: 2700 | Z2: 2800 | AA2: 2900 | AB2: 3000 | AC2: 3100 | AD2: 3200 | AE2: 3300 | AF2: 3400 | AG2: 3500 | AH2: 3600 | AI2: 3700 | AJ2: 3800 | AK2: 3900 | AL2: 4000 | AM2: 4100 | AN2: 4200 | AO2: 4300 | AP2: 4400 | AQ2: 4500 | AR2: 4600 | AS2: 4700 | AT2: 4800 | AU2: 4900 | AV2: 5000
A3: 400 | B3: 317 | C3: 326 | D3: 335 | E3: 343 | F3: 352 | G3: 360 | H3: 370 | I3: 378 | J3: 386 | K3: 395 | L3: 404 | M3: 413 | N3: 421 | O3: 429 | P3: 439 | Q3: 447 | R3: 456 | S3: 464 | T3: 473 | U3: 482 | V3: 490 | W3: 499 | X3: 507 | Y3: 516 | Z3: 525 | AA3: 533 | AB3: 543 | AC3: 551 | AD3: 559 | AE3: 568 | AF3: 576 | AG3: 586 | AH3: 594 | AI3: 602 | AJ3: 611 | AK3: 620 | AL3: 629 | AM3: 637 | AN3: 645 | AO3: 655 | AP3: 663 | AQ3: 672 | AR3: 680 | AS3: 689 | AT3: 698 | AU3: 706 | AV3: 715
A4: 500 | B4: 325 | C4: 335 | D4: 343 | E4: 351 | F4: 361 | G4: 369 | H4: 378 | I4: 386 | J4: 394 | K4: 404 | L4: 412 | M4: 421 | N4: 429 | O4: 438 | P4: 447 | Q4: 455 | R4: 464 | S4: 473 | T4: 481 | U4: 490 | V4: 498 | W4: 508 | X4: 516 | Y4: 524 | Z4: 533 | AA4: 542 | AB4: 551 | AC4: 559 | AD4: 567 | AE4: 577 | AF4: 585 | AG4: 594 | AH4: 602 | AI4: 611 | AJ4: 620 | AK4: 628 | AL4: 637 | AM4: 646 | AN4: 654 | AO4: 663 | AP4: 671 | AQ4: 681 | AR4: 689 | AS4: 697 | AT4: 706 | AU4: 714 | AV4: 724
A5: 600 | B5: 333 | C5: 343 | D5: 351 | E5: 359 | F5: 369 | G5: 377 | H5: 386 | I5: 394 | J5: 403 | K5: 412 | L5: 420 | M5: 429 | N5: 438 | O5: 446 | P5: 455 | Q5: 463 | R5: 473 | S5: 481 | T5: 489 | U5: 498 | V5: 507 | W5: 516 | X5: 524 | Y5: 532 | Z5: 542 | AA5: 550 | AB5: 559 | AC5: 567 | AD5: 576 | AE5: 585 | AF5: 593 | AG5: 602 | AH5: 611 | AI5: 619 | AJ5: 628 | AK5: 636 | AL5: 646 | AM5: 654 | AN5: 662 | AO5: 671 | AP5: 679 | AQ5: 689 | AR5: 697 | AS5: 705 | AT5: 714 | AU5: 723 | AV5: 732
A6: 700 | B6: 341 | C6: 351 | D6: 359 | E6: 368 | F6: 377 | G6: 385 | H6: 394 | I6: 403 | J6: 411 | K6: 420 | L6: 428 | M6: 438 | N6: 446 | O6: 454 | P6: 463 | Q6: 472 | R6: 481 | S6: 489 | T6: 497 | U6: 507 | V6: 515 | W6: 524 | X6: 532 | Y6: 541 | Z6: 550 | AA6: 558 | AB6: 567 | AC6: 576 | AD6: 584 | AE6: 593 | AF6: 601 | AG6: 611 | AH6: 619 | AI6: 627 | AJ6: 636 | AK6: 644 | AL6: 654 | AM6: 662 | AN6: 670 | AO6: 679 | AP6: 688 | AQ6: 697 | AR6: 705 | AS6: 713 | AT6: 723 | AU6: 731 | AV6: 740
A7: 800 | B7: 350 | C7: 359 | D7: 368 | E7: 376 | F7: 385 | G7: 393 | H7: 403 | I7: 411 | J7: 419 | K7: 428 | L7: 437 | M7: 446 | N7: 454 | O7: 462 | P7: 472 | Q7: 480 | R7: 489 | S7: 497 | T7: 506 | U7: 515 | V7: 523 | W7: 532 | X7: 541 | Y7: 549 | Z7: 558 | AA7: 566 | AB7: 576 | AC7: 584 | AD7: 592 | AE7: 601 | AF7: 609 | AG7: 619 | AH7: 627 | AI7: 635 | AJ7: 644 | AK7: 653 | AL7: 662 | AM7: 670 | AN7: 678 | AO7: 688 | AP7: 696 | AQ7: 705 | AR7: 713 | AS7: 722 | AT7: 731 | AU7: 739 | AV7: 748
A8: 900 | B8: 358 | C8: 368 | D8: 376 | E8: 384 | F8: 393 | G8: 402 | H8: 411 | I8: 419 | J8: 427 | K8: 437 | L8: 445 | M8: 454 | N8: 462 | O8: 471 | P8: 480 | Q8: 488 | R8: 497 | S8: 506 | T8: 514 | U8: 523 | V8: 531 | W8: 541 | X8: 549 | Y8: 557 | Z8: 566 | AA8: 574 | AB8: 584 | AC8: 592 | AD8: 600 | AE8: 609 | AF8: 618 | AG8: 627 | AH8: 635 | AI8: 643 | AJ8: 653 | AK8: 661 | AL8: 670 | AM8: 678 | AN8: 687 | AO8: 696 | AP8: 704 | AQ8: 713 | AR8: 722 | AS8: 730 | AT8: 739 | AU8: 747 | AV8: 757
A9: 1000 | B9: 366 | C9: 376 | D9: 384 | E9: 392 | F9: 402 | G9: 410 | H9: 419 | I9: 427 | J9: 436 | K9: 445 | L9: 453 | M9: 462 | N9: 471 | O9: 479 | P9: 488 | Q9: 496 | R9: 506 | S9: 514 | T9: 522 | U9: 531 | V9: 540 | W9: 549 | X9: 557 | Y9: 565 | Z9: 575 | AA9: 583 | AB9: 592 | AC9: 600 | AD9: 608 | AE9: 618 | AF9: 626 | AG9: 635 | AH9: 643 | AI9: 652 | AJ9: 661 | AK9: 669 | AL9: 678 | AM9: 687 | AN9: 695 | AO9: 704 | AP9: 712 | AQ9: 722 | AR9: 730 | AS9: 738 | AT9: 747 | AU9: 756 | AV9: 765
A10: 1100 | B10: 374 | C10: 384 | D10: 392 | E10: 401 | F10: 410 | G10: 418 | H10: 427 | I10: 436 | J10: 444 | K10: 453 | L10: 461 | M10: 471 | N10: 479 | O10: 487 | P10: 496 | Q10: 504 | R10: 514 | S10: 522 | T10: 530 | U10: 539 | V10: 548 | W10: 557 | X10: 565 | Y10: 573 | Z10: 583 | AA10: 591 | AB10: 600 | AC10: 608 | AD10: 617 | AE10: 626 | AF10: 634 | AG10: 643 | AH10: 652 | AI10: 660 | AJ10: 669 | AK10: 677 | AL10: 687 | AM10: 695 | AN10: 703 | AO10: 712 | AP10: 721 | AQ10: 730 | AR10: 738 | AS10: 746 | AT10: 756 | AU10: 764 | AV10: 773
A11: 1200 | B11: 383 | C11: 392 | D11: 401 | E11: 409 | F11: 418 | G11: 426 | H11: 436 | I11: 444 | J11: 452 | K11: 461 | L11: 469 | M11: 479 | N11: 487 | O11: 495 | P11: 504 | Q11: 513 | R11: 522 | S11: 530 | T11: 538 | U11: 548 | V11: 556 | W11: 565 | X11: 573 | Y11: 582 | Z11: 591 | AA11: 599 | AB11: 608 | AC11: 617 | AD11: 625 | AE11: 634 | AF11: 642 | AG11: 652 | AH11: 660 | AI11: 668 | AJ11: 677 | AK11: 686 | AL11: 695 | AM11: 703 | AN11: 711 | AO11: 721 | AP11: 729 | AQ11: 738 | AR11: 746 | AS11: 755 | AT11: 764 | AU11: 772 | AV11: 781
A12: 1300 | B12: 391 | C12: 401 | D12: 409 | E12: 417 | F12: 426 | G12: 434 | H12: 444 | I12: 452 | J12: 460 | K12: 469 | L12: 478 | M12: 487 | N12: 495 | O12: 503 | P12: 513 | Q12: 521 | R12: 530 | S12: 538 | T12: 547 | U12: 556 | V12: 564 | W12: 573 | X12: 582 | Y12: 590 | Z12: 599 | AA12: 607 | AB12: 617 | AC12: 625 | AD12: 633 | AE12: 642 | AF12: 651 | AG12: 660 | AH12: 668 | AI12: 676 | AJ12: 686 | AK12: 694 | AL12: 703 | AM12: 711 | AN12: 719 | AO12: 729 | AP12: 737 | AQ12: 746 | AR12: 755 | AS12: 763 | AT12: 772 | AU12: 780 | AV12: 789
A13: 1400 | B13: 399 | C13: 409 | D13: 417 | E13: 425 | F13: 435 | G13: 443 | H13: 452 | I13: 460 | J13: 468 | K13: 478 | L13: 486 | M13: 495 | N13: 503 | O13: 512 | P13: 521 | Q13: 529 | R13: 538 | S13: 547 | T13: 555 | U13: 564 | V13: 572 | W13: 582 | X13: 590 | Y13: 598 | Z13: 607 | AA13: 616 | AB13: 625 | AC13: 633 | AD13: 641 | AE13: 651 | AF13: 659 | AG13: 668 | AH13: 676 | AI13: 685 | AJ13: 694 | AK13: 702 | AL13: 711 | AM13: 720 | AN13: 728 | AO13: 737 | AP13: 745 | AQ13: 755 | AR13: 763 | AS13: 771 | AT13: 780 | AU13: 788 | AV13: 798
A14: 1500 | B14: 407 | C14: 417 | D14: 425 | E14: 434 | F14: 443 | G14: 451 | H14: 460 | I14: 468 | J14: 477 | K14: 486 | L14: 494 | M14: 503 | N14: 512 | O14: 520 | P14: 529 | Q14: 537 | R14: 547 | S14: 555 | T14: 563 | U14: 572 | V14: 581 | W14: 590 | X14: 598 | Y14: 606 | Z14: 616 | AA14: 624 | AB14: 633 | AC14: 641 | AD14: 650 | AE14: 659 | AF14: 667 | AG14: 676 | AH14: 685 | AI14: 693 | AJ14: 702 | AK14: 710 | AL14: 720 | AM14: 728 | AN14: 736 | AO14: 745 | AP14: 753 | AQ14: 763 | AR14: 771 | AS14: 779 | AT14: 788 | AU14: 797 | AV14: 806
... A22: 2300 | B22: 473 | C22: 483 | D22: 491 | E22: 499 | F22: 508 | G22: 517 | H22: 526 | I22: 534 | J22: 542 | K22: 552 | L22: 560 | M22: 569 | N22: 577 | O22: 586 | P22: 595 | Q22: 603 | R22: 612 | S22: 621 | T22: 629 | U22: 638 | V22: 646 | W22: 656 | X22: 664 | Y22: 672 | Z22: 681 | AA22: 690 | AB22: 699 | AC22: 707 | AD22: 715 | AE22: 725 | AF22: 733 | AG22: 742 | AH22: 750 | AI22: 759 | AJ22: 768 | AK22: 776 | AL22: 785 | AM22: 794 | AN22: 802 | AO22: 811 | AP22: 819 | AQ22: 828 | AR22: 837 | AS22: 845 | AT22: 854 | AU22: 862 | AV22: 872

Sheet rooflight
A1: type | B1: matrix | C1: rooflight_
B2: 600 | C2: 700 | D2: 800 | E2: 900 | F2: 1000 | G2: 1100 | H2: 1200 | I2: 1300 | J2: 1400 | K2: 1500 | L2: 1600 | M2: 1700 | N2: 1800 | O2: 1900 | P2: 2000 | Q2: 2100 | R2: 2200 | S2: 2300 | T2: 2400 | U2: 2500 | V2: 2600 | W2: 2700 | X2: 2800 | Y2: 2900 | Z2: 3000 | AA2: 3100 | AB2: 3200
A3: 600 | B3: 259.3 | C3: 288 | D3: 316.29 | E3: 342 | F3: 370.29 | G3: 398.57 | H3: 424.29 | I3: 452.57 | J3: 480.86 | K3: 506.57 | L3: 534.86 | M3: 560.57 | N3: 588.86 | O3: 617.14 | P3: 645.43 | Q3: 671.14 | R3: 699.43 | S3: 727.71 | T3: 753.43 | U3: 781.71 | V3: 807.43 | W3: 835.71 | X3: 864 | Y3: 889.71 | Z3: 918 | AA3: 946.29 | AB3: 972
A4: 700 | B4: 288 | C4: 318.86 | D4: 349.71 | E4: 380.57 | F4: 411.43 | G4: 439.71 | H4: 470.57 | I4: 501.43 | J4: 532.29 | K4: 563.14 | L4: 591.43 | M4: 622.29 | N4: 653.14 | O4: 684 | P4: 714.86 | Q4: 745.71 | R4: 774 | S4: 804.86 | T4: 835.71 | U4: 866.57 | V4: 897.43 | W4: 928.29 | X4: 959.14 | Y4: 1018.29 | Z4: 1018.29 | AA4: 1049.14 | AB4: 1080
A5: 800 | B5: 316.29 | C5: 349.71 | D5: 383.14 | E5: 416.57 | F5: 450 | G5: 483.43 | H5: 516.86 | I5: 550.29 | J5: 583.71 | K5: 617.14 | L5: 650.57 | M5: 684 | N5: 717.43 | O5: 750.86 | P5: 786.86 | Q5: 820.29 | R5: 851.14 | S5: 887.14 | T5: 920.57 | U5: 954 | V5: 987.43 | W5: 1020.86 | X5: 1054.29 | Y5: 1121.14 | Z5: 1121.14 | AA5: 1154.57 | AB5: 1188
A6: 900 | B6: 342 | C6: 380.57 | D6: 416.57 | E6: 452.57 | F6: 491.14 | G6: 527.14 | H6: 563.14 | I6: 599.14 | J6: 635.14 | K6: 673.71 | L6: 709.71 | M6: 745.71 | N6: 781.71 | O6: 817.71 | P6: 856.29 | Q6: 892.29 | R6: 928.29 | S6: 966.86 | T6: 1002.86 | U6: 1038.86 | V6: 1074.86 | W6: 1110.86 | X6: 1149.43 | Y6: 1221.43 | Z6: 1221.43 | AA6: 1257.43 | AB6: 1296
A7: 1000 | B7: 370.29 | C7: 411.43 | D7: 450 | E7: 491.14 | F7: 529.71 | G7: 568.29 | H7: 609.43 | I7: 648 | J7: 689.14 | K7: 727.71 | L7: 768.86 | M7: 807.43 | N7: 848.57 | O7: 887.14 | P7: 928.29 | Q7: 966.86 | R7: 1005.43 | S7: 1046.57 | T7: 1085.14 | U7: 1126.29 | V7: 1164.86 | W7: 1203.43 | X7: 1244.57 | Y7: 1324.29 | Z7: 1324.29 | AA7: 1362.86 | AB7: 1404
A8: 1100 | B8: 398.57 | C8: 439.71 | D8: 483.43 | E8: 527.14 | F8: 568.29 | G8: 612 | H8: 653.14 | I8: 696.86 | J8: 740.57 | K8: 784.29 | L8: 825.43 | M8: 869.14 | N8: 912.86 | O8: 954 | P8: 997.71 | Q8: 1038.86 | R8: 1082.57 | S8: 1126.29 | T8: 1167.43 | U8: 1211.14 | V8: 1254.86 | W8: 1296 | X8: 1339.71 | Y8: 1424.57 | Z8: 1424.57 | AA8: 1468.29 | AB8: 1509.43
A9: 1200 | B9: 424.29 | C9: 470.57 | D9: 516.86 | E9: 563.14 | F9: 609.43 | G9: 653.14 | H9: 699.43 | I9: 745.71 | J9: 792 | K9: 838.29 | L9: 884.57 | M9: 928.29 | N9: 974.57 | O9: 1020.86 | P9: 1067.14 | Q9: 1113.43 | R9: 1159.71 | S9: 1206 | T9: 1249.71 | U9: 1296 | V9: 1342.29 | W9: 1388.57 | X9: 1434.86 | Y9: 1527.43 | Z9: 1527.43 | AA9: 1571.14 | AB9: 1617.43
A10: 1300 | B10: 542.57 | C10: 594 | D10: 648 | E10: 699.43 | F10: 753.43 | G10: 804.86 | H10: 856.29 | I10: 910.29 | J10: 964.29 | K10: 1015.71 | L10: 1069.71 | M10: 1121.14 | N10: 1175.14 | O10: 1226.57 | P10: 1280.57 | Q10: 1332 | R10: 1386 | S10: 1437.43 | T10: 1491.43 | U10: 1542.86 | V10: 1596.86 | W10: 1648.29 | X10: 1702.29 | Y10: 1753.71 | Z10: 1807.71 | AA10: 1859.14 | AB10: 1913.14
A11: 1400 | B11: 573.43 | C11: 627.43 | D11: 684 | E11: 740.57 | F11: 797.14 | G11: 851.14 | H11: 907.71 | I11: 964.29 | J11: 1018.29 | K11: 1074.86 | L11: 1131.43 | M11: 1185.43 | N11: 1242 | O11: 1298.57 | P11: 1355.14 | Q11: 1409.14 | R11: 1465.71 | S11: 1522.29 | T11: 1576.29 | U11: 1632.86 | V11: 1689.43 | W11: 1743.43 | X11: 1800 | Y11: 1856.57 | Z11: 1913.14 | AA11: 1967.14 | AB11: 2023.71
A12: 1500 | B12: 604.29 | C12: 663.43 | D12: 722.57 | E12: 781.71 | F12: 840.86 | G12: 897.43 | H12: 956.57 | I12: 1015.71 | J12: 1074.86 | K12: 1134 | L12: 1193.14 | M12: 1252.29 | N12: 1311.43 | O12: 1370.57 | P12: 1429.71 | Q12: 1486.29 | R12: 1545.43 | S12: 1604.57 | T12: 1663.71 | U12: 1722.86 | V12: 1782 | W12: 1841.14 | X12: 1900.29 | Y12: 1959.43 | Z12: 2018.57 | AA12: 2075.14 | AB12: 2134.29
A13: 1600 | B13: 635.14 | C13: 696.86 | D13: 758.57 | E13: 820.29 | F13: 882 | G13: 943.71 | H13: 1005.43 | I13: 1069.71 | J13: 1131.43 | K13: 1131.43 | L13: 1254.86 | M13: 1316.57 | N13: 1378.29 | O13: 1440 | P13: 1501.71 | Q13: 1563.43 | R13: 1625.14 | S13: 1689.43 | T13: 1782 | U13: 1812.86 | V13: 1874.57 | W13: 1936.29 | X13: 1998 | Y13: 2059.71 | Z13: 2121.43 | AA13: 2183.14 | AB13: 2244.86
A14: 1700 | B14: 666 | C14: 730.29 | D14: 794.57 | E14: 861.43 | F14: 925.71 | G14: 990 | H14: 1054.29 | I14: 1121.14 | J14: 1185.43 | K14: 1185.43 | L14: 1316.57 | M14: 1380.86 | N14: 1445.14 | O14: 1512 | P14: 1576.29 | Q14: 1640.57 | R14: 1704.86 | S14: 1771.71 | T14: 1836 | U14: 1902.86 | V14: 1967.14 | W14: 2031.43 | X14: 2098.29 | Y14: 2162.57 | Z14: 2226.86 | AA14: 2291.14 | AB14: 2355.43
... A17: 2000 | B17: 758.57 | C17: 833.14 | D17: 907.71 | E17: 982.29 | F17: 1056.86 | G17: 1131.43 | H17: 1206 | I17: 1280.57 | J17: 1355.14 | K17: 1355.14 | L17: 1501.71 | M17: 1576.29 | N17: 1650.86 | O17: 1725.43 | P17: 1800 | Q17: 1874.57 | R17: 1949.14 | S17: 2023.71 | T17: 2098.29 | U17: 2172.86 | V17: 2244.86 | W17: 2319.43 | X17: 2394 | Y17: 2468.57 | Z17: 2543.14 | AA17: 2617.71 | AB17: 2692.29

Sheet lantern
A1: type | B1: matrix | C1: lantern_
B2: 800 | C2: 900 | D2: 1000 | E2: 1100 | F2: 1200 | G2: 1300 | H2: 1400 | I2: 1500 | J2: 1600 | K2: 1700 | L2: 1800 | M2: 1900 | N2: 2000 | O2: 2100 | P2: 2200 | Q2: 2300 | R2: 2400 | S2: 2500 | T2: 2600 | U2: 2700 | V2: 2800 | W2: 2900 | X2: 3000
A3: 600 | B3: 522.81 | C3: 539.02 | D3: 555.57 | E3: 571.78 | F3: 587.99 | G3: 604.53 | H3: 620.74 | I3: 636.95 | J3: 653.49 | K3: 669.7 | L3: 685.24 | M3: 702.46 | N3: 718.67 | O3: 734.87 | P3: 751.42 | Q3: 767.61 | R3: 783.82 | S3: 800.37 | T3: 816.58 | U3: 832.79 | V3: 849.33 | W3: 865.54 | X3: 881.75
A4: 700 | B4: 544.27 | C4: 561.36 | D4: 579.68 | E4: 596.77 | F4: 613.86 | G4: 631.29 | H4: 648.39 | I4: 665.48 | J4: 682.91 | K4: 700 | L4: 717.1 | M4: 734.53 | N4: 751.62 | O4: 768.7 | P4: 786.13 | Q4: 803.22 | R4: 821.2 | S4: 838.63 | T4: 855.72 | U4: 872.82 | V4: 890.25 | W4: 907.34 | X4: 924.43
A5: 800 | B5: 512.18 | C5: 584.25 | D5: 602.57 | E5: 620.54 | F5: 638.52 | G5: 656.84 | H5: 674.81 | I5: 693.68 | J5: 711.99 | K5: 729.97 | L5: 747.93 | M5: 766.25 | N5: 784.22 | O5: 803.09 | P5: 821.4 | Q5: 839.38 | R5: 857.36 | S5: 875.67 | T5: 894.53 | U5: 912.51 | V5: 930.83 | W5: 948.8 | X5: 966.78
A6: 900 | C6: 553.05 | D6: 625.46 | E6: 644.32 | F6: 664.07 | G6: 683.26 | H6: 702.13 | I6: 720.99 | J6: 741.06 | K6: 759.92 | L6: 778.78 | M6: 797.98 | N6: 817.73 | O6: 836.59 | P6: 855.79 | Q6: 875.54 | R6: 894.4 | S6: 914.99 | T6: 932.98 | U6: 952.21 | V6: 971.4 | W6: 990.27 | X6: 1010.01
A7: 1000 | D7: 595.47 | E7: 669.31 | F7: 689.06 | G7: 709.13 | H7: 729.76 | I7: 749.51 | J7: 769.59 | K7: 790.22 | L7: 809.97 | M7: 830.93 | N7: 850.68 | O7: 870.43 | P7: 891.4 | Q7: 911.14 | R7: 931.77 | S7: 951.86 | T7: 971.6 | U7: 992.24 | V7: 1012.32 | W7: 1032.07 | X7: 1052.7
A8: 1100 | E8: 639.88 | F8: 713.7 | G8: 735.55 | H8: 756.19 | I8: 778.15 | J8: 798.67 | K8: 820.19 | L8: 841.56 | M8: 862.67 | N8: 883.3 | O8: 904.82 | P8: 925.78 | Q8: 947.3 | R8: 967.93 | S8: 989.78 | T8: 1010.41 | U8: 1032.08 | V8: 1052.9 | W8: 1074.41 | X8: 1095.05
A9: 1200 | F9: 686.05 | G9: 761.1 | H9: 783.5 | I9: 805.9 | J9: 827.75 | K9: 850.15 | L9: 871.67 | M9: 894.4 | N9: 916.8 | O9: 938.32 | P9: 961.06 | Q9: 982.57 | R9: 1004.97 | S9: 1026.82 | T9: 1049.22 | U9: 1071.63 | V9: 1093.48 | W9: 1115.86 | X9: 1137.38
A10: 1300 | G10: 734.67 | H10: 811.15 | I10: 833.55 | J10: 857.17 | K10: 880.45 | L10: 902.85 | M10: 926.47 | N10: 949.76 | O10: 972.16 | P10: 995.78 | Q10: 1019.06 | R10: 1042.35 | S10: 1065.08 | T10: 1088.36 | U10: 1111.64 | V10: 1134.38 | W10: 1157.66 | X10: 1180.95
A11: 1400 | H11: 784.36 | I11: 861.74 | J11: 886.25 | K11: 910.42 | L11: 933.7 | M11: 958.21 | N11: 982.38 | O11: 1006.55 | P11: 1031.05 | Q11: 1054.34 | R11: 1078.49 | S11: 1103 | T11: 1127.17 | U11: 1151.34 | V11: 1174.96 | W11: 1199.13 | X11: 1223.3
A12: 1500 | I12: 836.73 | J12: 915.33 | K12: 956.3 | L12: 964.55 | M12: 957.44 | N12: 1015 | O12: 1040.04 | P12: 1065.42 | Q12: 1090.48 | R12: 1115.53 | S12: 1140.92 | T12: 1165.98 | U12: 1191.03 | V12: 1216.08 | W12: 1240.59 | X12: 1265.64
A13: 1600 | J13: 891.54 | K13: 970.68 | L13: 996.62 | M13: 1022.88 | N13: 1048.82 | O13: 1074.76 | P13: 1101.03 | Q13: 1126.97 | R13: 1152.91 | S13: 1179.18 | T13: 1205.12 | U13: 1231.31 | V13: 1257.33 | W13: 1283.27 | X13: 1309.21
A14: 1700 | K14: 947.44 | L14: 1027.46 | M14: 1054.62 | N14: 1081.44 | O14: 1108.26 | P14: 1135.42 | Q14: 1162.24 | R14: 1189.07 | S14: 1216.22 | T14: 1243.05 | U14: 1270.76 | V14: 1297.91 | W14: 1324.74 | X14: 1351.56
A15: 1800 | L15: 1005.11 | M15: 1086.35 | N15: 1114.06 | O15: 1141.76 | P15: 1169.81 | Q15: 1198.4 | R15: 1226.11 | S15: 1254.15 | T15: 1281.86 | U15: 1310.45 | V15: 1338.49 | W15: 1366.2 | X15: 1393.91
A16: 1900 | M16: 1065.22 | N16: 1147.01 | O16: 1176.49 | P16: 1205.42 | Q16: 1234.01 | R16: 1263.48 | S16: 1292.41 | T16: 1321 | U16: 1350.48 | V16: 1379.41 | W16: 1408 | X16: 1436.59
A17: 2000 | N17: 1127.31 | O17: 1209.99 | P17: 1239.8 | Q17: 1270.16 | R17: 1299.64 | S17: 1330.34 | T17: 1359.81 | U17: 1389.29 | V17: 1419.99 | W17: 1449.45 | X17: 1479.81
A18: 2100 | O18: 1190.29 | P18: 1275.08 | Q18: 1305.44 | R18: 1339.47 | S18: 1367.38 | T18: 1398.62 | U18: 1428.97 | V18: 1460.55 | W18: 1697.93 | X18: 1734.99
A19: 2200 | P19: 1256.59 | Q19: 1341.93 | R19: 1374.04 | S19: 1405.62 | T19: 1437.75 | U19: 1469 | V19: 1501.47 | W19: 1748.94 | X19: 1787.17
A20: 2300 | Q20: 1324.88 | R20: 1410.2 | S20: 1443.55 | T20: 1476.56 | U20: 1508.69 | V20: 1542.04 | W20: 1799.62 | X20: 1840.18
A21: 2400 | R21: 1394.05 | S21: 1481.48 | T21: 1515.38 | U21: 1548.39 | V21: 1582.62 | W21: 1850.31 | X21: 1892.03

Sheet internal
A1: type | B1: values | D1: base cost
A2: internal_single_door | B2: =D2*(1+MARKUP!$Z$8) -> 336.3399 | D2: 393.38
A3: internal_french_door | B3: =D3*(1+MARKUP!$Z$8) -> 691.524 | D3: 808.8
A4: internal_single_lockbox | B4: =D4*(1+MARKUP!$Z$8) -> 134.80785 | D4: 157.67
A5: internal_french_lockbox | B5: =D5*(1+MARKUP!$Z$8) -> 183.1581 | D5: 214.22
A6: internal_sidelight | B6: =D6*(1+MARKUP!$Z$8) -> 222.8301 | D6: 260.62
A7: internal_toplight | B7: =D7*(1+MARKUP!$Z$8) -> 126.3177 | D7: 147.74
A8: internal_patio_barn_one | B8: =D8*(1+MARKUP!$Z$9) -> 355.6629 | D8: 415.98
A9: internal_patio_barn_two | B9: =D9*(1+MARKUP!$Z$9) -> 704.4345 | D9: 823.9
A10: internal_patio_two | B10: =D10*(1+MARKUP!$Z$9) -> 554.7411 | D10: 648.82
A11: internal_patio_four | B11: =D11*(1+MARKUP!$Z$9) -> 1023.08445 | D11: 1196.59
A12: internal_glass_clear_sqm | B12: 50
A13: internal_glass_obscured_sqm | B13: 60

Sheet cutoffs
A1: type | B1: cutoffs
A2: glassWidthAndHeight6mmWidth | B2: 1400 | C2: 6mm requires both width and height
A3: glassWidthAndHeight6mmHeight | B3: 1400
A4: glassWidthOversized | B4: 2500 | C4: oversized requires width or height or sqm
A5: glassHeightOversized | B5: 2500
A6: glassSqmOversized | B6: 2.5

Sheet options
A1: type | B1: options
A2: hasDisabledToeHeelAdjuster | B2: 1
A3: hasDisabledLiftAndSlide | B3: 0
A4: hasDisabledAdjustableJamb | B4: 0
A5: hasDisabledCornerPost | B5: 1
A6: hasDisabledFloatingCorner | B6: 1
A7: hasDisabledBifoldExternalHandle | B7: 0
A8: hasDisabledBifoldHandle_steel | B8: 0
A9: hasDisabledBifoldHandle_rose_gold | B9: 1 | C9: Works with any handle code in the form `hasDisabledBifoldHandle_{handle}`
A10: NameOfWindowHandle_steel | B10: Satin
A11: hasDisabledSidelights | B11: 0
A12: hasEnabledCillHorns | B12: 0
A13: hasEnabledDoorCylinder | B13: 0
A14: doorCylinderName | C14: Override the door cylinder name when enabled
A15: hasDisabledVentInBifoldFrame | B15: 1
A16: hasDisabledVentInBifoldSashes | B16: 0
A17: hasDisabledVentInPatioFrame | B17: 1
A18: hasEnabledVentInPatioSashes | B18: 0
A19: hasDisabledHoodedVent | B19: 1
A20: hasEnabledPatioFMFStyles | B20: 0
A21: hasDisabledUntoughenedGlass | B21: 0
A22: hasDisabledGlassForInternalOrders | B22: 0
A23: hasEnabledAstragalInUnglazed | B23: 0
A24: hasDisabledMonorail | B24: 1
A25: hasDisabledTransom | B25: 0
A26: enabledObscuredPatterns | C26: Requires / separated glass codes, please ask technical
A27: disabledGlassOptions | C27: Requires / separated glass codes, please ask technical
A28: partsStrategy | B28: ultra | C28: Used to add the extra price for bifold low e glass key
A29: sqmSkuThresholds | C29: Requires / separated thresholds, Will emit skus of the form `glass_over_${threshold}_fixed`
A30: enabledPatioHandles | B30: white/black/gold/chrome/satin/coastal_black/coastal_steel | C30: Requires / separated handle codes, please ask technical
A31: enabledPatioLiftAndSlideHandles | C31: Requires / separated handle codes, please ask technical
A32: enabledBifoldThresholdOptions | B32: standard/low/integrated | C32: Requires / separated threshold codes, please ask technical
A33: enabledWindowAddons | B33: 0/20/38 | C33: Requires / separated addon codes, please ask technical
A34: enabledBifoldCills | B34: 0/90/150/180/230/integrated | C34: Requires / separated cill codes, please ask technical
A35: enabledPatioCills | B35: 0/230/250 | C35: Requires / separated cill codes, please ask technical
A36: enabledWindowCills | B36: 0/90/150/180/230 | C36: Requires / separated cill codes, please ask technical
A37: hasDisabledTiltTurn | B37: 1
A38: hasEnabledVentInWindowSashes | B38: 1
A39: hasForcedInterlock25 | B39: 1
A40: hasDisabledPatioRLRL | B40: 1
A41: hasDisabledWindowInternallyBeaded | B41: 1
A42: hasDisabledPatioTransom | B42: 1
A43: NameOfWindowOpener_F | B43: Fixed (externally beaded)

Sheet toggles
A1: type | B1: toggles
A2: webshopEnabled | B2: 1
A3: hideRetailPriceAfterContact | B3: 0
A4: glassPriceOverrideEnabled | B4: 1
A5: aluminiumMarkupsByProductEnabled | B5: 0
A6: disableRequestedDeliveryDate | B6: 0
A7: allowPayments | B7: 0
A8: showWatermark | B8: 0
A9: shouldShowGlassSizes | B9: 0
A10: retailDiscountCodesEnabled | B10: 0 | C10: Should not be enabled until clients discount codes have been implemented
A11: systemDeliveryEnabled | B11: 0 | C11: Should not be enabled until clients delivery logic has been implemented
A12: disabledSalesHubs | C12: Requires / separated customer IDs
A13: footerText | B13: QUOTATION TERMS AND CONDITIONS We are pleased to supply an estimate as detailed. This quote is only valid for 30 days, thereafter prices may be subject to change. Please be aware, unless otherwise specified, we have processed your order on the basis that: • All drawings are viewed from outside. Bay measurements are given from inside. Aluminium baypoles are not load bearing. • All window opening lights and dummy sashes to be internally beaded. • All sizes are finished frame sizes, inclusive of any frame extensions such as subcills and add-ons. We do not make allowances for tolerance, sunken frames or any other fitting details. • Unless you have specified 'no cill' or a particular subcill on your order, we will allow 150mm subcills (or the default subcill/drainage base for the system) as standard. • All subcills are cut to the exact frame width unless stated otherwise. Subcill depth may vary by +/- 10mm based on the extruder used. The subcill extruder/brand will be chosen by Ultra Windows & Bifold LTD to best suit with the products ordered. • All cill end caps can come in either black, grey or white. Grey cills come with either black or grey end caps depending on availability. • Astragal bars are supplied in full lengths. • Frames longer than 3000mm in any dimension may be coupled. Cills over 3000mm may be split and supplied with joiners. • Shaped windows can be manufactured in-house and they will not be covered by guarantee and our visual standards will not apply. • Lead times will be confirmed at the point of order. Special RAL coloured frames have an extended lead time. • All glass is supplied to GGF visual standards. No higher specification than this should be assumed. Please note: All lead times given are estimates only based on the best information available at the time. Although we will endeavor to meet the specified date, Ultra Windows & Bifold LTD will not be liable for any direct or consequential loss resulting from delays. Collection / Delivery: • Deliveries are subject to availability and require a minimum of 2 days' notice. • Collections must be arranged in advance and will only be handled at the allocated timeslot. • Delivery and collection requests are to be made through email only sales@ultrawindows.co.uk • All outstanding payments must be made with cleared funds two working days before the stated delivery/collection date. • Specific times for delivery cannot be guaranteed. • Customers are required to make suitable arrangements to ensure capacity is present to receive goods. Customers are also to ensure that all delivery addresses are correct at the time of booking. • Goods must be inspected and any defects reported via email within 24hours of receipt. Ultra Windows & Bifold LTD will not accept any liability for any claims made outside of this time period. • Glass units for beaded products will be supplied separately to be glazed on site. • Deliveries outside of a 100 mile radius may be subject to an additional surcharge If you would like to proceed with this quote as an order, please check that the specifications, sizes and designs meet your requirements. Please confirm by signing the section at the bottom of this page and returning this back to us along with a deposit for 50% of the total job value. Goods do not belong to you until paid for in full. We reserve the right to remove all unpaid items. Please note that no orders will be processed until a deposit has been received, unless agreed in advance, in writing. The full outstanding amount must be paid by cleared funds two working days before delivery or collection can take place. Card payments can be made to the office during working hours (Monday-Friday 9am-5pm) or can be made through BACS transaction (confirmation of this must be sent to the office). Bank details- Natwest Sort Code: 60-07-25 Account No: 53004353 Should you require any further assistance, please do not hesitate to contact our team. Ultra Windows & Bifold LTD. Vat No: 487455345 Company Reg: 16286735 I would like to proceed with this quotation as an order, and I confirm I have checked that the above designs, sizes and specifications are to my Satisfaction. Name:___________ Signed:___________ Date: ____________
